Workbook

Sheet Instrucciones iniciales
B2: Pasos Iniciales:
B4: • Para pooder usar está calculadora, deberás hacer una copia de este archivo, para eso ve a la parte superior izquierda donde dice
B5: Archivo o Files, da click y se va a desplegar una pestaña, luego ve donde dice Crear una copia o Make a copy.
B14: • Luego te saldrá la ventana emergente que encuentras abajo para que le pongas el nombre que tu quieras y elijas en que lugar
B15: de tu Google Drive lo quieres guardar.
B37: • NOTA: Este archivo esta creado para usarse en Google Drive, puedes descargar su versión en Excel pero no se garantiza que las
B38: formúlas funcionen igual.

Sheet Hoja de Datos
B2: Cómo usar (Hoja de Datos)
B3: • Selecciona la MONEDA en la celda C7 en la que llevas tus finanzas.
B4: • Los datos de las columnas B, C, D y E los puedes modificar de acuerdo a tus necesidades, puedes dejar unicamente los nombres de los
B5: pilares, inversión, entidades y monedas que hagan parte de tu plan financiero.
B7: Selecciona tú moneda: | C7: COP
B9: Pilar | C9: Nombre Inversión | D9: Entidades o Empresas | E9: Monedas
B10: Fondo de Imprevistos | C10: Fondo de Imprevistos | D10: Skandia | E10: USD
B11: Reserva de Oxigeno | C11: Reserva de Oxigeno | D11: BBVA | E11: COP
B12: Cuenta de Retiro | C12: Arch Finance | D12: Bancolombia | E12: USD
B13: Cuenta de Inversiones | C13: Crea Patrimonio | D13: NU | E13: EUR
B14: Objetivo 1 (Reemplaza el nombre) | C14: Evo 10 | D14: ITA | E14: JPY
B15: Objetivo 2 (Reemplaza el nombre) | C15: Trinity 15 años | D15: Trinity | E15: GBP
B16: Objetivo 3 (Reemplaza el nombre) | C16: Global66 Dolares | D16: Interactive Brokers | E16: CHF
B17: Objetivo 4 (Reemplaza el nombre) | C17: Apto de la 97 Gallery | D17: Banco de Bogotá | E17: CAD
B18: Objetivo 5 (Reemplaza el nombre) | C18: VOO | D18: Davivienda | E18: AUD
B19: Objetivo 6 (Reemplaza el nombre) | C19: Inversión 2 | D19: BBVA Colombia | E19: NZD
B20: Objetivo 7 (Reemplaza el nombre) | C20: Inversión 3 | D20: Scotiabank Colpatria | E20: CNY
C21: Inversión... | D21: Banco de Occidente | E21: HKD
D22: Banco Agrario | E22: SGD
D23: Banco Popular | E23: KRW
D24: Banco AV Villas | E24: SEK
D25: Banco Caja Social | E25: NOK
D26: Itaú Colombia | E26: DKK
D27: Banco GNB Sudameris | E27: MXN
D28: Banco Falabella | E28: CLP
D29: Banco Finandina | E29: ARS
D30: Citibank Colombia | E30: PEN
D31: Banco W | E31: COP
D32: Coopcentral | E32: BRL
D33: Fiduciaria Bancolombia | E33: UYU
... D50: Fiduoccidente | E50: ILS
D51: Fiducoomeva
D52: Protección
D53: Porvenir
D54: Colfondos
D55: Skandia
D56: Acciones & Valores
D57: Alianza Valores
D58: Valores Bancolombia
D59: Davivienda Corredores
D60: BTG Pactual
D61: BBVA Valores
D62: Casa de Bolsa
... D94: Western Union

Sheet Entradas y salidas
B2: Cómo usar (Entradas y salidas)
B3: • Modifica unicamente las celdas que están en color amarillo.
B4: • No toques las celdas en color verde.
B5: • Si tú inversión es en dólares debes poner el valor que invertiste en tu moneda local en la columna G y el valor
B6: de la TRM en la columna H. Es decir, a que precio estaba el dólar el día que hiciste la inversión.
B8: Pilar | C8: Entidad o Empresa | D8: Inversión | E8: Moneda (USD/COP) | F8: Fecha | G8: Aporte en COP (+) o tú moneda | H8: TRM (COP/USD) o (Tú moneda/USD) | I8: Flujo USD (auto) | J8: Flujo COP (auto) o tú moneda | K8: Flujo COP (auto) o tú moneda en USD | L8: Nota
B9: Fondo de Imprevistos | C9: NU | D9: Fondo de Imprevistos | E9: COP | F9: 45306 | G9: 5000000 | I9: =IFERROR(IF(E9="USD",-(G9/H9),""),"") | J9: =IF(E9='Hoja de Datos'!$C$7,-(G9),"") -> -5000000 | K9: =IF(E9='Hoja de Datos'!$C$7,"", IF(G9="","", -G9)) | L9: aporte 1
B10: Reserva de Oxigeno | C10: Skandia | D10: Reserva de Oxigeno | E10: COP | F10: 45361 | G10: 3000000 | I10: =IFERROR(IF(E10="USD",-(G10/H10),""),"") | J10: =IF(E10='Hoja de Datos'!$C$7,-(G10),"") -> -3000000 | K10: =IF(E10='Hoja de Datos'!$C$7,"", IF(G10="","", -G10)) | L10: aporte 2
B11: Fondo de Imprevistos | C11: Skandia | D11: Reserva de Oxigeno | E11: COP | F11: 45323 | G11: 3000000 | I11: =IFERROR(IF(E11="USD",-(G11/H11),""),"") | J11: =IF(E11='Hoja de Datos'!$C$7,-(G11),"") -> -3000000 | K11: =IF(E11='Hoja de Datos'!$C$7,"", IF(G11="","", -G11)) | L11: aporte 1
B12: Fondo de Imprevistos | C12: Skandia | D12: Reserva de Oxigeno | E12: COP | F12: 45397 | G12: 3000000 | I12: =IFERROR(IF(E12="USD",-(G12/H12),""),"") | J12: =IF(E12='Hoja de Datos'!$C$7,-(G12),"") -> -3000000 | K12: =IF(E12='Hoja de Datos'!$C$7,"", IF(G12="","", -G12)) | L12: aporte 2
B13: Fondo de Imprevistos | C13: Skandia | D13: Reserva de Oxigeno | E13: COP | F13: 45311 | G13: 2000000 | I13: =IFERROR(IF(E13="USD",-(G13/H13),""),"") | J13: =IF(E13='Hoja de Datos'!$C$7,-(G13),"") -> -2000000 | K13: =IF(E13='Hoja de Datos'!$C$7,"", IF(G13="","", -G13)) | L13: aporte 1
B14: Fondo de Imprevistos | C14: Skandia | D14: Reserva de Oxigeno | E14: COP | F14: 45432 | G14: 2000000 | I14: =IFERROR(IF(E14="USD",-(G14/H14),""),"") | J14: =IF(E14='Hoja de Datos'!$C$7,-(G14),"") -> -2000000 | K14: =IF(E14='Hoja de Datos'!$C$7,"", IF(G14="","", -G14)) | L14: aporte 2
B15: Fondo de Imprevistos | C15: Skandia | D15: Reserva de Oxigeno | E15: COP | F15: 45356 | G15: 500000 | I15: =IFERROR(IF(E15="USD",-(G15/H15),""),"") | J15: =IF(E15='Hoja de Datos'!$C$7,-(G15),"") -> -500000 | K15: =IF(E15='Hoja de Datos'!$C$7,"", IF(G15="","", -G15)) | L15: aporte 1
B16: Fondo de Imprevistos | C16: Skandia | D16: Reserva de Oxigeno | E16: COP | F16: 45448 | G16: 500000 | I16: =IFERROR(IF(E16="USD",-(G16/H16),""),"") | J16: =IF(E16='Hoja de Datos'!$C$7,-(G16),"") -> -500000 | K16: =IF(E16='Hoja de Datos'!$C$7,"", IF(G16="","", -G16)) | L16: aporte 2
B17: Fondo de Imprevistos | C17: NU | D17: Fondo de Imprevistos | E17: COP | F17: 45332 | G17: 1000000 | I17: =IFERROR(IF(E17="USD",-(G17/H17),""),"") | J17: =IF(E17='Hoja de Datos'!$C$7,-(G17),"") -> -1000000 | K17: =IF(E17='Hoja de Datos'!$C$7,"", IF(G17="","", -G17)) | L17: aporte COP
B18: Fondo de Imprevistos | C18: NU | D18: Fondo de Imprevistos | E18: COP | F18: 45361 | G18: 300000 | I18: =IFERROR(IF(E18="USD",-(G18/H18),""),"") | J18: =IF(E18='Hoja de Datos'!$C$7,-(G18),"") -> -300000 | K18: =IF(E18='Hoja de Datos'!$C$7,"", IF(G18="","", -G18)) | L18: aporte USD
B19: Cuenta de Inversiones | C19: ITA | D19: Evo 10 | E19: USD | F19: 44848 | G19: 11050000 | H19: 4420 | I19: =IFERROR(IF(E19="USD",-(G19/H19),""),"") -> -2500 | J19: =IF(E19='Hoja de Datos'!$C$7,-(G19),"") | K19: =IF(E19='Hoja de Datos'!$C$7,"", IF(G19="","", -G19)) -> -11050000
B20: Cuenta de Inversiones | C20: ITA | D20: Evo 10 | E20: USD | F20: 45211 | G20: 10897500 | H20: 4359 | I20: =IFERROR(IF(E20="USD",-(G20/H20),""),"") -> -2500 | J20: =IF(E20='Hoja de Datos'!$C$7,-(G20),"") | K20: =IF(E20='Hoja de Datos'!$C$7,"", IF(G20="","", -G20)) -> -10897500
B21: Cuenta de Inversiones | C21: ITA | D21: Evo 10 | E21: USD | F21: 45583 | G21: 10665000 | H21: 4266 | I21: =IFERROR(IF(E21="USD",-(G21/H21),""),"") -> -2500 | J21: =IF(E21='Hoja de Datos'!$C$7,-(G21),"") | K21: =IF(E21='Hoja de Datos'!$C$7,"", IF(G21="","", -G21)) -> -10665000
B22: Cuenta de Inversiones | C22: ITA | D22: Evo 10 | E22: USD | F22: 45944 | G22: 9737500 | H22: 3895 | I22: =IFERROR(IF(E22="USD",-(G22/H22),""),"") -> -2500 | J22: =IF(E22='Hoja de Datos'!$C$7,-(G22),"") | K22: =IF(E22='Hoja de Datos'!$C$7,"", IF(G22="","", -G22)) -> -9737500
B23: Cuenta de Inversiones | C23: Trinity | D23: Trinity 15 años | E23: USD | F23: 44848 | G23: 13260000 | H23: 4420 | I23: =IFERROR(IF(E23="USD",-(G23/H23),""),"") -> -3000 | J23: =IF(E23='Hoja de Datos'!$C$7,-(G23),"") | K23: =IF(E23='Hoja de Datos'!$C$7,"", IF(G23="","", -G23)) -> -13260000
B24: Cuenta de Inversiones | C24: Trinity | D24: Trinity 15 años | E24: USD | F24: 45211 | G24: 13077000 | H24: 4359 | I24: =IFERROR(IF(E24="USD",-(G24/H24),""),"") -> -3000 | J24: =IF(E24='Hoja de Datos'!$C$7,-(G24),"") | K24: =IF(E24='Hoja de Datos'!$C$7,"", IF(G24="","", -G24)) -> -13077000
B25: Cuenta de Inversiones | C25: Interactive Brokers | D25: VOO | E25: USD | F25: 45611 | G25: 8950000 | H25: 4475 | I25: =IFERROR(IF(E25="USD",-(G25/H25),""),"") -> -2000 | J25: =IF(E25='Hoja de Datos'!$C$7,-(G25),"") | K25: =IF(E25='Hoja de Datos'!$C$7,"", IF(G25="","", -G25)) -> -8950000
I26: =IFERROR(IF(E26="USD",-(G26/H26),""),"") | J26: =IF(E26='Hoja de Datos'!$C$7,-(G26),"") | K26: =IF(E26='Hoja de Datos'!$C$7,"", IF(G26="","", -G26))
I27: =IFERROR(IF(E27="USD",-(G27/H27),""),"") | J27: =IF(E27='Hoja de Datos'!$C$7,-(G27),"") | K27: =IF(E27='Hoja de Datos'!$C$7,"", IF(G27="","", -G27))
I28: =IFERROR(IF(E28="USD",-(G28/H28),""),"") | J28: =IF(E28='Hoja de Datos'!$C$7,-(G28),"") | K28: =IF(E28='Hoja de Datos'!$C$7,"", IF(G28="","", -G28))
I29: =IFERROR(IF(E29="USD",-(G29/H29),""),"") | J29: =IF(E29='Hoja de Datos'!$C$7,-(G29),"") | K29: =IF(E29='Hoja de Datos'!$C$7,"", IF(G29="","", -G29))
I30: =IFERROR(IF(E30="USD",-(G30/H30),""),"") | J30: =IF(E30='Hoja de Datos'!$C$7,-(G30),"") | K30: =IF(E30='Hoja de Datos'!$C$7,"", IF(G30="","", -G30))
I31: =IFERROR(IF(E31="USD",-(G31/H31),""),"") | J31: =IF(E31='Hoja de Datos'!$C$7,-(G31),"") | K31: =IF(E31='Hoja de Datos'!$C$7,"", IF(G31="","", -G31))
I32: =IFERROR(IF(E32="USD",-(G32/H32),""),"") | J32: =IF(E32='Hoja de Datos'!$C$7,-(G32),"") | K32: =IF(E32='Hoja de Datos'!$C$7,"", IF(G32="","", -G32))
I33: =IFERROR(IF(E33="USD",-(G33/H33),""),"") | J33: =IF(E33='Hoja de Datos'!$C$7,-(G33),"") | K33: =IF(E33='Hoja de Datos'!$C$7,"", IF(G33="","", -G33))
I34: =IFERROR(IF(E34="USD",-(G34/H34),""),"") | J34: =IF(E34='Hoja de Datos'!$C$7,-(G34),"") | K34: =IF(E34='Hoja de Datos'!$C$7,"", IF(G34="","", -G34))
I35: =IFERROR(IF(E35="USD",-(G35/H35),""),"") | J35: =IF(E35='Hoja de Datos'!$C$7,-(G35),"") | K35: =IF(E35='Hoja de Datos'!$C$7,"", IF(G35="","", -G35))
I36: =IFERROR(IF(E36="USD",-(G36/H36),""),"") | J36: =IF(E36='Hoja de Datos'!$C$7,-(G36),"") | K36: =IF(E36='Hoja de Datos'!$C$7,"", IF(G36="","", -G36))
I37: =IFERROR(IF(E37="USD",-(G37/H37),""),"") | J37: =IF(E37='Hoja de Datos'!$C$7,-(G37),"") | K37: =IF(E37='Hoja de Datos'!$C$7,"", IF(G37="","", -G37))
... I1993: =IFERROR(IF(E1993="USD",-(G1993/H1993),""),"") | J1993: =IF(E1993='Hoja de Datos'!$C$7,-(G1993),"") | K1993: =IF(E1993='Hoja de Datos'!$C$7,"", IF(G1993="","", -G1993))

Sheet Cortes x inversión
B2: Cómo usar (Cortes x inversión) | G2: Valor Dólar Hoy: | H2: =IFERROR(__xludf.DUMMYFUNCTION("GOOGLEFINANCE(""CURRENCY:USDCOP"")"),3768.28) -> 3768.28
B3: • Modifica unicamente las celdas que están en color amarillo.
B4: • No toques las celdas en color verde.
B5: • Cuando la inversión es en tú moneda local pon el valor en la columna F, cuando es en dólares
B6: pon el valor actual en dólares columna H y el valor de la TRM del día que estás revisando tu inversión.
B8: Pilar | C8: Entidad o Empresa | D8: Inversión | E8: Moneda (USD/COP) | F8: Valor final COP (+) o tú moneda | G8: Valor final USD (+) | H8: TRM final (COP/USD) o (Tú moneda/USD) | I8: Valor final USD a COP o tú moneda | J8: Fecha de corte | K8: Nota
B9: Fondo de Imprevistos | C9: NU | D9: Fondo de Imprevistos | E9: COP | F9: 6500000 | I9: =IF(G9>0, G9*H9, ) | J9: 45971
B10: Reserva de Oxigeno | C10: Skandia | D10: Reserva de Oxigeno | E10: COP | F10: 15000000 | I10: =IF(G10>0, G10*H10, ) | J10: 45971
B11: Cuenta de Retiro | C11: Trinity | D11: Trinity 15 años | E11: USD | G11: 6300 | H11: 3770 | I11: =IF(G11>0, G11*H11, ) -> 23751000 | J11: 45971
B12: Cuenta de Inversiones | C12: ITA | D12: Evo 10 | E12: USD | G12: 12000 | H12: 3770 | I12: =IF(G12>0, G12*H12, ) -> 45240000 | J12: 45971
B13: Cuenta de Inversiones | C13: Interactive Brokers | D13: VOO | E13: USD | G13: 2400 | H13: 3770 | I13: =IF(G13>0, G13*H13, ) -> 9048000 | J13: 45971
I14: =IF(G14>0, G14*H14, )
I15: =IF(G15>0, G15*H15, )
I16: =IF(G16>0, G16*H16, )
I17: =IF(G17>0, G17*H17, )
I18: =IF(G18>0, G18*H18, )
I19: =IF(G19>0, G19*H19, )
I20: =IF(G20>0, G20*H20, )
I21: =IF(G21>0, G21*H21, )
I22: =IF(G22>0, G22*H22, )
I23: =IF(G23>0, G23*H23, )
I24: =IF(G24>0, G24*H24, )
I25: =IF(G25>0, G25*H25, )
... I1001: =IF(G1001>0, G1001*H1001, )

Sheet Resultados x inversión
B2: Cómo usar (Resultados x inversión)
B3: • Modifica unicamente las celdas que están en color amarillo. Debes elegir los datos de las inversiones que quieres ver.
B4: • No toques las celdas en color verde.
B5: • Acá los datos que te interesará revisar son los que se encuentran en la columna I, N y T
B6: ahí verás el retorno sobre la inversión en tu moneda, en dólares y en dólares convertirdo a tu moneda local.
B8: Pilar | C8: Entidad o Empresa | D8: Inversión | E8: Moneda (USD/COP) | F8: Total aportado COP o tú moneda | G8: Valor final COP o tú moneda | H8: Ganancia/Pérdida COP | I8: TIR COP | K8: Total aportado USD | L8: Valor final USD | M8: Ganancia/Pérdida USD | N8: TIR USD | P8: Valor USD | Q8: Total aportado USD a COP o tú moneda | R8: Valor final USD a COP o tú moneda | S8: Ganancia/Pérdida USD a COP o tú moneda | T8: TIR USD a COP o tú moneda
B9: Fondo de Imprevistos | C9: NU | D9: Fondo de Imprevistos | E9: COP | F9: =IF(E9="COP", SUMIF('Entradas y salidas'!D:D, D9, 'Entradas y salidas'!J:J), ) -> -6300000 | G9: =IFERROR(__xludf.DUMMYFUNCTION("IF(E9=""COP"", INDEX(FILTER('Cortes x inversión'!F:F, 'Cortes x inversión'!D:D=D9),1), )"),6500000.0) -> 6500000 | H9: =IF(OR(F9="", G9=""),"", G9 - ABS(F9)) -> 200000 | I9: =IFERROR(__xludf.DUMMYFUNCTION("IF(ISBLANK(D9),"""",IFERROR(XIRR({FILTER('Entradas y salidas'!J:J, 'Entradas y salidas'!D:D=D9, NOT(ISBLANK('Entradas y salidas'!J:J))); INDEX(FILTER('Cortes x inversión'!F:F, 'Cortes x inversión'!D:D=D9),1)}, {FILTER('Entradas y salidas'!F:F, 'Entradas y"&" salidas'!D:D=D9, NOT(ISBLANK('Entradas y salidas'!J:J))); INDEX(FILTER('Cortes x inversión'!J:J, 'Cortes x inversión'!D:D=D9),1)}), """"))"),0.017480343914977887) -> 0.017480344 | K9: =IF(E9="USD", SUMIF('Entradas y salidas'!D:D, D9, 'Entradas y salidas'!I:I), ) | L9: =IFERROR(__xludf.DUMMYFUNCTION("IF(E9=""USD"", INDEX(FILTER('Cortes x inversión'!G:G, 'Cortes x inversión'!D:D=D9),1), )"),"") | M9: =IF(OR(K9="", L9=""),"", L9 - ABS(K9)) | N9: =IFERROR(__xludf.DUMMYFUNCTION("IF(ISBLANK(D9),"""",IFERROR(XIRR({FILTER('Entradas y salidas'!I:I, 'Entradas y salidas'!D:D=D9, NOT(ISBLANK('Entradas y salidas'!I:I))); INDEX(FILTER('Cortes x inversión'!G:G, 'Cortes x inversión'!D:D=D9),1)}, {FILTER('Entradas y salidas'!F:F, 'Entradas y"&" salidas'!D:D=D9, NOT(ISBLANK('Entradas y salidas'!I:I))); INDEX(FILTER('Cortes x inversión'!J:J, 'Cortes x inversión'!D:D=D9),1)}), """"))"),"") | P9: =IFERROR(__xludf.DUMMYFUNCTION("IF(K9="""","""", GOOGLEFINANCE(""CURRENCY:USDCOP"")) "),"") | Q9: =IF(K9="","", K9*P9) | R9: =IF(K9="","", L9*P9) | S9: =IF(OR(Q9="", R9=""),"", R9 - ABS(Q9)) | T9: =IFERROR(__xludf.DUMMYFUNCTION("IF(ISBLANK(D9),"""",IFERROR(XIRR({FILTER('Entradas y salidas'!K:K, 'Entradas y salidas'!D:D=D9, NOT(ISBLANK('Entradas y salidas'!K:K))); INDEX(FILTER('Cortes x inversión'!I:I, 'Cortes x inversión'!D:D=D9),1)}, {FILTER('Entradas y salidas'!F:F, 'Entradas y"&" salidas'!D:D=D9, NOT(ISBLANK('Entradas y salidas'!K:K))); INDEX(FILTER('Cortes x inversión'!J:J, 'Cortes x inversión'!D:D=D9),1)}), """"))"),"")
B10: Reserva de Oxigeno | C10: Skandia | D10: Reserva de Oxigeno | E10: COP | F10: =IF(E10="COP", SUMIF('Entradas y salidas'!D:D, D10, 'Entradas y salidas'!J:J), ) -> -14000000 | G10: =IFERROR(__xludf.DUMMYFUNCTION("IF(E10=""COP"", INDEX(FILTER('Cortes x inversión'!F:F, 'Cortes x inversión'!D:D=D10),1), )"),1.5E7) -> 15000000 | H10: =IF(OR(F10="", G10=""),"", G10 - ABS(F10)) -> 1000000 | I10: =IFERROR(__xludf.DUMMYFUNCTION("IF(ISBLANK(D10),"""",IFERROR(XIRR({FILTER('Entradas y salidas'!J:J, 'Entradas y salidas'!D:D=D10, NOT(ISBLANK('Entradas y salidas'!J:J))); INDEX(FILTER('Cortes x inversión'!F:F, 'Cortes x inversión'!D:D=D10),1)}, {FILTER('Entradas y salidas'!F:F, 'Entrada"&"s y salidas'!D:D=D10, NOT(ISBLANK('Entradas y salidas'!J:J))); INDEX(FILTER('Cortes x inversión'!J:J, 'Cortes x inversión'!D:D=D10),1)}), """"))"),0.04253030082479297) -> 0.042530301 | K10: =IF(E10="USD", SUMIF('Entradas y salidas'!D:D, D10, 'Entradas y salidas'!I:I), ) | L10: =IFERROR(__xludf.DUMMYFUNCTION("IF(E10=""USD"", INDEX(FILTER('Cortes x inversión'!G:G, 'Cortes x inversión'!D:D=D10),1), )"),"") | M10: =IF(OR(K10="", L10=""),"", L10 - ABS(K10)) | N10: =IFERROR(__xludf.DUMMYFUNCTION("IF(ISBLANK(D10),"""",IFERROR(XIRR({FILTER('Entradas y salidas'!I:I, 'Entradas y salidas'!D:D=D10, NOT(ISBLANK('Entradas y salidas'!I:I))); INDEX(FILTER('Cortes x inversión'!G:G, 'Cortes x inversión'!D:D=D10),1)}, {FILTER('Entradas y salidas'!F:F, 'Entrada"&"s y salidas'!D:D=D10, NOT(ISBLANK('Entradas y salidas'!I:I))); INDEX(FILTER('Cortes x inversión'!J:J, 'Cortes x inversión'!D:D=D10),1)}), """"))"),"") | P10: =IFERROR(__xludf.DUMMYFUNCTION("IF(K10="""","""", GOOGLEFINANCE(""CURRENCY:USDCOP"")) "),"") | Q10: =IF(K10="","", K10*P10) | R10: =IF(K10="","", L10*P10) | S10: =IF(OR(Q10="", R10=""),"", R10 - ABS(Q10)) | T10: =IFERROR(__xludf.DUMMYFUNCTION("IF(ISBLANK(D10),"""",IFERROR(XIRR({FILTER('Entradas y salidas'!K:K, 'Entradas y salidas'!D:D=D10, NOT(ISBLANK('Entradas y salidas'!K:K))); INDEX(FILTER('Cortes x inversión'!I:I, 'Cortes x inversión'!D:D=D10),1)}, {FILTER('Entradas y salidas'!F:F, 'Entrada"&"s y salidas'!D:D=D10, NOT(ISBLANK('Entradas y salidas'!K:K))); INDEX(FILTER('Cortes x inversión'!J:J, 'Cortes x inversión'!D:D=D10),1)}), """"))"),"")
B11: Cuenta de Retiro | C11: Trinity | D11: Trinity 15 años | E11: USD | F11: =IF(E11="COP", SUMIF('Entradas y salidas'!D:D, D11, 'Entradas y salidas'!J:J), ) | G11: =IFERROR(__xludf.DUMMYFUNCTION("IF(E11=""COP"", INDEX(FILTER('Cortes x inversión'!F:F, 'Cortes x inversión'!D:D=D11),1), )"),"") | H11: =IF(OR(F11="", G11=""),"", G11 - ABS(F11)) | I11: =IFERROR(__xludf.DUMMYFUNCTION("IF(ISBLANK(D11),"""",IFERROR(XIRR({FILTER('Entradas y salidas'!J:J, 'Entradas y salidas'!D:D=D11, NOT(ISBLANK('Entradas y salidas'!J:J))); INDEX(FILTER('Cortes x inversión'!F:F, 'Cortes x inversión'!D:D=D11),1)}, {FILTER('Entradas y salidas'!F:F, 'Entrada"&"s y salidas'!D:D=D11, NOT(ISBLANK('Entradas y salidas'!J:J))); INDEX(FILTER('Cortes x inversión'!J:J, 'Cortes x inversión'!D:D=D11),1)}), """"))"),"") | K11: =IF(E11="USD", SUMIF('Entradas y salidas'!D:D, D11, 'Entradas y salidas'!I:I), ) -> -6000 | L11: =IFERROR(__xludf.DUMMYFUNCTION("IF(E11=""USD"", INDEX(FILTER('Cortes x inversión'!G:G, 'Cortes x inversión'!D:D=D11),1), )"),6300.0) -> 6300 | M11: =IF(OR(K11="", L11=""),"", L11 - ABS(K11)) -> 300 | N11: =IFERROR(__xludf.DUMMYFUNCTION("IF(ISBLANK(D11),"""",IFERROR(XIRR({FILTER('Entradas y salidas'!I:I, 'Entradas y salidas'!D:D=D11, NOT(ISBLANK('Entradas y salidas'!I:I))); INDEX(FILTER('Cortes x inversión'!G:G, 'Cortes x inversión'!D:D=D11),1)}, {FILTER('Entradas y salidas'!F:F, 'Entrada"&"s y salidas'!D:D=D11, NOT(ISBLANK('Entradas y salidas'!I:I))); INDEX(FILTER('Cortes x inversión'!J:J, 'Cortes x inversión'!D:D=D11),1)}), """"))"),0.019077510452035686) -> 0.01907751 | P11: =IFERROR(__xludf.DUMMYFUNCTION("IF(K11="""","""", GOOGLEFINANCE(""CURRENCY:USDCOP"")) "),3768.28) -> 3768.28 | Q11: =IF(K11="","", K11*P11) -> -22609680 | R11: =IF(K11="","", L11*P11) -> 23740164 | S11: =IF(OR(Q11="", R11=""),"", R11 - ABS(Q11)) -> 1130484 | T11: =IFERROR(__xludf.DUMMYFUNCTION("IF(ISBLANK(D11),"""",IFERROR(XIRR({FILTER('Entradas y salidas'!K:K, 'Entradas y salidas'!D:D=D11, NOT(ISBLANK('Entradas y salidas'!K:K))); INDEX(FILTER('Cortes x inversión'!I:I, 'Cortes x inversión'!D:D=D11),1)}, {FILTER('Entradas y salidas'!F:F, 'Entrada"&"s y salidas'!D:D=D11, NOT(ISBLANK('Entradas y salidas'!K:K))); INDEX(FILTER('Cortes x inversión'!J:J, 'Cortes x inversión'!D:D=D11),1)}), """"))"),-0.039297069217602426) -> -0.039297069
B12: Cuenta de Inversiones | C12: ITA | D12: Evo 10 | E12: USD | F12: =IF(E12="COP", SUMIF('Entradas y salidas'!D:D, D12, 'Entradas y salidas'!J:J), ) | G12: =IFERROR(__xludf.DUMMYFUNCTION("IF(E12=""COP"", INDEX(FILTER('Cortes x inversión'!F:F, 'Cortes x inversión'!D:D=D12),1), )"),"") | H12: =IF(OR(F12="", G12=""),"", G12 - ABS(F12)) | I12: =IFERROR(__xludf.DUMMYFUNCTION("IF(ISBLANK(D12),"""",IFERROR(XIRR({FILTER('Entradas y salidas'!J:J, 'Entradas y salidas'!D:D=D12, NOT(ISBLANK('Entradas y salidas'!J:J))); INDEX(FILTER('Cortes x inversión'!F:F, 'Cortes x inversión'!D:D=D12),1)}, {FILTER('Entradas y salidas'!F:F, 'Entrada"&"s y salidas'!D:D=D12, NOT(ISBLANK('Entradas y salidas'!J:J))); INDEX(FILTER('Cortes x inversión'!J:J, 'Cortes x inversión'!D:D=D12),1)}), """"))"),"") | K12: =IF(E12="USD", SUMIF('Entradas y salidas'!D:D, D12, 'Entradas y salidas'!I:I), ) -> -10000 | L12: =IFERROR(__xludf.DUMMYFUNCTION("IF(E12=""USD"", INDEX(FILTER('Cortes x inversión'!G:G, 'Cortes x inversión'!D:D=D12),1), )"),12000.0) -> 12000 | M12: =IF(OR(K12="", L12=""),"", L12 - ABS(K12)) -> 2000 | N12: =IFERROR(__xludf.DUMMYFUNCTION("IF(ISBLANK(D12),"""",IFERROR(XIRR({FILTER('Entradas y salidas'!I:I, 'Entradas y salidas'!D:D=D12, NOT(ISBLANK('Entradas y salidas'!I:I))); INDEX(FILTER('Cortes x inversión'!G:G, 'Cortes x inversión'!D:D=D12),1)}, {FILTER('Entradas y salidas'!F:F, 'Entrada"&"s y salidas'!D:D=D12, NOT(ISBLANK('Entradas y salidas'!I:I))); INDEX(FILTER('Cortes x inversión'!J:J, 'Cortes x inversión'!D:D=D12),1)}), """"))"),0.11731676240573267) -> 0.11731676 | P12: =IFERROR(__xludf.DUMMYFUNCTION("IF(K12="""","""", GOOGLEFINANCE(""CURRENCY:USDCOP"")) "),3768.28) -> 3768.28 | Q12: =IF(K12="","", K12*P12) -> -37682800 | R12: =IF(K12="","", L12*P12) -> 45219360 | S12: =IF(OR(Q12="", R12=""),"", R12 - ABS(Q12)) -> 7536560 | T12: =IFERROR(__xludf.DUMMYFUNCTION("IF(ISBLANK(D12),"""",IFERROR(XIRR({FILTER('Entradas y salidas'!K:K, 'Entradas y salidas'!D:D=D12, NOT(ISBLANK('Entradas y salidas'!K:K))); INDEX(FILTER('Cortes x inversión'!I:I, 'Cortes x inversión'!D:D=D12),1)}, {FILTER('Entradas y salidas'!F:F, 'Entrada"&"s y salidas'!D:D=D12, NOT(ISBLANK('Entradas y salidas'!K:K))); INDEX(FILTER('Cortes x inversión'!J:J, 'Cortes x inversión'!D:D=D12),1)}), """"))"),0.04086936142249945) -> 0.040869361
B13: Cuenta de Inversiones | C13: Interactive Brokers | D13: VOO | E13: USD | F13: =IF(E13="COP", SUMIF('Entradas y salidas'!D:D, D13, 'Entradas y salidas'!J:J), ) | G13: =IFERROR(__xludf.DUMMYFUNCTION("IF(E13=""COP"", INDEX(FILTER('Cortes x inversión'!F:F, 'Cortes x inversión'!D:D=D13),1), )"),"") | H13: =IF(OR(F13="", G13=""),"", G13 - ABS(F13)) | I13: =IFERROR(__xludf.DUMMYFUNCTION("IF(ISBLANK(D13),"""",IFERROR(XIRR({FILTER('Entradas y salidas'!J:J, 'Entradas y salidas'!D:D=D13, NOT(ISBLANK('Entradas y salidas'!J:J))); INDEX(FILTER('Cortes x inversión'!F:F, 'Cortes x inversión'!D:D=D13),1)}, {FILTER('Entradas y salidas'!F:F, 'Entrada"&"s y salidas'!D:D=D13, NOT(ISBLANK('Entradas y salidas'!J:J))); INDEX(FILTER('Cortes x inversión'!J:J, 'Cortes x inversión'!D:D=D13),1)}), """"))"),"") | K13: =IF(E13="USD", SUMIF('Entradas y salidas'!D:D, D13, 'Entradas y salidas'!I:I), ) -> -2000 | L13: =IFERROR(__xludf.DUMMYFUNCTION("IF(E13=""USD"", INDEX(FILTER('Cortes x inversión'!G:G, 'Cortes x inversión'!D:D=D13),1), )"),2400.0) -> 2400 | M13: =IF(OR(K13="", L13=""),"", L13 - ABS(K13)) -> 400 | N13: =IFERROR(__xludf.DUMMYFUNCTION("IF(ISBLANK(D13),"""",IFERROR(XIRR({FILTER('Entradas y salidas'!I:I, 'Entradas y salidas'!D:D=D13, NOT(ISBLANK('Entradas y salidas'!I:I))); INDEX(FILTER('Cortes x inversión'!G:G, 'Cortes x inversión'!D:D=D13),1)}, {FILTER('Entradas y salidas'!F:F, 'Entrada"&"s y salidas'!D:D=D13, NOT(ISBLANK('Entradas y salidas'!I:I))); INDEX(FILTER('Cortes x inversión'!J:J, 'Cortes x inversión'!D:D=D13),1)}), """"))"),0.20304254321810247) -> 0.20304254 | P13: =IFERROR(__xludf.DUMMYFUNCTION("IF(K13="""","""", GOOGLEFINANCE(""CURRENCY:USDCOP"")) "),3768.28) -> 3768.28 | Q13: =IF(K13="","", K13*P13) -> -7536560 | R13: =IF(K13="","", L13*P13) -> 9043872 | S13: =IF(OR(Q13="", R13=""),"", R13 - ABS(Q13)) -> 1507312 | T13: =IFERROR(__xludf.DUMMYFUNCTION("IF(ISBLANK(D13),"""",IFERROR(XIRR({FILTER('Entradas y salidas'!K:K, 'Entradas y salidas'!D:D=D13, NOT(ISBLANK('Entradas y salidas'!K:K))); INDEX(FILTER('Cortes x inversión'!I:I, 'Cortes x inversión'!D:D=D13),1)}, {FILTER('Entradas y salidas'!F:F, 'Entrada"&"s y salidas'!D:D=D13, NOT(ISBLANK('Entradas y salidas'!K:K))); INDEX(FILTER('Cortes x inversión'!J:J, 'Cortes x inversión'!D:D=D13),1)}), """"))"),0.011102641280031241) -> 0.011102641
F14: =IF(E14="COP", SUMIF('Entradas y salidas'!D:D, D14, 'Entradas y salidas'!J:J), ) | G14: =IFERROR(__xludf.DUMMYFUNCTION("IF(E14=""COP"", INDEX(FILTER('Cortes x inversión'!F:F, 'Cortes x inversión'!D:D=D14),1), )"),"") | H14: =IF(OR(F14="", G14=""),"", G14 - ABS(F14)) | I14: =IFERROR(__xludf.DUMMYFUNCTION("IF(ISBLANK(D14),"""",IFERROR(XIRR({FILTER('Entradas y salidas'!J:J, 'Entradas y salidas'!D:D=D14, NOT(ISBLANK('Entradas y salidas'!J:J))); INDEX(FILTER('Cortes x inversión'!F:F, 'Cortes x inversión'!D:D=D14),1)}, {FILTER('Entradas y salidas'!F:F, 'Entrada"&"s y salidas'!D:D=D14, NOT(ISBLANK('Entradas y salidas'!J:J))); INDEX(FILTER('Cortes x inversión'!J:J, 'Cortes x inversión'!D:D=D14),1)}), """"))"),"") | K14: =IF(E14="USD", SUMIF('Entradas y salidas'!D:D, D14, 'Entradas y salidas'!I:I), ) | L14: =IFERROR(__xludf.DUMMYFUNCTION("IF(E14=""USD"", INDEX(FILTER('Cortes x inversión'!G:G, 'Cortes x inversión'!D:D=D14),1), )"),"") | M14: =IF(OR(K14="", L14=""),"", L14 - ABS(K14)) | N14: =IFERROR(__xludf.DUMMYFUNCTION("IF(ISBLANK(D14),"""",IFERROR(XIRR({FILTER('Entradas y salidas'!I:I, 'Entradas y salidas'!D:D=D14, NOT(ISBLANK('Entradas y salidas'!I:I))); INDEX(FILTER('Cortes x inversión'!G:G, 'Cortes x inversión'!D:D=D14),1)}, {FILTER('Entradas y salidas'!F:F, 'Entrada"&"s y salidas'!D:D=D14, NOT(ISBLANK('Entradas y salidas'!I:I))); INDEX(FILTER('Cortes x inversión'!J:J, 'Cortes x inversión'!D:D=D14),1)}), """"))"),"") | P14: =IFERROR(__xludf.DUMMYFUNCTION("IF(K14="""","""", GOOGLEFINANCE(""CURRENCY:USDCOP"")) "),"") | Q14: =IFERROR(__xludf.DUMMYFUNCTION("IF(L14="""","""", GOOGLEFINANCE(""CURRENCY:USDCOP"")) "),"") | R14: =IF(K14="","", L14*P14) | S14: =IF(OR(Q14="", R14=""),"", R14 - ABS(Q14)) | T14: =IFERROR(__xludf.DUMMYFUNCTION("IF(ISBLANK(D14),"""",IFERROR(XIRR({FILTER('Entradas y salidas'!K:K, 'Entradas y salidas'!D:D=D14, NOT(ISBLANK('Entradas y salidas'!K:K))); INDEX(FILTER('Cortes x inversión'!I:I, 'Cortes x inversión'!D:D=D14),1)}, {FILTER('Entradas y salidas'!F:F, 'Entrada"&"s y salidas'!D:D=D14, NOT(ISBLANK('Entradas y salidas'!K:K))); INDEX(FILTER('Cortes x inversión'!J:J, 'Cortes x inversión'!D:D=D14),1)}), """"))"),"")
F15: =IF(E15="COP", SUMIF('Entradas y salidas'!D:D, D15, 'Entradas y salidas'!J:J), ) | G15: =IFERROR(__xludf.DUMMYFUNCTION("IF(E15=""COP"", INDEX(FILTER('Cortes x inversión'!F:F, 'Cortes x inversión'!D:D=D15),1), )"),"") | H15: =IF(OR(F15="", G15=""),"", G15 - ABS(F15)) | I15: =IFERROR(__xludf.DUMMYFUNCTION("IF(ISBLANK(D15),"""",IFERROR(XIRR({FILTER('Entradas y salidas'!J:J, 'Entradas y salidas'!D:D=D15, NOT(ISBLANK('Entradas y salidas'!J:J))); INDEX(FILTER('Cortes x inversión'!F:F, 'Cortes x inversión'!D:D=D15),1)}, {FILTER('Entradas y salidas'!F:F, 'Entrada"&"s y salidas'!D:D=D15, NOT(ISBLANK('Entradas y salidas'!J:J))); INDEX(FILTER('Cortes x inversión'!J:J, 'Cortes x inversión'!D:D=D15),1)}), """"))"),"") | K15: =IF(E15="USD", SUMIF('Entradas y salidas'!D:D, D15, 'Entradas y salidas'!I:I), ) | L15: =IFERROR(__xludf.DUMMYFUNCTION("IF(E15=""USD"", INDEX(FILTER('Cortes x inversión'!G:G, 'Cortes x inversión'!D:D=D15),1), )"),"") | M15: =IF(OR(K15="", L15=""),"", L15 - ABS(K15)) | N15: =IFERROR(__xludf.DUMMYFUNCTION("IF(ISBLANK(D15),"""",IFERROR(XIRR({FILTER('Entradas y salidas'!I:I, 'Entradas y salidas'!D:D=D15, NOT(ISBLANK('Entradas y salidas'!I:I))); INDEX(FILTER('Cortes x inversión'!G:G, 'Cortes x inversión'!D:D=D15),1)}, {FILTER('Entradas y salidas'!F:F, 'Entrada"&"s y salidas'!D:D=D15, NOT(ISBLANK('Entradas y salidas'!I:I))); INDEX(FILTER('Cortes x inversión'!J:J, 'Cortes x inversión'!D:D=D15),1)}), """"))"),"") | P15: =IFERROR(__xludf.DUMMYFUNCTION("IF(K15="""","""", GOOGLEFINANCE(""CURRENCY:USDCOP"")) "),"") | Q15: =IFERROR(__xludf.DUMMYFUNCTION("IF(L15="""","""", GOOGLEFINANCE(""CURRENCY:USDCOP"")) "),"") | R15: =IF(K15="","", L15*P15) | S15: =IF(OR(Q15="", R15=""),"", R15 - ABS(Q15)) | T15: =IFERROR(__xludf.DUMMYFUNCTION("IF(ISBLANK(D15),"""",IFERROR(XIRR({FILTER('Entradas y salidas'!K:K, 'Entradas y salidas'!D:D=D15, NOT(ISBLANK('Entradas y salidas'!K:K))); INDEX(FILTER('Cortes x inversión'!I:I, 'Cortes x inversión'!D:D=D15),1)}, {FILTER('Entradas y salidas'!F:F, 'Entrada"&"s y salidas'!D:D=D15, NOT(ISBLANK('Entradas y salidas'!K:K))); INDEX(FILTER('Cortes x inversión'!J:J, 'Cortes x inversión'!D:D=D15),1)}), """"))"),"")
F16: =IF(E16="COP", SUMIF('Entradas y salidas'!D:D, D16, 'Entradas y salidas'!J:J), ) | G16: =IFERROR(__xludf.DUMMYFUNCTION("IF(E16=""COP"", INDEX(FILTER('Cortes x inversión'!F:F, 'Cortes x inversión'!D:D=D16),1), )"),"") | H16: =IF(OR(F16="", G16=""),"", G16 - ABS(F16)) | I16: =IFERROR(__xludf.DUMMYFUNCTION("IF(ISBLANK(D16),"""",IFERROR(XIRR({FILTER('Entradas y salidas'!J:J, 'Entradas y salidas'!D:D=D16, NOT(ISBLANK('Entradas y salidas'!J:J))); INDEX(FILTER('Cortes x inversión'!F:F, 'Cortes x inversión'!D:D=D16),1)}, {FILTER('Entradas y salidas'!F:F, 'Entrada"&"s y salidas'!D:D=D16, NOT(ISBLANK('Entradas y salidas'!J:J))); INDEX(FILTER('Cortes x inversión'!J:J, 'Cortes x inversión'!D:D=D16),1)}), """"))"),"") | K16: =IF(E16="USD", SUMIF('Entradas y salidas'!D:D, D16, 'Entradas y salidas'!I:I), ) | L16: =IFERROR(__xludf.DUMMYFUNCTION("IF(E16=""USD"", INDEX(FILTER('Cortes x inversión'!G:G, 'Cortes x inversión'!D:D=D16),1), )"),"") | M16: =IF(OR(K16="", L16=""),"", L16 - ABS(K16)) | N16: =IFERROR(__xludf.DUMMYFUNCTION("IF(ISBLANK(D16),"""",IFERROR(XIRR({FILTER('Entradas y salidas'!I:I, 'Entradas y salidas'!D:D=D16, NOT(ISBLANK('Entradas y salidas'!I:I))); INDEX(FILTER('Cortes x inversión'!G:G, 'Cortes x inversión'!D:D=D16),1)}, {FILTER('Entradas y salidas'!F:F, 'Entrada"&"s y salidas'!D:D=D16, NOT(ISBLANK('Entradas y salidas'!I:I))); INDEX(FILTER('Cortes x inversión'!J:J, 'Cortes x inversión'!D:D=D16),1)}), """"))"),"") | P16: =IFERROR(__xludf.DUMMYFUNCTION("IF(K16="""","""", GOOGLEFINANCE(""CURRENCY:USDCOP"")) "),"") | Q16: =IFERROR(__xludf.DUMMYFUNCTION("IF(L16="""","""", GOOGLEFINANCE(""CURRENCY:USDCOP"")) "),"") | R16: =IF(K16="","", L16*P16) | S16: =IF(OR(Q16="", R16=""),"", R16 - ABS(Q16)) | T16: =IFERROR(__xludf.DUMMYFUNCTION("IF(ISBLANK(D16),"""",IFERROR(XIRR({FILTER('Entradas y salidas'!K:K, 'Entradas y salidas'!D:D=D16, NOT(ISBLANK('Entradas y salidas'!K:K))); INDEX(FILTER('Cortes x inversión'!I:I, 'Cortes x inversión'!D:D=D16),1)}, {FILTER('Entradas y salidas'!F:F, 'Entrada"&"s y salidas'!D:D=D16, NOT(ISBLANK('Entradas y salidas'!K:K))); INDEX(FILTER('Cortes x inversión'!J:J, 'Cortes x inversión'!D:D=D16),1)}), """"))"),"")
F17: =IF(E17="COP", SUMIF('Entradas y salidas'!D:D, D17, 'Entradas y salidas'!J:J), ) | G17: =IFERROR(__xludf.DUMMYFUNCTION("IF(E17=""COP"", INDEX(FILTER('Cortes x inversión'!F:F, 'Cortes x inversión'!D:D=D17),1), )"),"") | H17: =IF(OR(F17="", G17=""),"", G17 - ABS(F17)) | I17: =IFERROR(__xludf.DUMMYFUNCTION("IF(ISBLANK(D17),"""",IFERROR(XIRR({FILTER('Entradas y salidas'!J:J, 'Entradas y salidas'!D:D=D17, NOT(ISBLANK('Entradas y salidas'!J:J))); INDEX(FILTER('Cortes x inversión'!F:F, 'Cortes x inversión'!D:D=D17),1)}, {FILTER('Entradas y salidas'!F:F, 'Entrada"&"s y salidas'!D:D=D17, NOT(ISBLANK('Entradas y salidas'!J:J))); INDEX(FILTER('Cortes x inversión'!J:J, 'Cortes x inversión'!D:D=D17),1)}), """"))"),"") | K17: =IF(E17="USD", SUMIF('Entradas y salidas'!D:D, D17, 'Entradas y salidas'!I:I), ) | L17: =IFERROR(__xludf.DUMMYFUNCTION("IF(E17=""USD"", INDEX(FILTER('Cortes x inversión'!G:G, 'Cortes x inversión'!D:D=D17),1), )"),"") | M17: =IF(OR(K17="", L17=""),"", L17 - ABS(K17)) | N17: =IFERROR(__xludf.DUMMYFUNCTION("IF(ISBLANK(D17),"""",IFERROR(XIRR({FILTER('Entradas y salidas'!I:I, 'Entradas y salidas'!D:D=D17, NOT(ISBLANK('Entradas y salidas'!I:I))); INDEX(FILTER('Cortes x inversión'!G:G, 'Cortes x inversión'!D:D=D17),1)}, {FILTER('Entradas y salidas'!F:F, 'Entrada"&"s y salidas'!D:D=D17, NOT(ISBLANK('Entradas y salidas'!I:I))); INDEX(FILTER('Cortes x inversión'!J:J, 'Cortes x inversión'!D:D=D17),1)}), """"))"),"") | P17: =IFERROR(__xludf.DUMMYFUNCTION("IF(K17="""","""", GOOGLEFINANCE(""CURRENCY:USDCOP"")) "),"") | Q17: =IFERROR(__xludf.DUMMYFUNCTION("IF(L17="""","""", GOOGLEFINANCE(""CURRENCY:USDCOP"")) "),"") | R17: =IF(K17="","", L17*P17) | S17: =IF(OR(Q17="", R17=""),"", R17 - ABS(Q17)) | T17: =IFERROR(__xludf.DUMMYFUNCTION("IF(ISBLANK(D17),"""",IFERROR(XIRR({FILTER('Entradas y salidas'!K:K, 'Entradas y salidas'!D:D=D17, NOT(ISBLANK('Entradas y salidas'!K:K))); INDEX(FILTER('Cortes x inversión'!I:I, 'Cortes x inversión'!D:D=D17),1)}, {FILTER('Entradas y salidas'!F:F, 'Entrada"&"s y salidas'!D:D=D17, NOT(ISBLANK('Entradas y salidas'!K:K))); INDEX(FILTER('Cortes x inversión'!J:J, 'Cortes x inversión'!D:D=D17),1)}), """"))"),"")
F18: =IF(E18="COP", SUMIF('Entradas y salidas'!D:D, D18, 'Entradas y salidas'!J:J), ) | G18: =IFERROR(__xludf.DUMMYFUNCTION("IF(E18=""COP"", INDEX(FILTER('Cortes x inversión'!F:F, 'Cortes x inversión'!D:D=D18),1), )"),"") | H18: =IF(OR(F18="", G18=""),"", G18 - ABS(F18)) | I18: =IFERROR(__xludf.DUMMYFUNCTION("IF(ISBLANK(D18),"""",IFERROR(XIRR({FILTER('Entradas y salidas'!J:J, 'Entradas y salidas'!D:D=D18, NOT(ISBLANK('Entradas y salidas'!J:J))); INDEX(FILTER('Cortes x inversión'!F:F, 'Cortes x inversión'!D:D=D18),1)}, {FILTER('Entradas y salidas'!F:F, 'Entrada"&"s y salidas'!D:D=D18, NOT(ISBLANK('Entradas y salidas'!J:J))); INDEX(FILTER('Cortes x inversión'!J:J, 'Cortes x inversión'!D:D=D18),1)}), """"))"),"") | K18: =IF(E18="USD", SUMIF('Entradas y salidas'!D:D, D18, 'Entradas y salidas'!I:I), ) | L18: =IFERROR(__xludf.DUMMYFUNCTION("IF(E18=""USD"", INDEX(FILTER('Cortes x inversión'!G:G, 'Cortes x inversión'!D:D=D18),1), )"),"") | M18: =IF(OR(K18="", L18=""),"", L18 - ABS(K18)) | N18: =IFERROR(__xludf.DUMMYFUNCTION("IF(ISBLANK(D18),"""",IFERROR(XIRR({FILTER('Entradas y salidas'!I:I, 'Entradas y salidas'!D:D=D18, NOT(ISBLANK('Entradas y salidas'!I:I))); INDEX(FILTER('Cortes x inversión'!G:G, 'Cortes x inversión'!D:D=D18),1)}, {FILTER('Entradas y salidas'!F:F, 'Entrada"&"s y salidas'!D:D=D18, NOT(ISBLANK('Entradas y salidas'!I:I))); INDEX(FILTER('Cortes x inversión'!J:J, 'Cortes x inversión'!D:D=D18),1)}), """"))"),"") | P18: =IFERROR(__xludf.DUMMYFUNCTION("IF(K18="""","""", GOOGLEFINANCE(""CURRENCY:USDCOP"")) "),"") | Q18: =IFERROR(__xludf.DUMMYFUNCTION("IF(L18="""","""", GOOGLEFINANCE(""CURRENCY:USDCOP"")) "),"") | R18: =IF(K18="","", L18*P18) | S18: =IF(OR(Q18="", R18=""),"", R18 - ABS(Q18)) | T18: =IFERROR(__xludf.DUMMYFUNCTION("IF(ISBLANK(D18),"""",IFERROR(XIRR({FILTER('Entradas y salidas'!K:K, 'Entradas y salidas'!D:D=D18, NOT(ISBLANK('Entradas y salidas'!K:K))); INDEX(FILTER('Cortes x inversión'!I:I, 'Cortes x inversión'!D:D=D18),1)}, {FILTER('Entradas y salidas'!F:F, 'Entrada"&"s y salidas'!D:D=D18, NOT(ISBLANK('Entradas y salidas'!K:K))); INDEX(FILTER('Cortes x inversión'!J:J, 'Cortes x inversión'!D:D=D18),1)}), """"))"),"")
F19: =IF(E19="COP", SUMIF('Entradas y salidas'!D:D, D19, 'Entradas y salidas'!J:J), ) | G19: =IFERROR(__xludf.DUMMYFUNCTION("IF(E19=""COP"", INDEX(FILTER('Cortes x inversión'!F:F, 'Cortes x inversión'!D:D=D19),1), )"),"") | H19: =IF(OR(F19="", G19=""),"", G19 - ABS(F19)) | I19: =IFERROR(__xludf.DUMMYFUNCTION("IF(ISBLANK(D19),"""",IFERROR(XIRR({FILTER('Entradas y salidas'!J:J, 'Entradas y salidas'!D:D=D19, NOT(ISBLANK('Entradas y salidas'!J:J))); INDEX(FILTER('Cortes x inversión'!F:F, 'Cortes x inversión'!D:D=D19),1)}, {FILTER('Entradas y salidas'!F:F, 'Entrada"&"s y salidas'!D:D=D19, NOT(ISBLANK('Entradas y salidas'!J:J))); INDEX(FILTER('Cortes x inversión'!J:J, 'Cortes x inversión'!D:D=D19),1)}), """"))"),"") | K19: =IF(E19="USD", SUMIF('Entradas y salidas'!D:D, D19, 'Entradas y salidas'!I:I), ) | L19: =IFERROR(__xludf.DUMMYFUNCTION("IF(E19=""USD"", INDEX(FILTER('Cortes x inversión'!G:G, 'Cortes x inversión'!D:D=D19),1), )"),"") | M19: =IF(OR(K19="", L19=""),"", L19 - ABS(K19)) | N19: =IFERROR(__xludf.DUMMYFUNCTION("IF(ISBLANK(D19),"""",IFERROR(XIRR({FILTER('Entradas y salidas'!I:I, 'Entradas y salidas'!D:D=D19, NOT(ISBLANK('Entradas y salidas'!I:I))); INDEX(FILTER('Cortes x inversión'!G:G, 'Cortes x inversión'!D:D=D19),1)}, {FILTER('Entradas y salidas'!F:F, 'Entrada"&"s y salidas'!D:D=D19, NOT(ISBLANK('Entradas y salidas'!I:I))); INDEX(FILTER('Cortes x inversión'!J:J, 'Cortes x inversión'!D:D=D19),1)}), """"))"),"") | P19: =IFERROR(__xludf.DUMMYFUNCTION("IF(K19="""","""", GOOGLEFINANCE(""CURRENCY:USDCOP"")) "),"") | Q19: =IFERROR(__xludf.DUMMYFUNCTION("IF(L19="""","""", GOOGLEFINANCE(""CURRENCY:USDCOP"")) "),"") | R19: =IF(K19="","", L19*P19) | S19: =IF(OR(Q19="", R19=""),"", R19 - ABS(Q19)) | T19: =IFERROR(__xludf.DUMMYFUNCTION("IF(ISBLANK(D19),"""",IFERROR(XIRR({FILTER('Entradas y salidas'!K:K, 'Entradas y salidas'!D:D=D19, NOT(ISBLANK('Entradas y salidas'!K:K))); INDEX(FILTER('Cortes x inversión'!I:I, 'Cortes x inversión'!D:D=D19),1)}, {FILTER('Entradas y salidas'!F:F, 'Entrada"&"s y salidas'!D:D=D19, NOT(ISBLANK('Entradas y salidas'!K:K))); INDEX(FILTER('Cortes x inversión'!J:J, 'Cortes x inversión'!D:D=D19),1)}), """"))"),"")
F20: =IF(E20="COP", SUMIF('Entradas y salidas'!D:D, D20, 'Entradas y salidas'!J:J), ) | G20: =IFERROR(__xludf.DUMMYFUNCTION("IF(E20=""COP"", INDEX(FILTER('Cortes x inversión'!F:F, 'Cortes x inversión'!D:D=D20),1), )"),"") | H20: =IF(OR(F20="", G20=""),"", G20 - ABS(F20)) | I20: =IFERROR(__xludf.DUMMYFUNCTION("IF(ISBLANK(D20),"""",IFERROR(XIRR({FILTER('Entradas y salidas'!J:J, 'Entradas y salidas'!D:D=D20, NOT(ISBLANK('Entradas y salidas'!J:J))); INDEX(FILTER('Cortes x inversión'!F:F, 'Cortes x inversión'!D:D=D20),1)}, {FILTER('Entradas y salidas'!F:F, 'Entrada"&"s y salidas'!D:D=D20, NOT(ISBLANK('Entradas y salidas'!J:J))); INDEX(FILTER('Cortes x inversión'!J:J, 'Cortes x inversión'!D:D=D20),1)}), """"))"),"") | K20: =IF(E20="USD", SUMIF('Entradas y salidas'!D:D, D20, 'Entradas y salidas'!I:I), ) | L20: =IFERROR(__xludf.DUMMYFUNCTION("IF(E20=""USD"", INDEX(FILTER('Cortes x inversión'!G:G, 'Cortes x inversión'!D:D=D20),1), )"),"") | M20: =IF(OR(K20="", L20=""),"", L20 - ABS(K20)) | N20: =IFERROR(__xludf.DUMMYFUNCTION("IF(ISBLANK(D20),"""",IFERROR(XIRR({FILTER('Entradas y salidas'!I:I, 'Entradas y salidas'!D:D=D20, NOT(ISBLANK('Entradas y salidas'!I:I))); INDEX(FILTER('Cortes x inversión'!G:G, 'Cortes x inversión'!D:D=D20),1)}, {FILTER('Entradas y salidas'!F:F, 'Entrada"&"s y salidas'!D:D=D20, NOT(ISBLANK('Entradas y salidas'!I:I))); INDEX(FILTER('Cortes x inversión'!J:J, 'Cortes x inversión'!D:D=D20),1)}), """"))"),"") | P20: =IFERROR(__xludf.DUMMYFUNCTION("IF(K20="""","""", GOOGLEFINANCE(""CURRENCY:USDCOP"")) "),"") | Q20: =IFERROR(__xludf.DUMMYFUNCTION("IF(L20="""","""", GOOGLEFINANCE(""CURRENCY:USDCOP"")) "),"") | R20: =IF(K20="","", L20*P20) | S20: =IF(OR(Q20="", R20=""),"", R20 - ABS(Q20)) | T20: =IFERROR(__xludf.DUMMYFUNCTION("IF(ISBLANK(D20),"""",IFERROR(XIRR({FILTER('Entradas y salidas'!K:K, 'Entradas y salidas'!D:D=D20, NOT(ISBLANK('Entradas y salidas'!K:K))); INDEX(FILTER('Cortes x inversión'!I:I, 'Cortes x inversión'!D:D=D20),1)}, {FILTER('Entradas y salidas'!F:F, 'Entrada"&"s y salidas'!D:D=D20, NOT(ISBLANK('Entradas y salidas'!K:K))); INDEX(FILTER('Cortes x inversión'!J:J, 'Cortes x inversión'!D:D=D20),1)}), """"))"),"")
F21: =IF(E21="COP", SUMIF('Entradas y salidas'!D:D, D21, 'Entradas y salidas'!J:J), ) | G21: =IFERROR(__xludf.DUMMYFUNCTION("IF(E21=""COP"", INDEX(FILTER('Cortes x inversión'!F:F, 'Cortes x inversión'!D:D=D21),1), )"),"") | H21: =IF(OR(F21="", G21=""),"", G21 - ABS(F21)) | I21: =IFERROR(__xludf.DUMMYFUNCTION("IF(ISBLANK(D21),"""",IFERROR(XIRR({FILTER('Entradas y salidas'!J:J, 'Entradas y salidas'!D:D=D21, NOT(ISBLANK('Entradas y salidas'!J:J))); INDEX(FILTER('Cortes x inversión'!F:F, 'Cortes x inversión'!D:D=D21),1)}, {FILTER('Entradas y salidas'!F:F, 'Entrada"&"s y salidas'!D:D=D21, NOT(ISBLANK('Entradas y salidas'!J:J))); INDEX(FILTER('Cortes x inversión'!J:J, 'Cortes x inversión'!D:D=D21),1)}), """"))"),"") | K21: =IF(E21="USD", SUMIF('Entradas y salidas'!D:D, D21, 'Entradas y salidas'!I:I), ) | L21: =IFERROR(__xludf.DUMMYFUNCTION("IF(E21=""USD"", INDEX(FILTER('Cortes x inversión'!G:G, 'Cortes x inversión'!D:D=D21),1), )"),"") | M21: =IF(OR(K21="", L21=""),"", L21 - ABS(K21)) | N21: =IFERROR(__xludf.DUMMYFUNCTION("IF(ISBLANK(D21),"""",IFERROR(XIRR({FILTER('Entradas y salidas'!I:I, 'Entradas y salidas'!D:D=D21, NOT(ISBLANK('Entradas y salidas'!I:I))); INDEX(FILTER('Cortes x inversión'!G:G, 'Cortes x inversión'!D:D=D21),1)}, {FILTER('Entradas y salidas'!F:F, 'Entrada"&"s y salidas'!D:D=D21, NOT(ISBLANK('Entradas y salidas'!I:I))); INDEX(FILTER('Cortes x inversión'!J:J, 'Cortes x inversión'!D:D=D21),1)}), """"))"),"") | P21: =IFERROR(__xludf.DUMMYFUNCTION("IF(K21="""","""", GOOGLEFINANCE(""CURRENCY:USDCOP"")) "),"") | Q21: =IFERROR(__xludf.DUMMYFUNCTION("IF(L21="""","""", GOOGLEFINANCE(""CURRENCY:USDCOP"")) "),"") | R21: =IF(K21="","", L21*P21) | S21: =IF(OR(Q21="", R21=""),"", R21 - ABS(Q21)) | T21: =IFERROR(__xludf.DUMMYFUNCTION("IF(ISBLANK(D21),"""",IFERROR(XIRR({FILTER('Entradas y salidas'!K:K, 'Entradas y salidas'!D:D=D21, NOT(ISBLANK('Entradas y salidas'!K:K))); INDEX(FILTER('Cortes x inversión'!I:I, 'Cortes x inversión'!D:D=D21),1)}, {FILTER('Entradas y salidas'!F:F, 'Entrada"&"s y salidas'!D:D=D21, NOT(ISBLANK('Entradas y salidas'!K:K))); INDEX(FILTER('Cortes x inversión'!J:J, 'Cortes x inversión'!D:D=D21),1)}), """"))"),"")
F22: =IF(E22="COP", SUMIF('Entradas y salidas'!D:D, D22, 'Entradas y salidas'!J:J), ) | G22: =IFERROR(__xludf.DUMMYFUNCTION("IF(E22=""COP"", INDEX(FILTER('Cortes x inversión'!F:F, 'Cortes x inversión'!D:D=D22),1), )"),"") | H22: =IF(OR(F22="", G22=""),"", G22 - ABS(F22)) | I22: =IFERROR(__xludf.DUMMYFUNCTION("IF(ISBLANK(D22),"""",IFERROR(XIRR({FILTER('Entradas y salidas'!J:J, 'Entradas y salidas'!D:D=D22, NOT(ISBLANK('Entradas y salidas'!J:J))); INDEX(FILTER('Cortes x inversión'!F:F, 'Cortes x inversión'!D:D=D22),1)}, {FILTER('Entradas y salidas'!F:F, 'Entrada"&"s y salidas'!D:D=D22, NOT(ISBLANK('Entradas y salidas'!J:J))); INDEX(FILTER('Cortes x inversión'!J:J, 'Cortes x inversión'!D:D=D22),1)}), """"))"),"") | K22: =IF(E22="USD", SUMIF('Entradas y salidas'!D:D, D22, 'Entradas y salidas'!I:I), ) | L22: =IFERROR(__xludf.DUMMYFUNCTION("IF(E22=""USD"", INDEX(FILTER('Cortes x inversión'!G:G, 'Cortes x inversión'!D:D=D22),1), )"),"") | M22: =IF(OR(K22="", L22=""),"", L22 - ABS(K22)) | N22: =IFERROR(__xludf.DUMMYFUNCTION("IF(ISBLANK(D22),"""",IFERROR(XIRR({FILTER('Entradas y salidas'!I:I, 'Entradas y salidas'!D:D=D22, NOT(ISBLANK('Entradas y salidas'!I:I))); INDEX(FILTER('Cortes x inversión'!G:G, 'Cortes x inversión'!D:D=D22),1)}, {FILTER('Entradas y salidas'!F:F, 'Entrada"&"s y salidas'!D:D=D22, NOT(ISBLANK('Entradas y salidas'!I:I))); INDEX(FILTER('Cortes x inversión'!J:J, 'Cortes x inversión'!D:D=D22),1)}), """"))"),"") | P22: =IFERROR(__xludf.DUMMYFUNCTION("IF(K22="""","""", GOOGLEFINANCE(""CURRENCY:USDCOP"")) "),"") | Q22: =IFERROR(__xludf.DUMMYFUNCTION("IF(L22="""","""", GOOGLEFINANCE(""CURRENCY:USDCOP"")) "),"") | R22: =IF(K22="","", L22*P22) | S22: =IF(OR(Q22="", R22=""),"", R22 - ABS(Q22)) | T22: =IFERROR(__xludf.DUMMYFUNCTION("IF(ISBLANK(D22),"""",IFERROR(XIRR({FILTER('Entradas y salidas'!K:K, 'Entradas y salidas'!D:D=D22, NOT(ISBLANK('Entradas y salidas'!K:K))); INDEX(FILTER('Cortes x inversión'!I:I, 'Cortes x inversión'!D:D=D22),1)}, {FILTER('Entradas y salidas'!F:F, 'Entrada"&"s y salidas'!D:D=D22, NOT(ISBLANK('Entradas y salidas'!K:K))); INDEX(FILTER('Cortes x inversión'!J:J, 'Cortes x inversión'!D:D=D22),1)}), """"))"),"")
F23: =IF(E23="COP", SUMIF('Entradas y salidas'!D:D, D23, 'Entradas y salidas'!J:J), ) | G23: =IFERROR(__xludf.DUMMYFUNCTION("IF(E23=""COP"", INDEX(FILTER('Cortes x inversión'!F:F, 'Cortes x inversión'!D:D=D23),1), )"),"") | H23: =IF(OR(F23="", G23=""),"", G23 - ABS(F23)) | I23: =IFERROR(__xludf.DUMMYFUNCTION("IF(ISBLANK(D23),"""",IFERROR(XIRR({FILTER('Entradas y salidas'!J:J, 'Entradas y salidas'!D:D=D23, NOT(ISBLANK('Entradas y salidas'!J:J))); INDEX(FILTER('Cortes x inversión'!F:F, 'Cortes x inversión'!D:D=D23),1)}, {FILTER('Entradas y salidas'!F:F, 'Entrada"&"s y salidas'!D:D=D23, NOT(ISBLANK('Entradas y salidas'!J:J))); INDEX(FILTER('Cortes x inversión'!J:J, 'Cortes x inversión'!D:D=D23),1)}), """"))"),"") | K23: =IF(E23="USD", SUMIF('Entradas y salidas'!D:D, D23, 'Entradas y salidas'!I:I), ) | L23: =IFERROR(__xludf.DUMMYFUNCTION("IF(E23=""USD"", INDEX(FILTER('Cortes x inversión'!G:G, 'Cortes x inversión'!D:D=D23),1), )"),"") | M23: =IF(OR(K23="", L23=""),"", L23 - ABS(K23)) | N23: =IFERROR(__xludf.DUMMYFUNCTION("IF(ISBLANK(D23),"""",IFERROR(XIRR({FILTER('Entradas y salidas'!I:I, 'Entradas y salidas'!D:D=D23, NOT(ISBLANK('Entradas y salidas'!I:I))); INDEX(FILTER('Cortes x inversión'!G:G, 'Cortes x inversión'!D:D=D23),1)}, {FILTER('Entradas y salidas'!F:F, 'Entrada"&"s y salidas'!D:D=D23, NOT(ISBLANK('Entradas y salidas'!I:I))); INDEX(FILTER('Cortes x inversión'!J:J, 'Cortes x inversión'!D:D=D23),1)}), """"))"),"") | P23: =IFERROR(__xludf.DUMMYFUNCTION("IF(K23="""","""", GOOGLEFINANCE(""CURRENCY:USDCOP"")) "),"") | Q23: =IFERROR(__xludf.DUMMYFUNCTION("IF(L23="""","""", GOOGLEFINANCE(""CURRENCY:USDCOP"")) "),"") | R23: =IF(K23="","", L23*P23) | S23: =IF(OR(Q23="", R23=""),"", R23 - ABS(Q23)) | T23: =IFERROR(__xludf.DUMMYFUNCTION("IF(ISBLANK(D23),"""",IFERROR(XIRR({FILTER('Entradas y salidas'!K:K, 'Entradas y salidas'!D:D=D23, NOT(ISBLANK('Entradas y salidas'!K:K))); INDEX(FILTER('Cortes x inversión'!I:I, 'Cortes x inversión'!D:D=D23),1)}, {FILTER('Entradas y salidas'!F:F, 'Entrada"&"s y salidas'!D:D=D23, NOT(ISBLANK('Entradas y salidas'!K:K))); INDEX(FILTER('Cortes x inversión'!J:J, 'Cortes x inversión'!D:D=D23),1)}), """"))"),"")
F24: =IF(E24="COP", SUMIF('Entradas y salidas'!D:D, D24, 'Entradas y salidas'!J:J), ) | G24: =IFERROR(__xludf.DUMMYFUNCTION("IF(E24=""COP"", INDEX(FILTER('Cortes x inversión'!F:F, 'Cortes x inversión'!D:D=D24),1), )"),"") | H24: =IF(OR(F24="", G24=""),"", G24 - ABS(F24)) | I24: =IFERROR(__xludf.DUMMYFUNCTION("IF(ISBLANK(D24),"""",IFERROR(XIRR({FILTER('Entradas y salidas'!J:J, 'Entradas y salidas'!D:D=D24, NOT(ISBLANK('Entradas y salidas'!J:J))); INDEX(FILTER('Cortes x inversión'!F:F, 'Cortes x inversión'!D:D=D24),1)}, {FILTER('Entradas y salidas'!F:F, 'Entrada"&"s y salidas'!D:D=D24, NOT(ISBLANK('Entradas y salidas'!J:J))); INDEX(FILTER('Cortes x inversión'!J:J, 'Cortes x inversión'!D:D=D24),1)}), """"))"),"") | K24: =IF(E24="USD", SUMIF('Entradas y salidas'!D:D, D24, 'Entradas y salidas'!I:I), ) | L24: =IFERROR(__xludf.DUMMYFUNCTION("IF(E24=""USD"", INDEX(FILTER('Cortes x inversión'!G:G, 'Cortes x inversión'!D:D=D24),1), )"),"") | M24: =IF(OR(K24="", L24=""),"", L24 - ABS(K24)) | N24: =IFERROR(__xludf.DUMMYFUNCTION("IF(ISBLANK(D24),"""",IFERROR(XIRR({FILTER('Entradas y salidas'!I:I, 'Entradas y salidas'!D:D=D24, NOT(ISBLANK('Entradas y salidas'!I:I))); INDEX(FILTER('Cortes x inversión'!G:G, 'Cortes x inversión'!D:D=D24),1)}, {FILTER('Entradas y salidas'!F:F, 'Entrada"&"s y salidas'!D:D=D24, NOT(ISBLANK('Entradas y salidas'!I:I))); INDEX(FILTER('Cortes x inversión'!J:J, 'Cortes x inversión'!D:D=D24),1)}), """"))"),"") | P24: =IFERROR(__xludf.DUMMYFUNCTION("IF(K24="""","""", GOOGLEFINANCE(""CURRENCY:USDCOP"")) "),"") | Q24: =IFERROR(__xludf.DUMMYFUNCTION("IF(L24="""","""", GOOGLEFINANCE(""CURRENCY:USDCOP"")) "),"") | R24: =IF(K24="","", L24*P24) | S24: =IF(OR(Q24="", R24=""),"", R24 - ABS(Q24)) | T24: =IFERROR(__xludf.DUMMYFUNCTION("IF(ISBLANK(D24),"""",IFERROR(XIRR({FILTER('Entradas y salidas'!K:K, 'Entradas y salidas'!D:D=D24, NOT(ISBLANK('Entradas y salidas'!K:K))); INDEX(FILTER('Cortes x inversión'!I:I, 'Cortes x inversión'!D:D=D24),1)}, {FILTER('Entradas y salidas'!F:F, 'Entrada"&"s y salidas'!D:D=D24, NOT(ISBLANK('Entradas y salidas'!K:K))); INDEX(FILTER('Cortes x inversión'!J:J, 'Cortes x inversión'!D:D=D24),1)}), """"))"),"")
F25: =IF(E25="COP", SUMIF('Entradas y salidas'!D:D, D25, 'Entradas y salidas'!J:J), ) | G25: =IFERROR(__xludf.DUMMYFUNCTION("IF(E25=""COP"", INDEX(FILTER('Cortes x inversión'!F:F, 'Cortes x inversión'!D:D=D25),1), )"),"") | H25: =IF(OR(F25="", G25=""),"", G25 - ABS(F25)) | I25: =IFERROR(__xludf.DUMMYFUNCTION("IF(ISBLANK(D25),"""",IFERROR(XIRR({FILTER('Entradas y salidas'!J:J, 'Entradas y salidas'!D:D=D25, NOT(ISBLANK('Entradas y salidas'!J:J))); INDEX(FILTER('Cortes x inversión'!F:F, 'Cortes x inversión'!D:D=D25),1)}, {FILTER('Entradas y salidas'!F:F, 'Entrada"&"s y salidas'!D:D=D25, NOT(ISBLANK('Entradas y salidas'!J:J))); INDEX(FILTER('Cortes x inversión'!J:J, 'Cortes x inversión'!D:D=D25),1)}), """"))"),"") | K25: =IF(E25="USD", SUMIF('Entradas y salidas'!D:D, D25, 'Entradas y salidas'!I:I), ) | L25: =IFERROR(__xludf.DUMMYFUNCTION("IF(E25=""USD"", INDEX(FILTER('Cortes x inversión'!G:G, 'Cortes x inversión'!D:D=D25),1), )"),"") | M25: =IF(OR(K25="", L25=""),"", L25 - ABS(K25)) | N25: =IFERROR(__xludf.DUMMYFUNCTION("IF(ISBLANK(D25),"""",IFERROR(XIRR({FILTER('Entradas y salidas'!I:I, 'Entradas y salidas'!D:D=D25, NOT(ISBLANK('Entradas y salidas'!I:I))); INDEX(FILTER('Cortes x inversión'!G:G, 'Cortes x inversión'!D:D=D25),1)}, {FILTER('Entradas y salidas'!F:F, 'Entrada"&"s y salidas'!D:D=D25, NOT(ISBLANK('Entradas y salidas'!I:I))); INDEX(FILTER('Cortes x inversión'!J:J, 'Cortes x inversión'!D:D=D25),1)}), """"))"),"") | P25: =IFERROR(__xludf.DUMMYFUNCTION("IF(K25="""","""", GOOGLEFINANCE(""CURRENCY:USDCOP"")) "),"") | Q25: =IFERROR(__xludf.DUMMYFUNCTION("IF(L25="""","""", GOOGLEFINANCE(""CURRENCY:USDCOP"")) "),"") | R25: =IF(K25="","", L25*P25) | S25: =IF(OR(Q25="", R25=""),"", R25 - ABS(Q25)) | T25: =IFERROR(__xludf.DUMMYFUNCTION("IF(ISBLANK(D25),"""",IFERROR(XIRR({FILTER('Entradas y salidas'!K:K, 'Entradas y salidas'!D:D=D25, NOT(ISBLANK('Entradas y salidas'!K:K))); INDEX(FILTER('Cortes x inversión'!I:I, 'Cortes x inversión'!D:D=D25),1)}, {FILTER('Entradas y salidas'!F:F, 'Entrada"&"s y salidas'!D:D=D25, NOT(ISBLANK('Entradas y salidas'!K:K))); INDEX(FILTER('Cortes x inversión'!J:J, 'Cortes x inversión'!D:D=D25),1)}), """"))"),"")
F26: =IF(E26="COP", SUMIF('Entradas y salidas'!D:D, D26, 'Entradas y salidas'!J:J), ) | G26: =IFERROR(__xludf.DUMMYFUNCTION("IF(E26=""COP"", INDEX(FILTER('Cortes x inversión'!F:F, 'Cortes x inversión'!D:D=D26),1), )"),"") | H26: =IF(OR(F26="", G26=""),"", G26 - ABS(F26)) | I26: =IFERROR(__xludf.DUMMYFUNCTION("IF(ISBLANK(D26),"""",IFERROR(XIRR({FILTER('Entradas y salidas'!J:J, 'Entradas y salidas'!D:D=D26, NOT(ISBLANK('Entradas y salidas'!J:J))); INDEX(FILTER('Cortes x inversión'!F:F, 'Cortes x inversión'!D:D=D26),1)}, {FILTER('Entradas y salidas'!F:F, 'Entrada"&"s y salidas'!D:D=D26, NOT(ISBLANK('Entradas y salidas'!J:J))); INDEX(FILTER('Cortes x inversión'!J:J, 'Cortes x inversión'!D:D=D26),1)}), """"))"),"") | K26: =IF(E26="USD", SUMIF('Entradas y salidas'!D:D, D26, 'Entradas y salidas'!I:I), ) | L26: =IFERROR(__xludf.DUMMYFUNCTION("IF(E26=""USD"", INDEX(FILTER('Cortes x inversión'!G:G, 'Cortes x inversión'!D:D=D26),1), )"),"") | M26: =IF(OR(K26="", L26=""),"", L26 - ABS(K26)) | N26: =IFERROR(__xludf.DUMMYFUNCTION("IF(ISBLANK(D26),"""",IFERROR(XIRR({FILTER('Entradas y salidas'!I:I, 'Entradas y salidas'!D:D=D26, NOT(ISBLANK('Entradas y salidas'!I:I))); INDEX(FILTER('Cortes x inversión'!G:G, 'Cortes x inversión'!D:D=D26),1)}, {FILTER('Entradas y salidas'!F:F, 'Entrada"&"s y salidas'!D:D=D26, NOT(ISBLANK('Entradas y salidas'!I:I))); INDEX(FILTER('Cortes x inversión'!J:J, 'Cortes x inversión'!D:D=D26),1)}), """"))"),"") | P26: =IFERROR(__xludf.DUMMYFUNCTION("IF(K26="""","""", GOOGLEFINANCE(""CURRENCY:USDCOP"")) "),"") | Q26: =IFERROR(__xludf.DUMMYFUNCTION("IF(L26="""","""", GOOGLEFINANCE(""CURRENCY:USDCOP"")) "),"") | R26: =IF(K26="","", L26*P26) | S26: =IF(OR(Q26="", R26=""),"", R26 - ABS(Q26)) | T26: =IFERROR(__xludf.DUMMYFUNCTION("IF(ISBLANK(D26),"""",IFERROR(XIRR({FILTER('Entradas y salidas'!K:K, 'Entradas y salidas'!D:D=D26, NOT(ISBLANK('Entradas y salidas'!K:K))); INDEX(FILTER('Cortes x inversión'!I:I, 'Cortes x inversión'!D:D=D26),1)}, {FILTER('Entradas y salidas'!F:F, 'Entrada"&"s y salidas'!D:D=D26, NOT(ISBLANK('Entradas y salidas'!K:K))); INDEX(FILTER('Cortes x inversión'!J:J, 'Cortes x inversión'!D:D=D26),1)}), """"))"),"")
F27: =IF(E27="COP", SUMIF('Entradas y salidas'!D:D, D27, 'Entradas y salidas'!J:J), ) | G27: =IFERROR(__xludf.DUMMYFUNCTION("IF(E27=""COP"", INDEX(FILTER('Cortes x inversión'!F:F, 'Cortes x inversión'!D:D=D27),1), )"),"") | H27: =IF(OR(F27="", G27=""),"", G27 - ABS(F27)) | I27: =IFERROR(__xludf.DUMMYFUNCTION("IF(ISBLANK(D27),"""",IFERROR(XIRR({FILTER('Entradas y salidas'!J:J, 'Entradas y salidas'!D:D=D27, NOT(ISBLANK('Entradas y salidas'!J:J))); INDEX(FILTER('Cortes x inversión'!F:F, 'Cortes x inversión'!D:D=D27),1)}, {FILTER('Entradas y salidas'!F:F, 'Entrada"&"s y salidas'!D:D=D27, NOT(ISBLANK('Entradas y salidas'!J:J))); INDEX(FILTER('Cortes x inversión'!J:J, 'Cortes x inversión'!D:D=D27),1)}), """"))"),"") | K27: =IF(E27="USD", SUMIF('Entradas y salidas'!D:D, D27, 'Entradas y salidas'!I:I), ) | L27: =IFERROR(__xludf.DUMMYFUNCTION("IF(E27=""USD"", INDEX(FILTER('Cortes x inversión'!G:G, 'Cortes x inversión'!D:D=D27),1), )"),"") | M27: =IF(OR(K27="", L27=""),"", L27 - ABS(K27)) | N27: =IFERROR(__xludf.DUMMYFUNCTION("IF(ISBLANK(D27),"""",IFERROR(XIRR({FILTER('Entradas y salidas'!I:I, 'Entradas y salidas'!D:D=D27, NOT(ISBLANK('Entradas y salidas'!I:I))); INDEX(FILTER('Cortes x inversión'!G:G, 'Cortes x inversión'!D:D=D27),1)}, {FILTER('Entradas y salidas'!F:F, 'Entrada"&"s y salidas'!D:D=D27, NOT(ISBLANK('Entradas y salidas'!I:I))); INDEX(FILTER('Cortes x inversión'!J:J, 'Cortes x inversión'!D:D=D27),1)}), """"))"),"") | P27: =IFERROR(__xludf.DUMMYFUNCTION("IF(K27="""","""", GOOGLEFINANCE(""CURRENCY:USDCOP"")) "),"") | Q27: =IFERROR(__xludf.DUMMYFUNCTION("IF(L27="""","""", GOOGLEFINANCE(""CURRENCY:USDCOP"")) "),"") | R27: =IF(K27="","", L27*P27) | S27: =IF(OR(Q27="", R27=""),"", R27 - ABS(Q27)) | T27: =IFERROR(__xludf.DUMMYFUNCTION("IF(ISBLANK(D27),"""",IFERROR(XIRR({FILTER('Entradas y salidas'!K:K, 'Entradas y salidas'!D:D=D27, NOT(ISBLANK('Entradas y salidas'!K:K))); INDEX(FILTER('Cortes x inversión'!I:I, 'Cortes x inversión'!D:D=D27),1)}, {FILTER('Entradas y salidas'!F:F, 'Entrada"&"s y salidas'!D:D=D27, NOT(ISBLANK('Entradas y salidas'!K:K))); INDEX(FILTER('Cortes x inversión'!J:J, 'Cortes x inversión'!D:D=D27),1)}), """"))"),"")
F28: =IF(E28="COP", SUMIF('Entradas y salidas'!D:D, D28, 'Entradas y salidas'!J:J), ) | G28: =IFERROR(__xludf.DUMMYFUNCTION("IF(E28=""COP"", INDEX(FILTER('Cortes x inversión'!F:F, 'Cortes x inversión'!D:D=D28),1), )"),"") | H28: =IF(OR(F28="", G28=""),"", G28 - ABS(F28)) | I28: =IFERROR(__xludf.DUMMYFUNCTION("IF(ISBLANK(D28),"""",IFERROR(XIRR({FILTER('Entradas y salidas'!J:J, 'Entradas y salidas'!D:D=D28, NOT(ISBLANK('Entradas y salidas'!J:J))); INDEX(FILTER('Cortes x inversión'!F:F, 'Cortes x inversión'!D:D=D28),1)}, {FILTER('Entradas y salidas'!F:F, 'Entrada"&"s y salidas'!D:D=D28, NOT(ISBLANK('Entradas y salidas'!J:J))); INDEX(FILTER('Cortes x inversión'!J:J, 'Cortes x inversión'!D:D=D28),1)}), """"))"),"") | K28: =IF(E28="USD", SUMIF('Entradas y salidas'!D:D, D28, 'Entradas y salidas'!I:I), ) | L28: =IFERROR(__xludf.DUMMYFUNCTION("IF(E28=""USD"", INDEX(FILTER('Cortes x inversión'!G:G, 'Cortes x inversión'!D:D=D28),1), )"),"") | M28: =IF(OR(K28="", L28=""),"", L28 - ABS(K28)) | N28: =IFERROR(__xludf.DUMMYFUNCTION("IF(ISBLANK(D28),"""",IFERROR(XIRR({FILTER('Entradas y salidas'!I:I, 'Entradas y salidas'!D:D=D28, NOT(ISBLANK('Entradas y salidas'!I:I))); INDEX(FILTER('Cortes x inversión'!G:G, 'Cortes x inversión'!D:D=D28),1)}, {FILTER('Entradas y salidas'!F:F, 'Entrada"&"s y salidas'!D:D=D28, NOT(ISBLANK('Entradas y salidas'!I:I))); INDEX(FILTER('Cortes x inversión'!J:J, 'Cortes x inversión'!D:D=D28),1)}), """"))"),"") | P28: =IFERROR(__xludf.DUMMYFUNCTION("IF(K28="""","""", GOOGLEFINANCE(""CURRENCY:USDCOP"")) "),"") | Q28: =IFERROR(__xludf.DUMMYFUNCTION("IF(L28="""","""", GOOGLEFINANCE(""CURRENCY:USDCOP"")) "),"") | R28: =IF(K28="","", L28*P28) | S28: =IF(OR(Q28="", R28=""),"", R28 - ABS(Q28)) | T28: =IFERROR(__xludf.DUMMYFUNCTION("IF(ISBLANK(D28),"""",IFERROR(XIRR({FILTER('Entradas y salidas'!K:K, 'Entradas y salidas'!D:D=D28, NOT(ISBLANK('Entradas y salidas'!K:K))); INDEX(FILTER('Cortes x inversión'!I:I, 'Cortes x inversión'!D:D=D28),1)}, {FILTER('Entradas y salidas'!F:F, 'Entrada"&"s y salidas'!D:D=D28, NOT(ISBLANK('Entradas y salidas'!K:K))); INDEX(FILTER('Cortes x inversión'!J:J, 'Cortes x inversión'!D:D=D28),1)}), """"))"),"")
F29: =IF(E29="COP", SUMIF('Entradas y salidas'!D:D, D29, 'Entradas y salidas'!J:J), ) | G29: =IFERROR(__xludf.DUMMYFUNCTION("IF(E29=""COP"", INDEX(FILTER('Cortes x inversión'!F:F, 'Cortes x inversión'!D:D=D29),1), )"),"") | H29: =IF(OR(F29="", G29=""),"", G29 - ABS(F29)) | I29: =IFERROR(__xludf.DUMMYFUNCTION("IF(ISBLANK(D29),"""",IFERROR(XIRR({FILTER('Entradas y salidas'!J:J, 'Entradas y salidas'!D:D=D29, NOT(ISBLANK('Entradas y salidas'!J:J))); INDEX(FILTER('Cortes x inversión'!F:F, 'Cortes x inversión'!D:D=D29),1)}, {FILTER('Entradas y salidas'!F:F, 'Entrada"&"s y salidas'!D:D=D29, NOT(ISBLANK('Entradas y salidas'!J:J))); INDEX(FILTER('Cortes x inversión'!J:J, 'Cortes x inversión'!D:D=D29),1)}), """"))"),"") | K29: =IF(E29="USD", SUMIF('Entradas y salidas'!D:D, D29, 'Entradas y salidas'!I:I), ) | L29: =IFERROR(__xludf.DUMMYFUNCTION("IF(E29=""USD"", INDEX(FILTER('Cortes x inversión'!G:G, 'Cortes x inversión'!D:D=D29),1), )"),"") | M29: =IF(OR(K29="", L29=""),"", L29 - ABS(K29)) | N29: =IFERROR(__xludf.DUMMYFUNCTION("IF(ISBLANK(D29),"""",IFERROR(XIRR({FILTER('Entradas y salidas'!I:I, 'Entradas y salidas'!D:D=D29, NOT(ISBLANK('Entradas y salidas'!I:I))); INDEX(FILTER('Cortes x inversión'!G:G, 'Cortes x inversión'!D:D=D29),1)}, {FILTER('Entradas y salidas'!F:F, 'Entrada"&"s y salidas'!D:D=D29, NOT(ISBLANK('Entradas y salidas'!I:I))); INDEX(FILTER('Cortes x inversión'!J:J, 'Cortes x inversión'!D:D=D29),1)}), """"))"),"") | P29: =IFERROR(__xludf.DUMMYFUNCTION("IF(K29="""","""", GOOGLEFINANCE(""CURRENCY:USDCOP"")) "),"") | Q29: =IFERROR(__xludf.DUMMYFUNCTION("IF(L29="""","""", GOOGLEFINANCE(""CURRENCY:USDCOP"")) "),"") | R29: =IF(K29="","", L29*P29) | S29: =IF(OR(Q29="", R29=""),"", R29 - ABS(Q29)) | T29: =IFERROR(__xludf.DUMMYFUNCTION("IF(ISBLANK(D29),"""",IFERROR(XIRR({FILTER('Entradas y salidas'!K:K, 'Entradas y salidas'!D:D=D29, NOT(ISBLANK('Entradas y salidas'!K:K))); INDEX(FILTER('Cortes x inversión'!I:I, 'Cortes x inversión'!D:D=D29),1)}, {FILTER('Entradas y salidas'!F:F, 'Entrada"&"s y salidas'!D:D=D29, NOT(ISBLANK('Entradas y salidas'!K:K))); INDEX(FILTER('Cortes x inversión'!J:J, 'Cortes x inversión'!D:D=D29),1)}), """"))"),"")
F30: =IF(E30="COP", SUMIF('Entradas y salidas'!D:D, D30, 'Entradas y salidas'!J:J), ) | G30: =IFERROR(__xludf.DUMMYFUNCTION("IF(E30=""COP"", INDEX(FILTER('Cortes x inversión'!F:F, 'Cortes x inversión'!D:D=D30),1), )"),"") | H30: =IF(OR(F30="", G30=""),"", G30 - ABS(F30)) | I30: =IFERROR(__xludf.DUMMYFUNCTION("IF(ISBLANK(D30),"""",IFERROR(XIRR({FILTER('Entradas y salidas'!J:J, 'Entradas y salidas'!D:D=D30, NOT(ISBLANK('Entradas y salidas'!J:J))); INDEX(FILTER('Cortes x inversión'!F:F, 'Cortes x inversión'!D:D=D30),1)}, {FILTER('Entradas y salidas'!F:F, 'Entrada"&"s y salidas'!D:D=D30, NOT(ISBLANK('Entradas y salidas'!J:J))); INDEX(FILTER('Cortes x inversión'!J:J, 'Cortes x inversión'!D:D=D30),1)}), """"))"),"") | K30: =IF(E30="USD", SUMIF('Entradas y salidas'!D:D, D30, 'Entradas y salidas'!I:I), ) | L30: =IFERROR(__xludf.DUMMYFUNCTION("IF(E30=""USD"", INDEX(FILTER('Cortes x inversión'!G:G, 'Cortes x inversión'!D:D=D30),1), )"),"") | M30: =IF(OR(K30="", L30=""),"", L30 - ABS(K30)) | N30: =IFERROR(__xludf.DUMMYFUNCTION("IF(ISBLANK(D30),"""",IFERROR(XIRR({FILTER('Entradas y salidas'!I:I, 'Entradas y salidas'!D:D=D30, NOT(ISBLANK('Entradas y salidas'!I:I))); INDEX(FILTER('Cortes x inversión'!G:G, 'Cortes x inversión'!D:D=D30),1)}, {FILTER('Entradas y salidas'!F:F, 'Entrada"&"s y salidas'!D:D=D30, NOT(ISBLANK('Entradas y salidas'!I:I))); INDEX(FILTER('Cortes x inversión'!J:J, 'Cortes x inversión'!D:D=D30),1)}), """"))"),"") | P30: =IFERROR(__xludf.DUMMYFUNCTION("IF(K30="""","""", GOOGLEFINANCE(""CURRENCY:USDCOP"")) "),"") | Q30: =IFERROR(__xludf.DUMMYFUNCTION("IF(L30="""","""", GOOGLEFINANCE(""CURRENCY:USDCOP"")) "),"") | R30: =IF(K30="","", L30*P30) | S30: =IF(OR(Q30="", R30=""),"", R30 - ABS(Q30)) | T30: =IFERROR(__xludf.DUMMYFUNCTION("IF(ISBLANK(D30),"""",IFERROR(XIRR({FILTER('Entradas y salidas'!K:K, 'Entradas y salidas'!D:D=D30, NOT(ISBLANK('Entradas y salidas'!K:K))); INDEX(FILTER('Cortes x inversión'!I:I, 'Cortes x inversión'!D:D=D30),1)}, {FILTER('Entradas y salidas'!F:F, 'Entrada"&"s y salidas'!D:D=D30, NOT(ISBLANK('Entradas y salidas'!K:K))); INDEX(FILTER('Cortes x inversión'!J:J, 'Cortes x inversión'!D:D=D30),1)}), """"))"),"")
F31: =IF(E31="COP", SUMIF('Entradas y salidas'!D:D, D31, 'Entradas y salidas'!J:J), ) | G31: =IFERROR(__xludf.DUMMYFUNCTION("IF(E31=""COP"", INDEX(FILTER('Cortes x inversión'!F:F, 'Cortes x inversión'!D:D=D31),1), )"),"") | H31: =IF(OR(F31="", G31=""),"", G31 - ABS(F31)) | I31: =IFERROR(__xludf.DUMMYFUNCTION("IF(ISBLANK(D31),"""",IFERROR(XIRR({FILTER('Entradas y salidas'!J:J, 'Entradas y salidas'!D:D=D31, NOT(ISBLANK('Entradas y salidas'!J:J))); INDEX(FILTER('Cortes x inversión'!F:F, 'Cortes x inversión'!D:D=D31),1)}, {FILTER('Entradas y salidas'!F:F, 'Entrada"&"s y salidas'!D:D=D31, NOT(ISBLANK('Entradas y salidas'!J:J))); INDEX(FILTER('Cortes x inversión'!J:J, 'Cortes x inversión'!D:D=D31),1)}), """"))"),"") | K31: =IF(E31="USD", SUMIF('Entradas y salidas'!D:D, D31, 'Entradas y salidas'!I:I), ) | L31: =IFERROR(__xludf.DUMMYFUNCTION("IF(E31=""USD"", INDEX(FILTER('Cortes x inversión'!G:G, 'Cortes x inversión'!D:D=D31),1), )"),"") | M31: =IF(OR(K31="", L31=""),"", L31 - ABS(K31)) | N31: =IFERROR(__xludf.DUMMYFUNCTION("IF(ISBLANK(D31),"""",IFERROR(XIRR({FILTER('Entradas y salidas'!I:I, 'Entradas y salidas'!D:D=D31, NOT(ISBLANK('Entradas y salidas'!I:I))); INDEX(FILTER('Cortes x inversión'!G:G, 'Cortes x inversión'!D:D=D31),1)}, {FILTER('Entradas y salidas'!F:F, 'Entrada"&"s y salidas'!D:D=D31, NOT(ISBLANK('Entradas y salidas'!I:I))); INDEX(FILTER('Cortes x inversión'!J:J, 'Cortes x inversión'!D:D=D31),1)}), """"))"),"") | P31: =IFERROR(__xludf.DUMMYFUNCTION("IF(K31="""","""", GOOGLEFINANCE(""CURRENCY:USDCOP"")) "),"") | Q31: =IFERROR(__xludf.DUMMYFUNCTION("IF(L31="""","""", GOOGLEFINANCE(""CURRENCY:USDCOP"")) "),"") | R31: =IF(K31="","", L31*P31) | S31: =IF(OR(Q31="", R31=""),"", R31 - ABS(Q31)) | T31: =IFERROR(__xludf.DUMMYFUNCTION("IF(ISBLANK(D31),"""",IFERROR(XIRR({FILTER('Entradas y salidas'!K:K, 'Entradas y salidas'!D:D=D31, NOT(ISBLANK('Entradas y salidas'!K:K))); INDEX(FILTER('Cortes x inversión'!I:I, 'Cortes x inversión'!D:D=D31),1)}, {FILTER('Entradas y salidas'!F:F, 'Entrada"&"s y salidas'!D:D=D31, NOT(ISBLANK('Entradas y salidas'!K:K))); INDEX(FILTER('Cortes x inversión'!J:J, 'Cortes x inversión'!D:D=D31),1)}), """"))"),"")
F32: =IF(E32="COP", SUMIF('Entradas y salidas'!D:D, D32, 'Entradas y salidas'!J:J), ) | G32: =IFERROR(__xludf.DUMMYFUNCTION("IF(E32=""COP"", INDEX(FILTER('Cortes x inversión'!F:F, 'Cortes x inversión'!D:D=D32),1), )"),"") | H32: =IF(OR(F32="", G32=""),"", G32 - ABS(F32)) | I32: =IFERROR(__xludf.DUMMYFUNCTION("IF(ISBLANK(D32),"""",IFERROR(XIRR({FILTER('Entradas y salidas'!J:J, 'Entradas y salidas'!D:D=D32, NOT(ISBLANK('Entradas y salidas'!J:J))); INDEX(FILTER('Cortes x inversión'!F:F, 'Cortes x inversión'!D:D=D32),1)}, {FILTER('Entradas y salidas'!F:F, 'Entrada"&"s y salidas'!D:D=D32, NOT(ISBLANK('Entradas y salidas'!J:J))); INDEX(FILTER('Cortes x inversión'!J:J, 'Cortes x inversión'!D:D=D32),1)}), """"))"),"") | K32: =IF(E32="USD", SUMIF('Entradas y salidas'!D:D, D32, 'Entradas y salidas'!I:I), ) | L32: =IFERROR(__xludf.DUMMYFUNCTION("IF(E32=""USD"", INDEX(FILTER('Cortes x inversión'!G:G, 'Cortes x inversión'!D:D=D32),1), )"),"") | M32: =IF(OR(K32="", L32=""),"", L32 - ABS(K32)) | N32: =IFERROR(__xludf.DUMMYFUNCTION("IF(ISBLANK(D32),"""",IFERROR(XIRR({FILTER('Entradas y salidas'!I:I, 'Entradas y salidas'!D:D=D32, NOT(ISBLANK('Entradas y salidas'!I:I))); INDEX(FILTER('Cortes x inversión'!G:G, 'Cortes x inversión'!D:D=D32),1)}, {FILTER('Entradas y salidas'!F:F, 'Entrada"&"s y salidas'!D:D=D32, NOT(ISBLANK('Entradas y salidas'!I:I))); INDEX(FILTER('Cortes x inversión'!J:J, 'Cortes x inversión'!D:D=D32),1)}), """"))"),"") | P32: =IFERROR(__xludf.DUMMYFUNCTION("IF(K32="""","""", GOOGLEFINANCE(""CURRENCY:USDCOP"")) "),"") | Q32: =IFERROR(__xludf.DUMMYFUNCTION("IF(L32="""","""", GOOGLEFINANCE(""CURRENCY:USDCOP"")) "),"") | R32: =IF(K32="","", L32*P32) | S32: =IF(OR(Q32="", R32=""),"", R32 - ABS(Q32)) | T32: =IFERROR(__xludf.DUMMYFUNCTION("IF(ISBLANK(D32),"""",IFERROR(XIRR({FILTER('Entradas y salidas'!K:K, 'Entradas y salidas'!D:D=D32, NOT(ISBLANK('Entradas y salidas'!K:K))); INDEX(FILTER('Cortes x inversión'!I:I, 'Cortes x inversión'!D:D=D32),1)}, {FILTER('Entradas y salidas'!F:F, 'Entrada"&"s y salidas'!D:D=D32, NOT(ISBLANK('Entradas y salidas'!K:K))); INDEX(FILTER('Cortes x inversión'!J:J, 'Cortes x inversión'!D:D=D32),1)}), """"))"),"")
F33: =IF(E33="COP", SUMIF('Entradas y salidas'!D:D, D33, 'Entradas y salidas'!J:J), ) | G33: =IFERROR(__xludf.DUMMYFUNCTION("IF(E33=""COP"", INDEX(FILTER('Cortes x inversión'!F:F, 'Cortes x inversión'!D:D=D33),1), )"),"") | H33: =IF(OR(F33="", G33=""),"", G33 - ABS(F33)) | I33: =IFERROR(__xludf.DUMMYFUNCTION("IF(ISBLANK(D33),"""",IFERROR(XIRR({FILTER('Entradas y salidas'!J:J, 'Entradas y salidas'!D:D=D33, NOT(ISBLANK('Entradas y salidas'!J:J))); INDEX(FILTER('Cortes x inversión'!F:F, 'Cortes x inversión'!D:D=D33),1)}, {FILTER('Entradas y salidas'!F:F, 'Entrada"&"s y salidas'!D:D=D33, NOT(ISBLANK('Entradas y salidas'!J:J))); INDEX(FILTER('Cortes x inversión'!J:J, 'Cortes x inversión'!D:D=D33),1)}), """"))"),"") | K33: =IF(E33="USD", SUMIF('Entradas y salidas'!D:D, D33, 'Entradas y salidas'!I:I), ) | L33: =IFERROR(__xludf.DUMMYFUNCTION("IF(E33=""USD"", INDEX(FILTER('Cortes x inversión'!G:G, 'Cortes x inversión'!D:D=D33),1), )"),"") | M33: =IF(OR(K33="", L33=""),"", L33 - ABS(K33)) | N33: =IFERROR(__xludf.DUMMYFUNCTION("IF(ISBLANK(D33),"""",IFERROR(XIRR({FILTER('Entradas y salidas'!I:I, 'Entradas y salidas'!D:D=D33, NOT(ISBLANK('Entradas y salidas'!I:I))); INDEX(FILTER('Cortes x inversión'!G:G, 'Cortes x inversión'!D:D=D33),1)}, {FILTER('Entradas y salidas'!F:F, 'Entrada"&"s y salidas'!D:D=D33, NOT(ISBLANK('Entradas y salidas'!I:I))); INDEX(FILTER('Cortes x inversión'!J:J, 'Cortes x inversión'!D:D=D33),1)}), """"))"),"") | P33: =IFERROR(__xludf.DUMMYFUNCTION("IF(K33="""","""", GOOGLEFINANCE(""CURRENCY:USDCOP"")) "),"") | Q33: =IFERROR(__xludf.DUMMYFUNCTION("IF(L33="""","""", GOOGLEFINANCE(""CURRENCY:USDCOP"")) "),"") | R33: =IF(K33="","", L33*P33) | S33: =IF(OR(Q33="", R33=""),"", R33 - ABS(Q33)) | T33: =IFERROR(__xludf.DUMMYFUNCTION("IF(ISBLANK(D33),"""",IFERROR(XIRR({FILTER('Entradas y salidas'!K:K, 'Entradas y salidas'!D:D=D33, NOT(ISBLANK('Entradas y salidas'!K:K))); INDEX(FILTER('Cortes x inversión'!I:I, 'Cortes x inversión'!D:D=D33),1)}, {FILTER('Entradas y salidas'!F:F, 'Entrada"&"s y salidas'!D:D=D33, NOT(ISBLANK('Entradas y salidas'!K:K))); INDEX(FILTER('Cortes x inversión'!J:J, 'Cortes x inversión'!D:D=D33),1)}), """"))"),"")
F34: =IF(E34="COP", SUMIF('Entradas y salidas'!D:D, D34, 'Entradas y salidas'!J:J), ) | G34: =IFERROR(__xludf.DUMMYFUNCTION("IF(E34=""COP"", INDEX(FILTER('Cortes x inversión'!F:F, 'Cortes x inversión'!D:D=D34),1), )"),"") | H34: =IF(OR(F34="", G34=""),"", G34 - ABS(F34)) | I34: =IFERROR(__xludf.DUMMYFUNCTION("IF(ISBLANK(D34),"""",IFERROR(XIRR({FILTER('Entradas y salidas'!J:J, 'Entradas y salidas'!D:D=D34, NOT(ISBLANK('Entradas y salidas'!J:J))); INDEX(FILTER('Cortes x inversión'!F:F, 'Cortes x inversión'!D:D=D34),1)}, {FILTER('Entradas y salidas'!F:F, 'Entrada"&"s y salidas'!D:D=D34, NOT(ISBLANK('Entradas y salidas'!J:J))); INDEX(FILTER('Cortes x inversión'!J:J, 'Cortes x inversión'!D:D=D34),1)}), """"))"),"") | K34: =IF(E34="USD", SUMIF('Entradas y salidas'!D:D, D34, 'Entradas y salidas'!I:I), ) | L34: =IFERROR(__xludf.DUMMYFUNCTION("IF(E34=""USD"", INDEX(FILTER('Cortes x inversión'!G:G, 'Cortes x inversión'!D:D=D34),1), )"),"") | M34: =IF(OR(K34="", L34=""),"", L34 - ABS(K34)) | N34: =IFERROR(__xludf.DUMMYFUNCTION("IF(ISBLANK(D34),"""",IFERROR(XIRR({FILTER('Entradas y salidas'!I:I, 'Entradas y salidas'!D:D=D34, NOT(ISBLANK('Entradas y salidas'!I:I))); INDEX(FILTER('Cortes x inversión'!G:G, 'Cortes x inversión'!D:D=D34),1)}, {FILTER('Entradas y salidas'!F:F, 'Entrada"&"s y salidas'!D:D=D34, NOT(ISBLANK('Entradas y salidas'!I:I))); INDEX(FILTER('Cortes x inversión'!J:J, 'Cortes x inversión'!D:D=D34),1)}), """"))"),"") | P34: =IFERROR(__xludf.DUMMYFUNCTION("IF(K34="""","""", GOOGLEFINANCE(""CURRENCY:USDCOP"")) "),"") | Q34: =IFERROR(__xludf.DUMMYFUNCTION("IF(L34="""","""", GOOGLEFINANCE(""CURRENCY:USDCOP"")) "),"") | R34: =IF(K34="","", L34*P34) | S34: =IF(OR(Q34="", R34=""),"", R34 - ABS(Q34)) | T34: =IFERROR(__xludf.DUMMYFUNCTION("IF(ISBLANK(D34),"""",IFERROR(XIRR({FILTER('Entradas y salidas'!K:K, 'Entradas y salidas'!D:D=D34, NOT(ISBLANK('Entradas y salidas'!K:K))); INDEX(FILTER('Cortes x inversión'!I:I, 'Cortes x inversión'!D:D=D34),1)}, {FILTER('Entradas y salidas'!F:F, 'Entrada"&"s y salidas'!D:D=D34, NOT(ISBLANK('Entradas y salidas'!K:K))); INDEX(FILTER('Cortes x inversión'!J:J, 'Cortes x inversión'!D:D=D34),1)}), """"))"),"")
F35: =IF(E35="COP", SUMIF('Entradas y salidas'!D:D, D35, 'Entradas y salidas'!J:J), ) | G35: =IFERROR(__xludf.DUMMYFUNCTION("IF(E35=""COP"", INDEX(FILTER('Cortes x inversión'!F:F, 'Cortes x inversión'!D:D=D35),1), )"),"") | H35: =IF(OR(F35="", G35=""),"", G35 - ABS(F35)) | I35: =IFERROR(__xludf.DUMMYFUNCTION("IF(ISBLANK(D35),"""",IFERROR(XIRR({FILTER('Entradas y salidas'!J:J, 'Entradas y salidas'!D:D=D35, NOT(ISBLANK('Entradas y salidas'!J:J))); INDEX(FILTER('Cortes x inversión'!F:F, 'Cortes x inversión'!D:D=D35),1)}, {FILTER('Entradas y salidas'!F:F, 'Entrada"&"s y salidas'!D:D=D35, NOT(ISBLANK('Entradas y salidas'!J:J))); INDEX(FILTER('Cortes x inversión'!J:J, 'Cortes x inversión'!D:D=D35),1)}), """"))"),"") | K35: =IF(E35="USD", SUMIF('Entradas y salidas'!D:D, D35, 'Entradas y salidas'!I:I), ) | L35: =IFERROR(__xludf.DUMMYFUNCTION("IF(E35=""USD"", INDEX(FILTER('Cortes x inversión'!G:G, 'Cortes x inversión'!D:D=D35),1), )"),"") | M35: =IF(OR(K35="", L35=""),"", L35 - ABS(K35)) | N35: =IFERROR(__xludf.DUMMYFUNCTION("IF(ISBLANK(D35),"""",IFERROR(XIRR({FILTER('Entradas y salidas'!I:I, 'Entradas y salidas'!D:D=D35, NOT(ISBLANK('Entradas y salidas'!I:I))); INDEX(FILTER('Cortes x inversión'!G:G, 'Cortes x inversión'!D:D=D35),1)}, {FILTER('Entradas y salidas'!F:F, 'Entrada"&"s y salidas'!D:D=D35, NOT(ISBLANK('Entradas y salidas'!I:I))); INDEX(FILTER('Cortes x inversión'!J:J, 'Cortes x inversión'!D:D=D35),1)}), """"))"),"") | P35: =IFERROR(__xludf.DUMMYFUNCTION("IF(K35="""","""", GOOGLEFINANCE(""CURRENCY:USDCOP"")) "),"") | Q35: =IFERROR(__xludf.DUMMYFUNCTION("IF(L35="""","""", GOOGLEFINANCE(""CURRENCY:USDCOP"")) "),"") | R35: =IF(K35="","", L35*P35) | S35: =IF(OR(Q35="", R35=""),"", R35 - ABS(Q35)) | T35: =IFERROR(__xludf.DUMMYFUNCTION("IF(ISBLANK(D35),"""",IFERROR(XIRR({FILTER('Entradas y salidas'!K:K, 'Entradas y salidas'!D:D=D35, NOT(ISBLANK('Entradas y salidas'!K:K))); INDEX(FILTER('Cortes x inversión'!I:I, 'Cortes x inversión'!D:D=D35),1)}, {FILTER('Entradas y salidas'!F:F, 'Entrada"&"s y salidas'!D:D=D35, NOT(ISBLANK('Entradas y salidas'!K:K))); INDEX(FILTER('Cortes x inversión'!J:J, 'Cortes x inversión'!D:D=D35),1)}), """"))"),"")
F36: =IF(E36="COP", SUMIF('Entradas y salidas'!D:D, D36, 'Entradas y salidas'!J:J), ) | G36: =IFERROR(__xludf.DUMMYFUNCTION("IF(E36=""COP"", INDEX(FILTER('Cortes x inversión'!F:F, 'Cortes x inversión'!D:D=D36),1), )"),"") | H36: =IF(OR(F36="", G36=""),"", G36 - ABS(F36)) | I36: =IFERROR(__xludf.DUMMYFUNCTION("IF(ISBLANK(D36),"""",IFERROR(XIRR({FILTER('Entradas y salidas'!J:J, 'Entradas y salidas'!D:D=D36, NOT(ISBLANK('Entradas y salidas'!J:J))); INDEX(FILTER('Cortes x inversión'!F:F, 'Cortes x inversión'!D:D=D36),1)}, {FILTER('Entradas y salidas'!F:F, 'Entrada"&"s y salidas'!D:D=D36, NOT(ISBLANK('Entradas y salidas'!J:J))); INDEX(FILTER('Cortes x inversión'!J:J, 'Cortes x inversión'!D:D=D36),1)}), """"))"),"") | K36: =IF(E36="USD", SUMIF('Entradas y salidas'!D:D, D36, 'Entradas y salidas'!I:I), ) | L36: =IFERROR(__xludf.DUMMYFUNCTION("IF(E36=""USD"", INDEX(FILTER('Cortes x inversión'!G:G, 'Cortes x inversión'!D:D=D36),1), )"),"") | M36: =IF(OR(K36="", L36=""),"", L36 - ABS(K36)) | N36: =IFERROR(__xludf.DUMMYFUNCTION("IF(ISBLANK(D36),"""",IFERROR(XIRR({FILTER('Entradas y salidas'!I:I, 'Entradas y salidas'!D:D=D36, NOT(ISBLANK('Entradas y salidas'!I:I))); INDEX(FILTER('Cortes x inversión'!G:G, 'Cortes x inversión'!D:D=D36),1)}, {FILTER('Entradas y salidas'!F:F, 'Entrada"&"s y salidas'!D:D=D36, NOT(ISBLANK('Entradas y salidas'!I:I))); INDEX(FILTER('Cortes x inversión'!J:J, 'Cortes x inversión'!D:D=D36),1)}), """"))"),"") | P36: =IFERROR(__xludf.DUMMYFUNCTION("IF(K36="""","""", GOOGLEFINANCE(""CURRENCY:USDCOP"")) "),"") | Q36: =IFERROR(__xludf.DUMMYFUNCTION("IF(L36="""","""", GOOGLEFINANCE(""CURRENCY:USDCOP"")) "),"") | R36: =IF(K36="","", L36*P36) | S36: =IF(OR(Q36="", R36=""),"", R36 - ABS(Q36)) | T36: =IFERROR(__xludf.DUMMYFUNCTION("IF(ISBLANK(D36),"""",IFERROR(XIRR({FILTER('Entradas y salidas'!K:K, 'Entradas y salidas'!D:D=D36, NOT(ISBLANK('Entradas y salidas'!K:K))); INDEX(FILTER('Cortes x inversión'!I:I, 'Cortes x inversión'!D:D=D36),1)}, {FILTER('Entradas y salidas'!F:F, 'Entrada"&"s y salidas'!D:D=D36, NOT(ISBLANK('Entradas y salidas'!K:K))); INDEX(FILTER('Cortes x inversión'!J:J, 'Cortes x inversión'!D:D=D36),1)}), """"))"),"")
F37: =IF(E37="COP", SUMIF('Entradas y salidas'!D:D, D37, 'Entradas y salidas'!J:J), ) | G37: =IFERROR(__xludf.DUMMYFUNCTION("IF(E37=""COP"", INDEX(FILTER('Cortes x inversión'!F:F, 'Cortes x inversión'!D:D=D37),1), )"),"") | H37: =IF(OR(F37="", G37=""),"", G37 - ABS(F37)) | I37: =IFERROR(__xludf.DUMMYFUNCTION("IF(ISBLANK(D37),"""",IFERROR(XIRR({FILTER('Entradas y salidas'!J:J, 'Entradas y salidas'!D:D=D37, NOT(ISBLANK('Entradas y salidas'!J:J))); INDEX(FILTER('Cortes x inversión'!F:F, 'Cortes x inversión'!D:D=D37),1)}, {FILTER('Entradas y salidas'!F:F, 'Entrada"&"s y salidas'!D:D=D37, NOT(ISBLANK('Entradas y salidas'!J:J))); INDEX(FILTER('Cortes x inversión'!J:J, 'Cortes x inversión'!D:D=D37),1)}), """"))"),"") | K37: =IF(E37="USD", SUMIF('Entradas y salidas'!D:D, D37, 'Entradas y salidas'!I:I), ) | L37: =IFERROR(__xludf.DUMMYFUNCTION("IF(E37=""USD"", INDEX(FILTER('Cortes x inversión'!G:G, 'Cortes x inversión'!D:D=D37),1), )"),"") | M37: =IF(OR(K37="", L37=""),"", L37 - ABS(K37)) | N37: =IFERROR(__xludf.DUMMYFUNCTION("IF(ISBLANK(D37),"""",IFERROR(XIRR({FILTER('Entradas y salidas'!I:I, 'Entradas y salidas'!D:D=D37, NOT(ISBLANK('Entradas y salidas'!I:I))); INDEX(FILTER('Cortes x inversión'!G:G, 'Cortes x inversión'!D:D=D37),1)}, {FILTER('Entradas y salidas'!F:F, 'Entrada"&"s y salidas'!D:D=D37, NOT(ISBLANK('Entradas y salidas'!I:I))); INDEX(FILTER('Cortes x inversión'!J:J, 'Cortes x inversión'!D:D=D37),1)}), """"))"),"") | P37: =IFERROR(__xludf.DUMMYFUNCTION("IF(K37="""","""", GOOGLEFINANCE(""CURRENCY:USDCOP"")) "),"") | Q37: =IFERROR(__xludf.DUMMYFUNCTION("IF(L37="""","""", GOOGLEFINANCE(""CURRENCY:USDCOP"")) "),"") | R37: =IF(K37="","", L37*P37) | S37: =IF(OR(Q37="", R37=""),"", R37 - ABS(Q37)) | T37: =IFERROR(__xludf.DUMMYFUNCTION("IF(ISBLANK(D37),"""",IFERROR(XIRR({FILTER('Entradas y salidas'!K:K, 'Entradas y salidas'!D:D=D37, NOT(ISBLANK('Entradas y salidas'!K:K))); INDEX(FILTER('Cortes x inversión'!I:I, 'Cortes x inversión'!D:D=D37),1)}, {FILTER('Entradas y salidas'!F:F, 'Entrada"&"s y salidas'!D:D=D37, NOT(ISBLANK('Entradas y salidas'!K:K))); INDEX(FILTER('Cortes x inversión'!J:J, 'Cortes x inversión'!D:D=D37),1)}), """"))"),"")
F38: =IF(E38="COP", SUMIF('Entradas y salidas'!D:D, D38, 'Entradas y salidas'!J:J), ) | G38: =IFERROR(__xludf.DUMMYFUNCTION("IF(E38=""COP"", INDEX(FILTER('Cortes x inversión'!F:F, 'Cortes x inversión'!D:D=D38),1), )"),"") | H38: =IF(OR(F38="", G38=""),"", G38 - ABS(F38)) | I38: =IFERROR(__xludf.DUMMYFUNCTION("IF(ISBLANK(D38),"""",IFERROR(XIRR({FILTER('Entradas y salidas'!J:J, 'Entradas y salidas'!D:D=D38, NOT(ISBLANK('Entradas y salidas'!J:J))); INDEX(FILTER('Cortes x inversión'!F:F, 'Cortes x inversión'!D:D=D38),1)}, {FILTER('Entradas y salidas'!F:F, 'Entrada"&"s y salidas'!D:D=D38, NOT(ISBLANK('Entradas y salidas'!J:J))); INDEX(FILTER('Cortes x inversión'!J:J, 'Cortes x inversión'!D:D=D38),1)}), """"))"),"") | K38: =IF(E38="USD", SUMIF('Entradas y salidas'!D:D, D38, 'Entradas y salidas'!I:I), ) | L38: =IFERROR(__xludf.DUMMYFUNCTION("IF(E38=""USD"", INDEX(FILTER('Cortes x inversión'!G:G, 'Cortes x inversión'!D:D=D38),1), )"),"") | M38: =IF(OR(K38="", L38=""),"", L38 - ABS(K38)) | N38: =IFERROR(__xludf.DUMMYFUNCTION("IF(ISBLANK(D38),"""",IFERROR(XIRR({FILTER('Entradas y salidas'!I:I, 'Entradas y salidas'!D:D=D38, NOT(ISBLANK('Entradas y salidas'!I:I))); INDEX(FILTER('Cortes x inversión'!G:G, 'Cortes x inversión'!D:D=D38),1)}, {FILTER('Entradas y salidas'!F:F, 'Entrada"&"s y salidas'!D:D=D38, NOT(ISBLANK('Entradas y salidas'!I:I))); INDEX(FILTER('Cortes x inversión'!J:J, 'Cortes x inversión'!D:D=D38),1)}), """"))"),"") | P38: =IFERROR(__xludf.DUMMYFUNCTION("IF(K38="""","""", GOOGLEFINANCE(""CURRENCY:USDCOP"")) "),"") | Q38: =IFERROR(__xludf.DUMMYFUNCTION("IF(L38="""","""", GOOGLEFINANCE(""CURRENCY:USDCOP"")) "),"") | R38: =IF(K38="","", L38*P38) | S38: =IF(OR(Q38="", R38=""),"", R38 - ABS(Q38)) | T38: =IFERROR(__xludf.DUMMYFUNCTION("IF(ISBLANK(D38),"""",IFERROR(XIRR({FILTER('Entradas y salidas'!K:K, 'Entradas y salidas'!D:D=D38, NOT(ISBLANK('Entradas y salidas'!K:K))); INDEX(FILTER('Cortes x inversión'!I:I, 'Cortes x inversión'!D:D=D38),1)}, {FILTER('Entradas y salidas'!F:F, 'Entrada"&"s y salidas'!D:D=D38, NOT(ISBLANK('Entradas y salidas'!K:K))); INDEX(FILTER('Cortes x inversión'!J:J, 'Cortes x inversión'!D:D=D38),1)}), """"))"),"")
F39: =IF(E39="COP", SUMIF('Entradas y salidas'!D:D, D39, 'Entradas y salidas'!J:J), ) | G39: =IFERROR(__xludf.DUMMYFUNCTION("IF(E39=""COP"", INDEX(FILTER('Cortes x inversión'!F:F, 'Cortes x inversión'!D:D=D39),1), )"),"") | H39: =IF(OR(F39="", G39=""),"", G39 - ABS(F39)) | I39: =IFERROR(__xludf.DUMMYFUNCTION("IF(ISBLANK(D39),"""",IFERROR(XIRR({FILTER('Entradas y salidas'!J:J, 'Entradas y salidas'!D:D=D39, NOT(ISBLANK('Entradas y salidas'!J:J))); INDEX(FILTER('Cortes x inversión'!F:F, 'Cortes x inversión'!D:D=D39),1)}, {FILTER('Entradas y salidas'!F:F, 'Entrada"&"s y salidas'!D:D=D39, NOT(ISBLANK('Entradas y salidas'!J:J))); INDEX(FILTER('Cortes x inversión'!J:J, 'Cortes x inversión'!D:D=D39),1)}), """"))"),"") | K39: =IF(E39="USD", SUMIF('Entradas y salidas'!D:D, D39, 'Entradas y salidas'!I:I), ) | L39: =IFERROR(__xludf.DUMMYFUNCTION("IF(E39=""USD"", INDEX(FILTER('Cortes x inversión'!G:G, 'Cortes x inversión'!D:D=D39),1), )"),"") | M39: =IF(OR(K39="", L39=""),"", L39 - ABS(K39)) | N39: =IFERROR(__xludf.DUMMYFUNCTION("IF(ISBLANK(D39),"""",IFERROR(XIRR({FILTER('Entradas y salidas'!I:I, 'Entradas y salidas'!D:D=D39, NOT(ISBLANK('Entradas y salidas'!I:I))); INDEX(FILTER('Cortes x inversión'!G:G, 'Cortes x inversión'!D:D=D39),1)}, {FILTER('Entradas y salidas'!F:F, 'Entrada"&"s y salidas'!D:D=D39, NOT(ISBLANK('Entradas y salidas'!I:I))); INDEX(FILTER('Cortes x inversión'!J:J, 'Cortes x inversión'!D:D=D39),1)}), """"))"),"") | P39: =IFERROR(__xludf.DUMMYFUNCTION("IF(K39="""","""", GOOGLEFINANCE(""CURRENCY:USDCOP"")) "),"") | Q39: =IFERROR(__xludf.DUMMYFUNCTION("IF(L39="""","""", GOOGLEFINANCE(""CURRENCY:USDCOP"")) "),"") | R39: =IF(K39="","", L39*P39) | S39: =IF(OR(Q39="", R39=""),"", R39 - ABS(Q39)) | T39: =IFERROR(__xludf.DUMMYFUNCTION("IF(ISBLANK(D39),"""",IFERROR(XIRR({FILTER('Entradas y salidas'!K:K, 'Entradas y salidas'!D:D=D39, NOT(ISBLANK('Entradas y salidas'!K:K))); INDEX(FILTER('Cortes x inversión'!I:I, 'Cortes x inversión'!D:D=D39),1)}, {FILTER('Entradas y salidas'!F:F, 'Entrada"&"s y salidas'!D:D=D39, NOT(ISBLANK('Entradas y salidas'!K:K))); INDEX(FILTER('Cortes x inversión'!J:J, 'Cortes x inversión'!D:D=D39),1)}), """"))"),"")
F40: =IF(E40="COP", SUMIF('Entradas y salidas'!D:D, D40, 'Entradas y salidas'!J:J), ) | G40: =IFERROR(__xludf.DUMMYFUNCTION("IF(E40=""COP"", INDEX(FILTER('Cortes x inversión'!F:F, 'Cortes x inversión'!D:D=D40),1), )"),"") | H40: =IF(OR(F40="", G40=""),"", G40 - ABS(F40)) | I40: =IFERROR(__xludf.DUMMYFUNCTION("IF(ISBLANK(D40),"""",IFERROR(XIRR({FILTER('Entradas y salidas'!J:J, 'Entradas y salidas'!D:D=D40, NOT(ISBLANK('Entradas y salidas'!J:J))); INDEX(FILTER('Cortes x inversión'!F:F, 'Cortes x inversión'!D:D=D40),1)}, {FILTER('Entradas y salidas'!F:F, 'Entrada"&"s y salidas'!D:D=D40, NOT(ISBLANK('Entradas y salidas'!J:J))); INDEX(FILTER('Cortes x inversión'!J:J, 'Cortes x inversión'!D:D=D40),1)}), """"))"),"") | K40: =IF(E40="USD", SUMIF('Entradas y salidas'!D:D, D40, 'Entradas y salidas'!I:I), ) | L40: =IFERROR(__xludf.DUMMYFUNCTION("IF(E40=""USD"", INDEX(FILTER('Cortes x inversión'!G:G, 'Cortes x inversión'!D:D=D40),1), )"),"") | M40: =IF(OR(K40="", L40=""),"", L40 - ABS(K40)) | N40: =IFERROR(__xludf.DUMMYFUNCTION("IF(ISBLANK(D40),"""",IFERROR(XIRR({FILTER('Entradas y salidas'!I:I, 'Entradas y salidas'!D:D=D40, NOT(ISBLANK('Entradas y salidas'!I:I))); INDEX(FILTER('Cortes x inversión'!G:G, 'Cortes x inversión'!D:D=D40),1)}, {FILTER('Entradas y salidas'!F:F, 'Entrada"&"s y salidas'!D:D=D40, NOT(ISBLANK('Entradas y salidas'!I:I))); INDEX(FILTER('Cortes x inversión'!J:J, 'Cortes x inversión'!D:D=D40),1)}), """"))"),"") | P40: =IFERROR(__xludf.DUMMYFUNCTION("IF(K40="""","""", GOOGLEFINANCE(""CURRENCY:USDCOP"")) "),"") | Q40: =IFERROR(__xludf.DUMMYFUNCTION("IF(L40="""","""", GOOGLEFINANCE(""CURRENCY:USDCOP"")) "),"") | R40: =IF(K40="","", L40*P40) | S40: =IF(OR(Q40="", R40=""),"", R40 - ABS(Q40)) | T40: =IFERROR(__xludf.DUMMYFUNCTION("IF(ISBLANK(D40),"""",IFERROR(XIRR({FILTER('Entradas y salidas'!K:K, 'Entradas y salidas'!D:D=D40, NOT(ISBLANK('Entradas y salidas'!K:K))); INDEX(FILTER('Cortes x inversión'!I:I, 'Cortes x inversión'!D:D=D40),1)}, {FILTER('Entradas y salidas'!F:F, 'Entrada"&"s y salidas'!D:D=D40, NOT(ISBLANK('Entradas y salidas'!K:K))); INDEX(FILTER('Cortes x inversión'!J:J, 'Cortes x inversión'!D:D=D40),1)}), """"))"),"")
F41: =IF(E41="COP", SUMIF('Entradas y salidas'!D:D, D41, 'Entradas y salidas'!J:J), ) | G41: =IFERROR(__xludf.DUMMYFUNCTION("IF(E41=""COP"", INDEX(FILTER('Cortes x inversión'!F:F, 'Cortes x inversión'!D:D=D41),1), )"),"") | H41: =IF(OR(F41="", G41=""),"", G41 - ABS(F41)) | I41: =IFERROR(__xludf.DUMMYFUNCTION("IF(ISBLANK(D41),"""",IFERROR(XIRR({FILTER('Entradas y salidas'!J:J, 'Entradas y salidas'!D:D=D41, NOT(ISBLANK('Entradas y salidas'!J:J))); INDEX(FILTER('Cortes x inversión'!F:F, 'Cortes x inversión'!D:D=D41),1)}, {FILTER('Entradas y salidas'!F:F, 'Entrada"&"s y salidas'!D:D=D41, NOT(ISBLANK('Entradas y salidas'!J:J))); INDEX(FILTER('Cortes x inversión'!J:J, 'Cortes x inversión'!D:D=D41),1)}), """"))"),"") | K41: =IF(E41="USD", SUMIF('Entradas y salidas'!D:D, D41, 'Entradas y salidas'!I:I), ) | L41: =IFERROR(__xludf.DUMMYFUNCTION("IF(E41=""USD"", INDEX(FILTER('Cortes x inversión'!G:G, 'Cortes x inversión'!D:D=D41),1), )"),"") | M41: =IF(OR(K41="", L41=""),"", L41 - ABS(K41)) | N41: =IFERROR(__xludf.DUMMYFUNCTION("IF(ISBLANK(D41),"""",IFERROR(XIRR({FILTER('Entradas y salidas'!I:I, 'Entradas y salidas'!D:D=D41, NOT(ISBLANK('Entradas y salidas'!I:I))); INDEX(FILTER('Cortes x inversión'!G:G, 'Cortes x inversión'!D:D=D41),1)}, {FILTER('Entradas y salidas'!F:F, 'Entrada"&"s y salidas'!D:D=D41, NOT(ISBLANK('Entradas y salidas'!I:I))); INDEX(FILTER('Cortes x inversión'!J:J, 'Cortes x inversión'!D:D=D41),1)}), """"))"),"") | P41: =IFERROR(__xludf.DUMMYFUNCTION("IF(K41="""","""", GOOGLEFINANCE(""CURRENCY:USDCOP"")) "),"") | Q41: =IFERROR(__xludf.DUMMYFUNCTION("IF(L41="""","""", GOOGLEFINANCE(""CURRENCY:USDCOP"")) "),"") | R41: =IF(K41="","", L41*P41) | S41: =IF(OR(Q41="", R41=""),"", R41 - ABS(Q41)) | T41: =IFERROR(__xludf.DUMMYFUNCTION("IF(ISBLANK(D41),"""",IFERROR(XIRR({FILTER('Entradas y salidas'!K:K, 'Entradas y salidas'!D:D=D41, NOT(ISBLANK('Entradas y salidas'!K:K))); INDEX(FILTER('Cortes x inversión'!I:I, 'Cortes x inversión'!D:D=D41),1)}, {FILTER('Entradas y salidas'!F:F, 'Entrada"&"s y salidas'!D:D=D41, NOT(ISBLANK('Entradas y salidas'!K:K))); INDEX(FILTER('Cortes x inversión'!J:J, 'Cortes x inversión'!D:D=D41),1)}), """"))"),"")
F42: =IF(E42="COP", SUMIF('Entradas y salidas'!D:D, D42, 'Entradas y salidas'!J:J), ) | G42: =IFERROR(__xludf.DUMMYFUNCTION("IF(E42=""COP"", INDEX(FILTER('Cortes x inversión'!F:F, 'Cortes x inversión'!D:D=D42),1), )"),"") | H42: =IF(OR(F42="", G42=""),"", G42 - ABS(F42)) | I42: =IFERROR(__xludf.DUMMYFUNCTION("IF(ISBLANK(D42),"""",IFERROR(XIRR({FILTER('Entradas y salidas'!J:J, 'Entradas y salidas'!D:D=D42, NOT(ISBLANK('Entradas y salidas'!J:J))); INDEX(FILTER('Cortes x inversión'!F:F, 'Cortes x inversión'!D:D=D42),1)}, {FILTER('Entradas y salidas'!F:F, 'Entrada"&"s y salidas'!D:D=D42, NOT(ISBLANK('Entradas y salidas'!J:J))); INDEX(FILTER('Cortes x inversión'!J:J, 'Cortes x inversión'!D:D=D42),1)}), """"))"),"") | K42: =IF(E42="USD", SUMIF('Entradas y salidas'!D:D, D42, 'Entradas y salidas'!I:I), ) | L42: =IFERROR(__xludf.DUMMYFUNCTION("IF(E42=""USD"", INDEX(FILTER('Cortes x inversión'!G:G, 'Cortes x inversión'!D:D=D42),1), )"),"") | M42: =IF(OR(K42="", L42=""),"", L42 - ABS(K42)) | N42: =IFERROR(__xludf.DUMMYFUNCTION("IF(ISBLANK(D42),"""",IFERROR(XIRR({FILTER('Entradas y salidas'!I:I, 'Entradas y salidas'!D:D=D42, NOT(ISBLANK('Entradas y salidas'!I:I))); INDEX(FILTER('Cortes x inversión'!G:G, 'Cortes x inversión'!D:D=D42),1)}, {FILTER('Entradas y salidas'!F:F, 'Entrada"&"s y salidas'!D:D=D42, NOT(ISBLANK('Entradas y salidas'!I:I))); INDEX(FILTER('Cortes x inversión'!J:J, 'Cortes x inversión'!D:D=D42),1)}), """"))"),"") | P42: =IFERROR(__xludf.DUMMYFUNCTION("IF(K42="""","""", GOOGLEFINANCE(""CURRENCY:USDCOP"")) "),"") | Q42: =IFERROR(__xludf.DUMMYFUNCTION("IF(L42="""","""", GOOGLEFINANCE(""CURRENCY:USDCOP"")) "),"") | R42: =IF(K42="","", L42*P42) | S42: =IF(OR(Q42="", R42=""),"", R42 - ABS(Q42)) | T42: =IFERROR(__xludf.DUMMYFUNCTION("IF(ISBLANK(D42),"""",IFERROR(XIRR({FILTER('Entradas y salidas'!K:K, 'Entradas y salidas'!D:D=D42, NOT(ISBLANK('Entradas y salidas'!K:K))); INDEX(FILTER('Cortes x inversión'!I:I, 'Cortes x inversión'!D:D=D42),1)}, {FILTER('Entradas y salidas'!F:F, 'Entrada"&"s y salidas'!D:D=D42, NOT(ISBLANK('Entradas y salidas'!K:K))); INDEX(FILTER('Cortes x inversión'!J:J, 'Cortes x inversión'!D:D=D42),1)}), """"))"),"")
F43: =IF(E43="COP", SUMIF('Entradas y salidas'!D:D, D43, 'Entradas y salidas'!J:J), ) | G43: =IFERROR(__xludf.DUMMYFUNCTION("IF(E43=""COP"", INDEX(FILTER('Cortes x inversión'!F:F, 'Cortes x inversión'!D:D=D43),1), )"),"") | H43: =IF(OR(F43="", G43=""),"", G43 - ABS(F43)) | I43: =IFERROR(__xludf.DUMMYFUNCTION("IF(ISBLANK(D43),"""",IFERROR(XIRR({FILTER('Entradas y salidas'!J:J, 'Entradas y salidas'!D:D=D43, NOT(ISBLANK('Entradas y salidas'!J:J))); INDEX(FILTER('Cortes x inversión'!F:F, 'Cortes x inversión'!D:D=D43),1)}, {FILTER('Entradas y salidas'!F:F, 'Entrada"&"s y salidas'!D:D=D43, NOT(ISBLANK('Entradas y salidas'!J:J))); INDEX(FILTER('Cortes x inversión'!J:J, 'Cortes x inversión'!D:D=D43),1)}), """"))"),"") | K43: =IF(E43="USD", SUMIF('Entradas y salidas'!D:D, D43, 'Entradas y salidas'!I:I), ) | L43: =IFERROR(__xludf.DUMMYFUNCTION("IF(E43=""USD"", INDEX(FILTER('Cortes x inversión'!G:G, 'Cortes x inversión'!D:D=D43),1), )"),"") | M43: =IF(OR(K43="", L43=""),"", L43 - ABS(K43)) | N43: =IFERROR(__xludf.DUMMYFUNCTION("IF(ISBLANK(D43),"""",IFERROR(XIRR({FILTER('Entradas y salidas'!I:I, 'Entradas y salidas'!D:D=D43, NOT(ISBLANK('Entradas y salidas'!I:I))); INDEX(FILTER('Cortes x inversión'!G:G, 'Cortes x inversión'!D:D=D43),1)}, {FILTER('Entradas y salidas'!F:F, 'Entrada"&"s y salidas'!D:D=D43, NOT(ISBLANK('Entradas y salidas'!I:I))); INDEX(FILTER('Cortes x inversión'!J:J, 'Cortes x inversión'!D:D=D43),1)}), """"))"),"") | P43: =IFERROR(__xludf.DUMMYFUNCTION("IF(K43="""","""", GOOGLEFINANCE(""CURRENCY:USDCOP"")) "),"") | Q43: =IFERROR(__xludf.DUMMYFUNCTION("IF(L43="""","""", GOOGLEFINANCE(""CURRENCY:USDCOP"")) "),"") | R43: =IF(K43="","", L43*P43) | S43: =IF(OR(Q43="", R43=""),"", R43 - ABS(Q43)) | T43: =IFERROR(__xludf.DUMMYFUNCTION("IF(ISBLANK(D43),"""",IFERROR(XIRR({FILTER('Entradas y salidas'!K:K, 'Entradas y salidas'!D:D=D43, NOT(ISBLANK('Entradas y salidas'!K:K))); INDEX(FILTER('Cortes x inversión'!I:I, 'Cortes x inversión'!D:D=D43),1)}, {FILTER('Entradas y salidas'!F:F, 'Entrada"&"s y salidas'!D:D=D43, NOT(ISBLANK('Entradas y salidas'!K:K))); INDEX(FILTER('Cortes x inversión'!J:J, 'Cortes x inversión'!D:D=D43),1)}), """"))"),"")
F44: =IF(E44="COP", SUMIF('Entradas y salidas'!D:D, D44, 'Entradas y salidas'!J:J), ) | G44: =IFERROR(__xludf.DUMMYFUNCTION("IF(E44=""COP"", INDEX(FILTER('Cortes x inversión'!F:F, 'Cortes x inversión'!D:D=D44),1), )"),"") | H44: =IF(OR(F44="", G44=""),"", G44 - ABS(F44)) | I44: =IFERROR(__xludf.DUMMYFUNCTION("IF(ISBLANK(D44),"""",IFERROR(XIRR({FILTER('Entradas y salidas'!J:J, 'Entradas y salidas'!D:D=D44, NOT(ISBLANK('Entradas y salidas'!J:J))); INDEX(FILTER('Cortes x inversión'!F:F, 'Cortes x inversión'!D:D=D44),1)}, {FILTER('Entradas y salidas'!F:F, 'Entrada"&"s y salidas'!D:D=D44, NOT(ISBLANK('Entradas y salidas'!J:J))); INDEX(FILTER('Cortes x inversión'!J:J, 'Cortes x inversión'!D:D=D44),1)}), """"))"),"") | K44: =IF(E44="USD", SUMIF('Entradas y salidas'!D:D, D44, 'Entradas y salidas'!I:I), ) | L44: =IFERROR(__xludf.DUMMYFUNCTION("IF(E44=""USD"", INDEX(FILTER('Cortes x inversión'!G:G, 'Cortes x inversión'!D:D=D44),1), )"),"") | M44: =IF(OR(K44="", L44=""),"", L44 - ABS(K44)) | N44: =IFERROR(__xludf.DUMMYFUNCTION("IF(ISBLANK(D44),"""",IFERROR(XIRR({FILTER('Entradas y salidas'!I:I, 'Entradas y salidas'!D:D=D44, NOT(ISBLANK('Entradas y salidas'!I:I))); INDEX(FILTER('Cortes x inversión'!G:G, 'Cortes x inversión'!D:D=D44),1)}, {FILTER('Entradas y salidas'!F:F, 'Entrada"&"s y salidas'!D:D=D44, NOT(ISBLANK('Entradas y salidas'!I:I))); INDEX(FILTER('Cortes x inversión'!J:J, 'Cortes x inversión'!D:D=D44),1)}), """"))"),"") | P44: =IFERROR(__xludf.DUMMYFUNCTION("IF(K44="""","""", GOOGLEFINANCE(""CURRENCY:USDCOP"")) "),"") | Q44: =IFERROR(__xludf.DUMMYFUNCTION("IF(L44="""","""", GOOGLEFINANCE(""CURRENCY:USDCOP"")) "),"") | R44: =IF(K44="","", L44*P44) | S44: =IF(OR(Q44="", R44=""),"", R44 - ABS(Q44)) | T44: =IFERROR(__xludf.DUMMYFUNCTION("IF(ISBLANK(D44),"""",IFERROR(XIRR({FILTER('Entradas y salidas'!K:K, 'Entradas y salidas'!D:D=D44, NOT(ISBLANK('Entradas y salidas'!K:K))); INDEX(FILTER('Cortes x inversión'!I:I, 'Cortes x inversión'!D:D=D44),1)}, {FILTER('Entradas y salidas'!F:F, 'Entrada"&"s y salidas'!D:D=D44, NOT(ISBLANK('Entradas y salidas'!K:K))); INDEX(FILTER('Cortes x inversión'!J:J, 'Cortes x inversión'!D:D=D44),1)}), """"))"),"")
F45: =IF(E45="COP", SUMIF('Entradas y salidas'!D:D, D45, 'Entradas y salidas'!J:J), ) | G45: =IFERROR(__xludf.DUMMYFUNCTION("IF(E45=""COP"", INDEX(FILTER('Cortes x inversión'!F:F, 'Cortes x inversión'!D:D=D45),1), )"),"") | H45: =IF(OR(F45="", G45=""),"", G45 - ABS(F45)) | I45: =IFERROR(__xludf.DUMMYFUNCTION("IF(ISBLANK(D45),"""",IFERROR(XIRR({FILTER('Entradas y salidas'!J:J, 'Entradas y salidas'!D:D=D45, NOT(ISBLANK('Entradas y salidas'!J:J))); INDEX(FILTER('Cortes x inversión'!F:F, 'Cortes x inversión'!D:D=D45),1)}, {FILTER('Entradas y salidas'!F:F, 'Entrada"&"s y salidas'!D:D=D45, NOT(ISBLANK('Entradas y salidas'!J:J))); INDEX(FILTER('Cortes x inversión'!J:J, 'Cortes x inversión'!D:D=D45),1)}), """"))"),"") | K45: =IF(E45="USD", SUMIF('Entradas y salidas'!D:D, D45, 'Entradas y salidas'!I:I), ) | L45: =IFERROR(__xludf.DUMMYFUNCTION("IF(E45=""USD"", INDEX(FILTER('Cortes x inversión'!G:G, 'Cortes x inversión'!D:D=D45),1), )"),"") | M45: =IF(OR(K45="", L45=""),"", L45 - ABS(K45)) | N45: =IFERROR(__xludf.DUMMYFUNCTION("IF(ISBLANK(D45),"""",IFERROR(XIRR({FILTER('Entradas y salidas'!I:I, 'Entradas y salidas'!D:D=D45, NOT(ISBLANK('Entradas y salidas'!I:I))); INDEX(FILTER('Cortes x inversión'!G:G, 'Cortes x inversión'!D:D=D45),1)}, {FILTER('Entradas y salidas'!F:F, 'Entrada"&"s y salidas'!D:D=D45, NOT(ISBLANK('Entradas y salidas'!I:I))); INDEX(FILTER('Cortes x inversión'!J:J, 'Cortes x inversión'!D:D=D45),1)}), """"))"),"") | P45: =IFERROR(__xludf.DUMMYFUNCTION("IF(K45="""","""", GOOGLEFINANCE(""CURRENCY:USDCOP"")) "),"") | Q45: =IFERROR(__xludf.DUMMYFUNCTION("IF(L45="""","""", GOOGLEFINANCE(""CURRENCY:USDCOP"")) "),"") | R45: =IF(K45="","", L45*P45) | S45: =IF(OR(Q45="", R45=""),"", R45 - ABS(Q45)) | T45: =IFERROR(__xludf.DUMMYFUNCTION("IF(ISBLANK(D45),"""",IFERROR(XIRR({FILTER('Entradas y salidas'!K:K, 'Entradas y salidas'!D:D=D45, NOT(ISBLANK('Entradas y salidas'!K:K))); INDEX(FILTER('Cortes x inversión'!I:I, 'Cortes x inversión'!D:D=D45),1)}, {FILTER('Entradas y salidas'!F:F, 'Entrada"&"s y salidas'!D:D=D45, NOT(ISBLANK('Entradas y salidas'!K:K))); INDEX(FILTER('Cortes x inversión'!J:J, 'Cortes x inversión'!D:D=D45),1)}), """"))"),"")
F46: =IF(E46="COP", SUMIF('Entradas y salidas'!D:D, D46, 'Entradas y salidas'!J:J), ) | G46: =IFERROR(__xludf.DUMMYFUNCTION("IF(E46=""COP"", INDEX(FILTER('Cortes x inversión'!F:F, 'Cortes x inversión'!D:D=D46),1), )"),"") | H46: =IF(OR(F46="", G46=""),"", G46 - ABS(F46)) | I46: =IFERROR(__xludf.DUMMYFUNCTION("IF(ISBLANK(D46),"""",IFERROR(XIRR({FILTER('Entradas y salidas'!J:J, 'Entradas y salidas'!D:D=D46, NOT(ISBLANK('Entradas y salidas'!J:J))); INDEX(FILTER('Cortes x inversión'!F:F, 'Cortes x inversión'!D:D=D46),1)}, {FILTER('Entradas y salidas'!F:F, 'Entrada"&"s y salidas'!D:D=D46, NOT(ISBLANK('Entradas y salidas'!J:J))); INDEX(FILTER('Cortes x inversión'!J:J, 'Cortes x inversión'!D:D=D46),1)}), """"))"),"") | K46: =IF(E46="USD", SUMIF('Entradas y salidas'!D:D, D46, 'Entradas y salidas'!I:I), ) | L46: =IFERROR(__xludf.DUMMYFUNCTION("IF(E46=""USD"", INDEX(FILTER('Cortes x inversión'!G:G, 'Cortes x inversión'!D:D=D46),1), )"),"") | M46: =IF(OR(K46="", L46=""),"", L46 - ABS(K46)) | N46: =IFERROR(__xludf.DUMMYFUNCTION("IF(ISBLANK(D46),"""",IFERROR(XIRR({FILTER('Entradas y salidas'!I:I, 'Entradas y salidas'!D:D=D46, NOT(ISBLANK('Entradas y salidas'!I:I))); INDEX(FILTER('Cortes x inversión'!G:G, 'Cortes x inversión'!D:D=D46),1)}, {FILTER('Entradas y salidas'!F:F, 'Entrada"&"s y salidas'!D:D=D46, NOT(ISBLANK('Entradas y salidas'!I:I))); INDEX(FILTER('Cortes x inversión'!J:J, 'Cortes x inversión'!D:D=D46),1)}), """"))"),"") | P46: =IFERROR(__xludf.DUMMYFUNCTION("IF(K46="""","""", GOOGLEFINANCE(""CURRENCY:USDCOP"")) "),"") | Q46: =IFERROR(__xludf.DUMMYFUNCTION("IF(L46="""","""", GOOGLEFINANCE(""CURRENCY:USDCOP"")) "),"") | R46: =IF(K46="","", L46*P46) | S46: =IF(OR(Q46="", R46=""),"", R46 - ABS(Q46)) | T46: =IFERROR(__xludf.DUMMYFUNCTION("IF(ISBLANK(D46),"""",IFERROR(XIRR({FILTER('Entradas y salidas'!K:K, 'Entradas y salidas'!D:D=D46, NOT(ISBLANK('Entradas y salidas'!K:K))); INDEX(FILTER('Cortes x inversión'!I:I, 'Cortes x inversión'!D:D=D46),1)}, {FILTER('Entradas y salidas'!F:F, 'Entrada"&"s y salidas'!D:D=D46, NOT(ISBLANK('Entradas y salidas'!K:K))); INDEX(FILTER('Cortes x inversión'!J:J, 'Cortes x inversión'!D:D=D46),1)}), """"))"),"")
F47: =IF(E47="COP", SUMIF('Entradas y salidas'!D:D, D47, 'Entradas y salidas'!J:J), ) | G47: =IFERROR(__xludf.DUMMYFUNCTION("IF(E47=""COP"", INDEX(FILTER('Cortes x inversión'!F:F, 'Cortes x inversión'!D:D=D47),1), )"),"") | H47: =IF(OR(F47="", G47=""),"", G47 - ABS(F47)) | I47: =IFERROR(__xludf.DUMMYFUNCTION("IF(ISBLANK(D47),"""",IFERROR(XIRR({FILTER('Entradas y salidas'!J:J, 'Entradas y salidas'!D:D=D47, NOT(ISBLANK('Entradas y salidas'!J:J))); INDEX(FILTER('Cortes x inversión'!F:F, 'Cortes x inversión'!D:D=D47),1)}, {FILTER('Entradas y salidas'!F:F, 'Entrada"&"s y salidas'!D:D=D47, NOT(ISBLANK('Entradas y salidas'!J:J))); INDEX(FILTER('Cortes x inversión'!J:J, 'Cortes x inversión'!D:D=D47),1)}), """"))"),"") | K47: =IF(E47="USD", SUMIF('Entradas y salidas'!D:D, D47, 'Entradas y salidas'!I:I), ) | L47: =IFERROR(__xludf.DUMMYFUNCTION("IF(E47=""USD"", INDEX(FILTER('Cortes x inversión'!G:G, 'Cortes x inversión'!D:D=D47),1), )"),"") | M47: =IF(OR(K47="", L47=""),"", L47 - ABS(K47)) | N47: =IFERROR(__xludf.DUMMYFUNCTION("IF(ISBLANK(D47),"""",IFERROR(XIRR({FILTER('Entradas y salidas'!I:I, 'Entradas y salidas'!D:D=D47, NOT(ISBLANK('Entradas y salidas'!I:I))); INDEX(FILTER('Cortes x inversión'!G:G, 'Cortes x inversión'!D:D=D47),1)}, {FILTER('Entradas y salidas'!F:F, 'Entrada"&"s y salidas'!D:D=D47, NOT(ISBLANK('Entradas y salidas'!I:I))); INDEX(FILTER('Cortes x inversión'!J:J, 'Cortes x inversión'!D:D=D47),1)}), """"))"),"") | P47: =IFERROR(__xludf.DUMMYFUNCTION("IF(K47="""","""", GOOGLEFINANCE(""CURRENCY:USDCOP"")) "),"") | Q47: =IFERROR(__xludf.DUMMYFUNCTION("IF(L47="""","""", GOOGLEFINANCE(""CURRENCY:USDCOP"")) "),"") | R47: =IF(K47="","", L47*P47) | S47: =IF(OR(Q47="", R47=""),"", R47 - ABS(Q47)) | T47: =IFERROR(__xludf.DUMMYFUNCTION("IF(ISBLANK(D47),"""",IFERROR(XIRR({FILTER('Entradas y salidas'!K:K, 'Entradas y salidas'!D:D=D47, NOT(ISBLANK('Entradas y salidas'!K:K))); INDEX(FILTER('Cortes x inversión'!I:I, 'Cortes x inversión'!D:D=D47),1)}, {FILTER('Entradas y salidas'!F:F, 'Entrada"&"s y salidas'!D:D=D47, NOT(ISBLANK('Entradas y salidas'!K:K))); INDEX(FILTER('Cortes x inversión'!J:J, 'Cortes x inversión'!D:D=D47),1)}), """"))"),"")
F48: =IF(E48="COP", SUMIF('Entradas y salidas'!D:D, D48, 'Entradas y salidas'!J:J), ) | G48: =IFERROR(__xludf.DUMMYFUNCTION("IF(E48=""COP"", INDEX(FILTER('Cortes x inversión'!F:F, 'Cortes x inversión'!D:D=D48),1), )"),"") | H48: =IF(OR(F48="", G48=""),"", G48 - ABS(F48)) | I48: =IFERROR(__xludf.DUMMYFUNCTION("IF(ISBLANK(D48),"""",IFERROR(XIRR({FILTER('Entradas y salidas'!J:J, 'Entradas y salidas'!D:D=D48, NOT(ISBLANK('Entradas y salidas'!J:J))); INDEX(FILTER('Cortes x inversión'!F:F, 'Cortes x inversión'!D:D=D48),1)}, {FILTER('Entradas y salidas'!F:F, 'Entrada"&"s y salidas'!D:D=D48, NOT(ISBLANK('Entradas y salidas'!J:J))); INDEX(FILTER('Cortes x inversión'!J:J, 'Cortes x inversión'!D:D=D48),1)}), """"))"),"") | K48: =IF(E48="USD", SUMIF('Entradas y salidas'!D:D, D48, 'Entradas y salidas'!I:I), ) | L48: =IFERROR(__xludf.DUMMYFUNCTION("IF(E48=""USD"", INDEX(FILTER('Cortes x inversión'!G:G, 'Cortes x inversión'!D:D=D48),1), )"),"") | M48: =IF(OR(K48="", L48=""),"", L48 - ABS(K48)) | N48: =IFERROR(__xludf.DUMMYFUNCTION("IF(ISBLANK(D48),"""",IFERROR(XIRR({FILTER('Entradas y salidas'!I:I, 'Entradas y salidas'!D:D=D48, NOT(ISBLANK('Entradas y salidas'!I:I))); INDEX(FILTER('Cortes x inversión'!G:G, 'Cortes x inversión'!D:D=D48),1)}, {FILTER('Entradas y salidas'!F:F, 'Entrada"&"s y salidas'!D:D=D48, NOT(ISBLANK('Entradas y salidas'!I:I))); INDEX(FILTER('Cortes x inversión'!J:J, 'Cortes x inversión'!D:D=D48),1)}), """"))"),"") | P48: =IFERROR(__xludf.DUMMYFUNCTION("IF(K48="""","""", GOOGLEFINANCE(""CURRENCY:USDCOP"")) "),"") | Q48: =IFERROR(__xludf.DUMMYFUNCTION("IF(L48="""","""", GOOGLEFINANCE(""CURRENCY:USDCOP"")) "),"") | R48: =IF(K48="","", L48*P48) | S48: =IF(OR(Q48="", R48=""),"", R48 - ABS(Q48)) | T48: =IFERROR(__xludf.DUMMYFUNCTION("IF(ISBLANK(D48),"""",IFERROR(XIRR({FILTER('Entradas y salidas'!K:K, 'Entradas y salidas'!D:D=D48, NOT(ISBLANK('Entradas y salidas'!K:K))); INDEX(FILTER('Cortes x inversión'!I:I, 'Cortes x inversión'!D:D=D48),1)}, {FILTER('Entradas y salidas'!F:F, 'Entrada"&"s y salidas'!D:D=D48, NOT(ISBLANK('Entradas y salidas'!K:K))); INDEX(FILTER('Cortes x inversión'!J:J, 'Cortes x inversión'!D:D=D48),1)}), """"))"),"")
F49: =IF(E49="COP", SUMIF('Entradas y salidas'!D:D, D49, 'Entradas y salidas'!J:J), ) | G49: =IFERROR(__xludf.DUMMYFUNCTION("IF(E49=""COP"", INDEX(FILTER('Cortes x inversión'!F:F, 'Cortes x inversión'!D:D=D49),1), )"),"") | H49: =IF(OR(F49="", G49=""),"", G49 - ABS(F49)) | I49: =IFERROR(__xludf.DUMMYFUNCTION("IF(ISBLANK(D49),"""",IFERROR(XIRR({FILTER('Entradas y salidas'!J:J, 'Entradas y salidas'!D:D=D49, NOT(ISBLANK('Entradas y salidas'!J:J))); INDEX(FILTER('Cortes x inversión'!F:F, 'Cortes x inversión'!D:D=D49),1)}, {FILTER('Entradas y salidas'!F:F, 'Entrada"&"s y salidas'!D:D=D49, NOT(ISBLANK('Entradas y salidas'!J:J))); INDEX(FILTER('Cortes x inversión'!J:J, 'Cortes x inversión'!D:D=D49),1)}), """"))"),"") | K49: =IF(E49="USD", SUMIF('Entradas y salidas'!D:D, D49, 'Entradas y salidas'!I:I), ) | L49: =IFERROR(__xludf.DUMMYFUNCTION("IF(E49=""USD"", INDEX(FILTER('Cortes x inversión'!G:G, 'Cortes x inversión'!D:D=D49),1), )"),"") | M49: =IF(OR(K49="", L49=""),"", L49 - ABS(K49)) | N49: =IFERROR(__xludf.DUMMYFUNCTION("IF(ISBLANK(D49),"""",IFERROR(XIRR({FILTER('Entradas y salidas'!I:I, 'Entradas y salidas'!D:D=D49, NOT(ISBLANK('Entradas y salidas'!I:I))); INDEX(FILTER('Cortes x inversión'!G:G, 'Cortes x inversión'!D:D=D49),1)}, {FILTER('Entradas y salidas'!F:F, 'Entrada"&"s y salidas'!D:D=D49, NOT(ISBLANK('Entradas y salidas'!I:I))); INDEX(FILTER('Cortes x inversión'!J:J, 'Cortes x inversión'!D:D=D49),1)}), """"))"),"") | P49: =IFERROR(__xludf.DUMMYFUNCTION("IF(K49="""","""", GOOGLEFINANCE(""CURRENCY:USDCOP"")) "),"") | Q49: =IFERROR(__xludf.DUMMYFUNCTION("IF(L49="""","""", GOOGLEFINANCE(""CURRENCY:USDCOP"")) "),"") | R49: =IF(K49="","", L49*P49) | S49: =IF(OR(Q49="", R49=""),"", R49 - ABS(Q49)) | T49: =IFERROR(__xludf.DUMMYFUNCTION("IF(ISBLANK(D49),"""",IFERROR(XIRR({FILTER('Entradas y salidas'!K:K, 'Entradas y salidas'!D:D=D49, NOT(ISBLANK('Entradas y salidas'!K:K))); INDEX(FILTER('Cortes x inversión'!I:I, 'Cortes x inversión'!D:D=D49),1)}, {FILTER('Entradas y salidas'!F:F, 'Entrada"&"s y salidas'!D:D=D49, NOT(ISBLANK('Entradas y salidas'!K:K))); INDEX(FILTER('Cortes x inversión'!J:J, 'Cortes x inversión'!D:D=D49),1)}), """"))"),"")
F50: =IF(E50="COP", SUMIF('Entradas y salidas'!D:D, D50, 'Entradas y salidas'!J:J), ) | G50: =IFERROR(__xludf.DUMMYFUNCTION("IF(E50=""COP"", INDEX(FILTER('Cortes x inversión'!F:F, 'Cortes x inversión'!D:D=D50),1), )"),"") | H50: =IF(OR(F50="", G50=""),"", G50 - ABS(F50)) | I50: =IFERROR(__xludf.DUMMYFUNCTION("IF(ISBLANK(D50),"""",IFERROR(XIRR({FILTER('Entradas y salidas'!J:J, 'Entradas y salidas'!D:D=D50, NOT(ISBLANK('Entradas y salidas'!J:J))); INDEX(FILTER('Cortes x inversión'!F:F, 'Cortes x inversión'!D:D=D50),1)}, {FILTER('Entradas y salidas'!F:F, 'Entrada"&"s y salidas'!D:D=D50, NOT(ISBLANK('Entradas y salidas'!J:J))); INDEX(FILTER('Cortes x inversión'!J:J, 'Cortes x inversión'!D:D=D50),1)}), """"))"),"") | K50: =IF(E50="USD", SUMIF('Entradas y salidas'!D:D, D50, 'Entradas y salidas'!I:I), ) | L50: =IFERROR(__xludf.DUMMYFUNCTION("IF(E50=""USD"", INDEX(FILTER('Cortes x inversión'!G:G, 'Cortes x inversión'!D:D=D50),1), )"),"") | M50: =IF(OR(K50="", L50=""),"", L50 - ABS(K50)) | N50: =IFERROR(__xludf.DUMMYFUNCTION("IF(ISBLANK(D50),"""",IFERROR(XIRR({FILTER('Entradas y salidas'!I:I, 'Entradas y salidas'!D:D=D50, NOT(ISBLANK('Entradas y salidas'!I:I))); INDEX(FILTER('Cortes x inversión'!G:G, 'Cortes x inversión'!D:D=D50),1)}, {FILTER('Entradas y salidas'!F:F, 'Entrada"&"s y salidas'!D:D=D50, NOT(ISBLANK('Entradas y salidas'!I:I))); INDEX(FILTER('Cortes x inversión'!J:J, 'Cortes x inversión'!D:D=D50),1)}), """"))"),"") | P50: =IFERROR(__xludf.DUMMYFUNCTION("IF(K50="""","""", GOOGLEFINANCE(""CURRENCY:USDCOP"")) "),"") | Q50: =IFERROR(__xludf.DUMMYFUNCTION("IF(L50="""","""", GOOGLEFINANCE(""CURRENCY:USDCOP"")) "),"") | R50: =IF(K50="","", L50*P50) | S50: =IF(OR(Q50="", R50=""),"", R50 - ABS(Q50)) | T50: =IFERROR(__xludf.DUMMYFUNCTION("IF(ISBLANK(D50),"""",IFERROR(XIRR({FILTER('Entradas y salidas'!K:K, 'Entradas y salidas'!D:D=D50, NOT(ISBLANK('Entradas y salidas'!K:K))); INDEX(FILTER('Cortes x inversión'!I:I, 'Cortes x inversión'!D:D=D50),1)}, {FILTER('Entradas y salidas'!F:F, 'Entrada"&"s y salidas'!D:D=D50, NOT(ISBLANK('Entradas y salidas'!K:K))); INDEX(FILTER('Cortes x inversión'!J:J, 'Cortes x inversión'!D:D=D50),1)}), """"))"),"")
F51: =IF(E51="COP", SUMIF('Entradas y salidas'!D:D, D51, 'Entradas y salidas'!J:J), ) | G51: =IFERROR(__xludf.DUMMYFUNCTION("IF(E51=""COP"", INDEX(FILTER('Cortes x inversión'!F:F, 'Cortes x inversión'!D:D=D51),1), )"),"") | H51: =IF(OR(F51="", G51=""),"", G51 - ABS(F51)) | I51: =IFERROR(__xludf.DUMMYFUNCTION("IF(ISBLANK(D51),"""",IFERROR(XIRR({FILTER('Entradas y salidas'!J:J, 'Entradas y salidas'!D:D=D51, NOT(ISBLANK('Entradas y salidas'!J:J))); INDEX(FILTER('Cortes x inversión'!F:F, 'Cortes x inversión'!D:D=D51),1)}, {FILTER('Entradas y salidas'!F:F, 'Entrada"&"s y salidas'!D:D=D51, NOT(ISBLANK('Entradas y salidas'!J:J))); INDEX(FILTER('Cortes x inversión'!J:J, 'Cortes x inversión'!D:D=D51),1)}), """"))"),"") | K51: =IF(E51="USD", SUMIF('Entradas y salidas'!D:D, D51, 'Entradas y salidas'!I:I), ) | L51: =IFERROR(__xludf.DUMMYFUNCTION("IF(E51=""USD"", INDEX(FILTER('Cortes x inversión'!G:G, 'Cortes x inversión'!D:D=D51),1), )"),"") | M51: =IF(OR(K51="", L51=""),"", L51 - ABS(K51)) | N51: =IFERROR(__xludf.DUMMYFUNCTION("IF(ISBLANK(D51),"""",IFERROR(XIRR({FILTER('Entradas y salidas'!I:I, 'Entradas y salidas'!D:D=D51, NOT(ISBLANK('Entradas y salidas'!I:I))); INDEX(FILTER('Cortes x inversión'!G:G, 'Cortes x inversión'!D:D=D51),1)}, {FILTER('Entradas y salidas'!F:F, 'Entrada"&"s y salidas'!D:D=D51, NOT(ISBLANK('Entradas y salidas'!I:I))); INDEX(FILTER('Cortes x inversión'!J:J, 'Cortes x inversión'!D:D=D51),1)}), """"))"),"") | P51: =IFERROR(__xludf.DUMMYFUNCTION("IF(K51="""","""", GOOGLEFINANCE(""CURRENCY:USDCOP"")) "),"") | Q51: =IFERROR(__xludf.DUMMYFUNCTION("IF(L51="""","""", GOOGLEFINANCE(""CURRENCY:USDCOP"")) "),"") | R51: =IF(K51="","", L51*P51) | S51: =IF(OR(Q51="", R51=""),"", R51 - ABS(Q51)) | T51: =IFERROR(__xludf.DUMMYFUNCTION("IF(ISBLANK(D51),"""",IFERROR(XIRR({FILTER('Entradas y salidas'!K:K, 'Entradas y salidas'!D:D=D51, NOT(ISBLANK('Entradas y salidas'!K:K))); INDEX(FILTER('Cortes x inversión'!I:I, 'Cortes x inversión'!D:D=D51),1)}, {FILTER('Entradas y salidas'!F:F, 'Entrada"&"s y salidas'!D:D=D51, NOT(ISBLANK('Entradas y salidas'!K:K))); INDEX(FILTER('Cortes x inversión'!J:J, 'Cortes x inversión'!D:D=D51),1)}), """"))"),"")
F52: =IF(E52="COP", SUMIF('Entradas y salidas'!D:D, D52, 'Entradas y salidas'!J:J), ) | G52: =IFERROR(__xludf.DUMMYFUNCTION("IF(E52=""COP"", INDEX(FILTER('Cortes x inversión'!F:F, 'Cortes x inversión'!D:D=D52),1), )"),"") | H52: =IF(OR(F52="", G52=""),"", G52 - ABS(F52)) | I52: =IFERROR(__xludf.DUMMYFUNCTION("IF(ISBLANK(D52),"""",IFERROR(XIRR({FILTER('Entradas y salidas'!J:J, 'Entradas y salidas'!D:D=D52, NOT(ISBLANK('Entradas y salidas'!J:J))); INDEX(FILTER('Cortes x inversión'!F:F, 'Cortes x inversión'!D:D=D52),1)}, {FILTER('Entradas y salidas'!F:F, 'Entrada"&"s y salidas'!D:D=D52, NOT(ISBLANK('Entradas y salidas'!J:J))); INDEX(FILTER('Cortes x inversión'!J:J, 'Cortes x inversión'!D:D=D52),1)}), """"))"),"") | K52: =IF(E52="USD", SUMIF('Entradas y salidas'!D:D, D52, 'Entradas y salidas'!I:I), ) | L52: =IFERROR(__xludf.DUMMYFUNCTION("IF(E52=""USD"", INDEX(FILTER('Cortes x inversión'!G:G, 'Cortes x inversión'!D:D=D52),1), )"),"") | M52: =IF(OR(K52="", L52=""),"", L52 - ABS(K52)) | N52: =IFERROR(__xludf.DUMMYFUNCTION("IF(ISBLANK(D52),"""",IFERROR(XIRR({FILTER('Entradas y salidas'!I:I, 'Entradas y salidas'!D:D=D52, NOT(ISBLANK('Entradas y salidas'!I:I))); INDEX(FILTER('Cortes x inversión'!G:G, 'Cortes x inversión'!D:D=D52),1)}, {FILTER('Entradas y salidas'!F:F, 'Entrada"&"s y salidas'!D:D=D52, NOT(ISBLANK('Entradas y salidas'!I:I))); INDEX(FILTER('Cortes x inversión'!J:J, 'Cortes x inversión'!D:D=D52),1)}), """"))"),"") | P52: =IFERROR(__xludf.DUMMYFUNCTION("IF(K52="""","""", GOOGLEFINANCE(""CURRENCY:USDCOP"")) "),"") | Q52: =IFERROR(__xludf.DUMMYFUNCTION("IF(L52="""","""", GOOGLEFINANCE(""CURRENCY:USDCOP"")) "),"") | R52: =IF(K52="","", L52*P52) | S52: =IF(OR(Q52="", R52=""),"", R52 - ABS(Q52)) | T52: =IFERROR(__xludf.DUMMYFUNCTION("IF(ISBLANK(D52),"""",IFERROR(XIRR({FILTER('Entradas y salidas'!K:K, 'Entradas y salidas'!D:D=D52, NOT(ISBLANK('Entradas y salidas'!K:K))); INDEX(FILTER('Cortes x inversión'!I:I, 'Cortes x inversión'!D:D=D52),1)}, {FILTER('Entradas y salidas'!F:F, 'Entrada"&"s y salidas'!D:D=D52, NOT(ISBLANK('Entradas y salidas'!K:K))); INDEX(FILTER('Cortes x inversión'!J:J, 'Cortes x inversión'!D:D=D52),1)}), """"))"),"")
F53: =IF(E53="COP", SUMIF('Entradas y salidas'!D:D, D53, 'Entradas y salidas'!J:J), ) | G53: =IFERROR(__xludf.DUMMYFUNCTION("IF(E53=""COP"", INDEX(FILTER('Cortes x inversión'!F:F, 'Cortes x inversión'!D:D=D53),1), )"),"") | H53: =IF(OR(F53="", G53=""),"", G53 - ABS(F53)) | I53: =IFERROR(__xludf.DUMMYFUNCTION("IF(ISBLANK(D53),"""",IFERROR(XIRR({FILTER('Entradas y salidas'!J:J, 'Entradas y salidas'!D:D=D53, NOT(ISBLANK('Entradas y salidas'!J:J))); INDEX(FILTER('Cortes x inversión'!F:F, 'Cortes x inversión'!D:D=D53),1)}, {FILTER('Entradas y salidas'!F:F, 'Entrada"&"s y salidas'!D:D=D53, NOT(ISBLANK('Entradas y salidas'!J:J))); INDEX(FILTER('Cortes x inversión'!J:J, 'Cortes x inversión'!D:D=D53),1)}), """"))"),"") | K53: =IF(E53="USD", SUMIF('Entradas y salidas'!D:D, D53, 'Entradas y salidas'!I:I), ) | L53: =IFERROR(__xludf.DUMMYFUNCTION("IF(E53=""USD"", INDEX(FILTER('Cortes x inversión'!G:G, 'Cortes x inversión'!D:D=D53),1), )"),"") | M53: =IF(OR(K53="", L53=""),"", L53 - ABS(K53)) | N53: =IFERROR(__xludf.DUMMYFUNCTION("IF(ISBLANK(D53),"""",IFERROR(XIRR({FILTER('Entradas y salidas'!I:I, 'Entradas y salidas'!D:D=D53, NOT(ISBLANK('Entradas y salidas'!I:I))); INDEX(FILTER('Cortes x inversión'!G:G, 'Cortes x inversión'!D:D=D53),1)}, {FILTER('Entradas y salidas'!F:F, 'Entrada"&"s y salidas'!D:D=D53, NOT(ISBLANK('Entradas y salidas'!I:I))); INDEX(FILTER('Cortes x inversión'!J:J, 'Cortes x inversión'!D:D=D53),1)}), """"))"),"") | P53: =IFERROR(__xludf.DUMMYFUNCTION("IF(K53="""","""", GOOGLEFINANCE(""CURRENCY:USDCOP"")) "),"") | Q53: =IFERROR(__xludf.DUMMYFUNCTION("IF(L53="""","""", GOOGLEFINANCE(""CURRENCY:USDCOP"")) "),"") | R53: =IF(K53="","", L53*P53) | S53: =IF(OR(Q53="", R53=""),"", R53 - ABS(Q53)) | T53: =IFERROR(__xludf.DUMMYFUNCTION("IF(ISBLANK(D53),"""",IFERROR(XIRR({FILTER('Entradas y salidas'!K:K, 'Entradas y salidas'!D:D=D53, NOT(ISBLANK('Entradas y salidas'!K:K))); INDEX(FILTER('Cortes x inversión'!I:I, 'Cortes x inversión'!D:D=D53),1)}, {FILTER('Entradas y salidas'!F:F, 'Entrada"&"s y salidas'!D:D=D53, NOT(ISBLANK('Entradas y salidas'!K:K))); INDEX(FILTER('Cortes x inversión'!J:J, 'Cortes x inversión'!D:D=D53),1)}), """"))"),"")
F54: =IF(E54="COP", SUMIF('Entradas y salidas'!D:D, D54, 'Entradas y salidas'!J:J), ) | G54: =IFERROR(__xludf.DUMMYFUNCTION("IF(E54=""COP"", INDEX(FILTER('Cortes x inversión'!F:F, 'Cortes x inversión'!D:D=D54),1), )"),"") | H54: =IF(OR(F54="", G54=""),"", G54 - ABS(F54)) | I54: =IFERROR(__xludf.DUMMYFUNCTION("IF(ISBLANK(D54),"""",IFERROR(XIRR({FILTER('Entradas y salidas'!J:J, 'Entradas y salidas'!D:D=D54, NOT(ISBLANK('Entradas y salidas'!J:J))); INDEX(FILTER('Cortes x inversión'!F:F, 'Cortes x inversión'!D:D=D54),1)}, {FILTER('Entradas y salidas'!F:F, 'Entrada"&"s y salidas'!D:D=D54, NOT(ISBLANK('Entradas y salidas'!J:J))); INDEX(FILTER('Cortes x inversión'!J:J, 'Cortes x inversión'!D:D=D54),1)}), """"))"),"") | K54: =IF(E54="USD", SUMIF('Entradas y salidas'!D:D, D54, 'Entradas y salidas'!I:I), ) | L54: =IFERROR(__xludf.DUMMYFUNCTION("IF(E54=""USD"", INDEX(FILTER('Cortes x inversión'!G:G, 'Cortes x inversión'!D:D=D54),1), )"),"") | M54: =IF(OR(K54="", L54=""),"", L54 - ABS(K54)) | N54: =IFERROR(__xludf.DUMMYFUNCTION("IF(ISBLANK(D54),"""",IFERROR(XIRR({FILTER('Entradas y salidas'!I:I, 'Entradas y salidas'!D:D=D54, NOT(ISBLANK('Entradas y salidas'!I:I))); INDEX(FILTER('Cortes x inversión'!G:G, 'Cortes x inversión'!D:D=D54),1)}, {FILTER('Entradas y salidas'!F:F, 'Entrada"&"s y salidas'!D:D=D54, NOT(ISBLANK('Entradas y salidas'!I:I))); INDEX(FILTER('Cortes x inversión'!J:J, 'Cortes x inversión'!D:D=D54),1)}), """"))"),"") | P54: =IFERROR(__xludf.DUMMYFUNCTION("IF(K54="""","""", GOOGLEFINANCE(""CURRENCY:USDCOP"")) "),"") | Q54: =IFERROR(__xludf.DUMMYFUNCTION("IF(L54="""","""", GOOGLEFINANCE(""CURRENCY:USDCOP"")) "),"") | R54: =IF(K54="","", L54*P54) | S54: =IF(OR(Q54="", R54=""),"", R54 - ABS(Q54)) | T54: =IFERROR(__xludf.DUMMYFUNCTION("IF(ISBLANK(D54),"""",IFERROR(XIRR({FILTER('Entradas y salidas'!K:K, 'Entradas y salidas'!D:D=D54, NOT(ISBLANK('Entradas y salidas'!K:K))); INDEX(FILTER('Cortes x inversión'!I:I, 'Cortes x inversión'!D:D=D54),1)}, {FILTER('Entradas y salidas'!F:F, 'Entrada"&"s y salidas'!D:D=D54, NOT(ISBLANK('Entradas y salidas'!K:K))); INDEX(FILTER('Cortes x inversión'!J:J, 'Cortes x inversión'!D:D=D54),1)}), """"))"),"")
F55: =IF(E55="COP", SUMIF('Entradas y salidas'!D:D, D55, 'Entradas y salidas'!J:J), ) | G55: =IFERROR(__xludf.DUMMYFUNCTION("IF(E55=""COP"", INDEX(FILTER('Cortes x inversión'!F:F, 'Cortes x inversión'!D:D=D55),1), )"),"") | H55: =IF(OR(F55="", G55=""),"", G55 - ABS(F55)) | I55: =IFERROR(__xludf.DUMMYFUNCTION("IF(ISBLANK(D55),"""",IFERROR(XIRR({FILTER('Entradas y salidas'!J:J, 'Entradas y salidas'!D:D=D55, NOT(ISBLANK('Entradas y salidas'!J:J))); INDEX(FILTER('Cortes x inversión'!F:F, 'Cortes x inversión'!D:D=D55),1)}, {FILTER('Entradas y salidas'!F:F, 'Entrada"&"s y salidas'!D:D=D55, NOT(ISBLANK('Entradas y salidas'!J:J))); INDEX(FILTER('Cortes x inversión'!J:J, 'Cortes x inversión'!D:D=D55),1)}), """"))"),"") | K55: =IF(E55="USD", SUMIF('Entradas y salidas'!D:D, D55, 'Entradas y salidas'!I:I), ) | L55: =IFERROR(__xludf.DUMMYFUNCTION("IF(E55=""USD"", INDEX(FILTER('Cortes x inversión'!G:G, 'Cortes x inversión'!D:D=D55),1), )"),"") | M55: =IF(OR(K55="", L55=""),"", L55 - ABS(K55)) | N55: =IFERROR(__xludf.DUMMYFUNCTION("IF(ISBLANK(D55),"""",IFERROR(XIRR({FILTER('Entradas y salidas'!I:I, 'Entradas y salidas'!D:D=D55, NOT(ISBLANK('Entradas y salidas'!I:I))); INDEX(FILTER('Cortes x inversión'!G:G, 'Cortes x inversión'!D:D=D55),1)}, {FILTER('Entradas y salidas'!F:F, 'Entrada"&"s y salidas'!D:D=D55, NOT(ISBLANK('Entradas y salidas'!I:I))); INDEX(FILTER('Cortes x inversión'!J:J, 'Cortes x inversión'!D:D=D55),1)}), """"))"),"") | P55: =IFERROR(__xludf.DUMMYFUNCTION("IF(K55="""","""", GOOGLEFINANCE(""CURRENCY:USDCOP"")) "),"") | Q55: =IFERROR(__xludf.DUMMYFUNCTION("IF(L55="""","""", GOOGLEFINANCE(""CURRENCY:USDCOP"")) "),"") | R55: =IF(K55="","", L55*P55) | S55: =IF(OR(Q55="", R55=""),"", R55 - ABS(Q55)) | T55: =IFERROR(__xludf.DUMMYFUNCTION("IF(ISBLANK(D55),"""",IFERROR(XIRR({FILTER('Entradas y salidas'!K:K, 'Entradas y salidas'!D:D=D55, NOT(ISBLANK('Entradas y salidas'!K:K))); INDEX(FILTER('Cortes x inversión'!I:I, 'Cortes x inversión'!D:D=D55),1)}, {FILTER('Entradas y salidas'!F:F, 'Entrada"&"s y salidas'!D:D=D55, NOT(ISBLANK('Entradas y salidas'!K:K))); INDEX(FILTER('Cortes x inversión'!J:J, 'Cortes x inversión'!D:D=D55),1)}), """"))"),"")
F56: =IF(E56="COP", SUMIF('Entradas y salidas'!D:D, D56, 'Entradas y salidas'!J:J), ) | G56: =IFERROR(__xludf.DUMMYFUNCTION("IF(E56=""COP"", INDEX(FILTER('Cortes x inversión'!F:F, 'Cortes x inversión'!D:D=D56),1), )"),"") | H56: =IF(OR(F56="", G56=""),"", G56 - ABS(F56)) | I56: =IFERROR(__xludf.DUMMYFUNCTION("IF(ISBLANK(D56),"""",IFERROR(XIRR({FILTER('Entradas y salidas'!J:J, 'Entradas y salidas'!D:D=D56, NOT(ISBLANK('Entradas y salidas'!J:J))); INDEX(FILTER('Cortes x inversión'!F:F, 'Cortes x inversión'!D:D=D56),1)}, {FILTER('Entradas y salidas'!F:F, 'Entrada"&"s y salidas'!D:D=D56, NOT(ISBLANK('Entradas y salidas'!J:J))); INDEX(FILTER('Cortes x inversión'!J:J, 'Cortes x inversión'!D:D=D56),1)}), """"))"),"") | K56: =IF(E56="USD", SUMIF('Entradas y salidas'!D:D, D56, 'Entradas y salidas'!I:I), ) | L56: =IFERROR(__xludf.DUMMYFUNCTION("IF(E56=""USD"", INDEX(FILTER('Cortes x inversión'!G:G, 'Cortes x inversión'!D:D=D56),1), )"),"") | M56: =IF(OR(K56="", L56=""),"", L56 - ABS(K56)) | N56: =IFERROR(__xludf.DUMMYFUNCTION("IF(ISBLANK(D56),"""",IFERROR(XIRR({FILTER('Entradas y salidas'!I:I, 'Entradas y salidas'!D:D=D56, NOT(ISBLANK('Entradas y salidas'!I:I))); INDEX(FILTER('Cortes x inversión'!G:G, 'Cortes x inversión'!D:D=D56),1)}, {FILTER('Entradas y salidas'!F:F, 'Entrada"&"s y salidas'!D:D=D56, NOT(ISBLANK('Entradas y salidas'!I:I))); INDEX(FILTER('Cortes x inversión'!J:J, 'Cortes x inversión'!D:D=D56),1)}), """"))"),"") | P56: =IFERROR(__xludf.DUMMYFUNCTION("IF(K56="""","""", GOOGLEFINANCE(""CURRENCY:USDCOP"")) "),"") | Q56: =IFERROR(__xludf.DUMMYFUNCTION("IF(L56="""","""", GOOGLEFINANCE(""CURRENCY:USDCOP"")) "),"") | R56: =IF(K56="","", L56*P56) | S56: =IF(OR(Q56="", R56=""),"", R56 - ABS(Q56)) | T56: =IFERROR(__xludf.DUMMYFUNCTION("IF(ISBLANK(D56),"""",IFERROR(XIRR({FILTER('Entradas y salidas'!K:K, 'Entradas y salidas'!D:D=D56, NOT(ISBLANK('Entradas y salidas'!K:K))); INDEX(FILTER('Cortes x inversión'!I:I, 'Cortes x inversión'!D:D=D56),1)}, {FILTER('Entradas y salidas'!F:F, 'Entrada"&"s y salidas'!D:D=D56, NOT(ISBLANK('Entradas y salidas'!K:K))); INDEX(FILTER('Cortes x inversión'!J:J, 'Cortes x inversión'!D:D=D56),1)}), """"))"),"")
F57: =IF(E57="COP", SUMIF('Entradas y salidas'!D:D, D57, 'Entradas y salidas'!J:J), ) | G57: =IFERROR(__xludf.DUMMYFUNCTION("IF(E57=""COP"", INDEX(FILTER('Cortes x inversión'!F:F, 'Cortes x inversión'!D:D=D57),1), )"),"") | H57: =IF(OR(F57="", G57=""),"", G57 - ABS(F57)) | I57: =IFERROR(__xludf.DUMMYFUNCTION("IF(ISBLANK(D57),"""",IFERROR(XIRR({FILTER('Entradas y salidas'!J:J, 'Entradas y salidas'!D:D=D57, NOT(ISBLANK('Entradas y salidas'!J:J))); INDEX(FILTER('Cortes x inversión'!F:F, 'Cortes x inversión'!D:D=D57),1)}, {FILTER('Entradas y salidas'!F:F, 'Entrada"&"s y salidas'!D:D=D57, NOT(ISBLANK('Entradas y salidas'!J:J))); INDEX(FILTER('Cortes x inversión'!J:J, 'Cortes x inversión'!D:D=D57),1)}), """"))"),"") | K57: =IF(E57="USD", SUMIF('Entradas y salidas'!D:D, D57, 'Entradas y salidas'!I:I), ) | L57: =IFERROR(__xludf.DUMMYFUNCTION("IF(E57=""USD"", INDEX(FILTER('Cortes x inversión'!G:G, 'Cortes x inversión'!D:D=D57),1), )"),"") | M57: =IF(OR(K57="", L57=""),"", L57 - ABS(K57)) | N57: =IFERROR(__xludf.DUMMYFUNCTION("IF(ISBLANK(D57),"""",IFERROR(XIRR({FILTER('Entradas y salidas'!I:I, 'Entradas y salidas'!D:D=D57, NOT(ISBLANK('Entradas y salidas'!I:I))); INDEX(FILTER('Cortes x inversión'!G:G, 'Cortes x inversión'!D:D=D57),1)}, {FILTER('Entradas y salidas'!F:F, 'Entrada"&"s y salidas'!D:D=D57, NOT(ISBLANK('Entradas y salidas'!I:I))); INDEX(FILTER('Cortes x inversión'!J:J, 'Cortes x inversión'!D:D=D57),1)}), """"))"),"") | P57: =IFERROR(__xludf.DUMMYFUNCTION("IF(K57="""","""", GOOGLEFINANCE(""CURRENCY:USDCOP"")) "),"") | Q57: =IFERROR(__xludf.DUMMYFUNCTION("IF(L57="""","""", GOOGLEFINANCE(""CURRENCY:USDCOP"")) "),"") | R57: =IF(K57="","", L57*P57) | S57: =IF(OR(Q57="", R57=""),"", R57 - ABS(Q57)) | T57: =IFERROR(__xludf.DUMMYFUNCTION("IF(ISBLANK(D57),"""",IFERROR(XIRR({FILTER('Entradas y salidas'!K:K, 'Entradas y salidas'!D:D=D57, NOT(ISBLANK('Entradas y salidas'!K:K))); INDEX(FILTER('Cortes x inversión'!I:I, 'Cortes x inversión'!D:D=D57),1)}, {FILTER('Entradas y salidas'!F:F, 'Entrada"&"s y salidas'!D:D=D57, NOT(ISBLANK('Entradas y salidas'!K:K))); INDEX(FILTER('Cortes x inversión'!J:J, 'Cortes x inversión'!D:D=D57),1)}), """"))"),"")
F58: =IF(E58="COP", SUMIF('Entradas y salidas'!D:D, D58, 'Entradas y salidas'!J:J), ) | G58: =IFERROR(__xludf.DUMMYFUNCTION("IF(E58=""COP"", INDEX(FILTER('Cortes x inversión'!F:F, 'Cortes x inversión'!D:D=D58),1), )"),"") | H58: =IF(OR(F58="", G58=""),"", G58 - ABS(F58)) | I58: =IFERROR(__xludf.DUMMYFUNCTION("IF(ISBLANK(D58),"""",IFERROR(XIRR({FILTER('Entradas y salidas'!J:J, 'Entradas y salidas'!D:D=D58, NOT(ISBLANK('Entradas y salidas'!J:J))); INDEX(FILTER('Cortes x inversión'!F:F, 'Cortes x inversión'!D:D=D58),1)}, {FILTER('Entradas y salidas'!F:F, 'Entrada"&"s y salidas'!D:D=D58, NOT(ISBLANK('Entradas y salidas'!J:J))); INDEX(FILTER('Cortes x inversión'!J:J, 'Cortes x inversión'!D:D=D58),1)}), """"))"),"") | K58: =IF(E58="USD", SUMIF('Entradas y salidas'!D:D, D58, 'Entradas y salidas'!I:I), ) | L58: =IFERROR(__xludf.DUMMYFUNCTION("IF(E58=""USD"", INDEX(FILTER('Cortes x inversión'!G:G, 'Cortes x inversión'!D:D=D58),1), )"),"") | M58: =IF(OR(K58="", L58=""),"", L58 - ABS(K58)) | N58: =IFERROR(__xludf.DUMMYFUNCTION("IF(ISBLANK(D58),"""",IFERROR(XIRR({FILTER('Entradas y salidas'!I:I, 'Entradas y salidas'!D:D=D58, NOT(ISBLANK('Entradas y salidas'!I:I))); INDEX(FILTER('Cortes x inversión'!G:G, 'Cortes x inversión'!D:D=D58),1)}, {FILTER('Entradas y salidas'!F:F, 'Entrada"&"s y salidas'!D:D=D58, NOT(ISBLANK('Entradas y salidas'!I:I))); INDEX(FILTER('Cortes x inversión'!J:J, 'Cortes x inversión'!D:D=D58),1)}), """"))"),"") | P58: =IFERROR(__xludf.DUMMYFUNCTION("IF(K58="""","""", GOOGLEFINANCE(""CURRENCY:USDCOP"")) "),"") | Q58: =IFERROR(__xludf.DUMMYFUNCTION("IF(L58="""","""", GOOGLEFINANCE(""CURRENCY:USDCOP"")) "),"") | R58: =IF(K58="","", L58*P58) | S58: =IF(OR(Q58="", R58=""),"", R58 - ABS(Q58)) | T58: =IFERROR(__xludf.DUMMYFUNCTION("IF(ISBLANK(D58),"""",IFERROR(XIRR({FILTER('Entradas y salidas'!K:K, 'Entradas y salidas'!D:D=D58, NOT(ISBLANK('Entradas y salidas'!K:K))); INDEX(FILTER('Cortes x inversión'!I:I, 'Cortes x inversión'!D:D=D58),1)}, {FILTER('Entradas y salidas'!F:F, 'Entrada"&"s y salidas'!D:D=D58, NOT(ISBLANK('Entradas y salidas'!K:K))); INDEX(FILTER('Cortes x inversión'!J:J, 'Cortes x inversión'!D:D=D58),1)}), """"))"),"")
F59: =IF(E59="COP", SUMIF('Entradas y salidas'!D:D, D59, 'Entradas y salidas'!J:J), ) | G59: =IFERROR(__xludf.DUMMYFUNCTION("IF(E59=""COP"", INDEX(FILTER('Cortes x inversión'!F:F, 'Cortes x inversión'!D:D=D59),1), )"),"") | H59: =IF(OR(F59="", G59=""),"", G59 - ABS(F59)) | I59: =IFERROR(__xludf.DUMMYFUNCTION("IF(ISBLANK(D59),"""",IFERROR(XIRR({FILTER('Entradas y salidas'!J:J, 'Entradas y salidas'!D:D=D59, NOT(ISBLANK('Entradas y salidas'!J:J))); INDEX(FILTER('Cortes x inversión'!F:F, 'Cortes x inversión'!D:D=D59),1)}, {FILTER('Entradas y salidas'!F:F, 'Entrada"&"s y salidas'!D:D=D59, NOT(ISBLANK('Entradas y salidas'!J:J))); INDEX(FILTER('Cortes x inversión'!J:J, 'Cortes x inversión'!D:D=D59),1)}), """"))"),"") | K59: =IF(E59="USD", SUMIF('Entradas y salidas'!D:D, D59, 'Entradas y salidas'!I:I), ) | L59: =IFERROR(__xludf.DUMMYFUNCTION("IF(E59=""USD"", INDEX(FILTER('Cortes x inversión'!G:G, 'Cortes x inversión'!D:D=D59),1), )"),"") | M59: =IF(OR(K59="", L59=""),"", L59 - ABS(K59)) | N59: =IFERROR(__xludf.DUMMYFUNCTION("IF(ISBLANK(D59),"""",IFERROR(XIRR({FILTER('Entradas y salidas'!I:I, 'Entradas y salidas'!D:D=D59, NOT(ISBLANK('Entradas y salidas'!I:I))); INDEX(FILTER('Cortes x inversión'!G:G, 'Cortes x inversión'!D:D=D59),1)}, {FILTER('Entradas y salidas'!F:F, 'Entrada"&"s y salidas'!D:D=D59, NOT(ISBLANK('Entradas y salidas'!I:I))); INDEX(FILTER('Cortes x inversión'!J:J, 'Cortes x inversión'!D:D=D59),1)}), """"))"),"") | P59: =IFERROR(__xludf.DUMMYFUNCTION("IF(K59="""","""", GOOGLEFINANCE(""CURRENCY:USDCOP"")) "),"") | Q59: =IFERROR(__xludf.DUMMYFUNCTION("IF(L59="""","""", GOOGLEFINANCE(""CURRENCY:USDCOP"")) "),"") | R59: =IF(K59="","", L59*P59) | S59: =IF(OR(Q59="", R59=""),"", R59 - ABS(Q59)) | T59: =IFERROR(__xludf.DUMMYFUNCTION("IF(ISBLANK(D59),"""",IFERROR(XIRR({FILTER('Entradas y salidas'!K:K, 'Entradas y salidas'!D:D=D59, NOT(ISBLANK('Entradas y salidas'!K:K))); INDEX(FILTER('Cortes x inversión'!I:I, 'Cortes x inversión'!D:D=D59),1)}, {FILTER('Entradas y salidas'!F:F, 'Entrada"&"s y salidas'!D:D=D59, NOT(ISBLANK('Entradas y salidas'!K:K))); INDEX(FILTER('Cortes x inversión'!J:J, 'Cortes x inversión'!D:D=D59),1)}), """"))"),"")
F60: =IF(E60="COP", SUMIF('Entradas y salidas'!D:D, D60, 'Entradas y salidas'!J:J), ) | G60: =IFERROR(__xludf.DUMMYFUNCTION("IF(E60=""COP"", INDEX(FILTER('Cortes x inversión'!F:F, 'Cortes x inversión'!D:D=D60),1), )"),"") | H60: =IF(OR(F60="", G60=""),"", G60 - ABS(F60)) | I60: =IFERROR(__xludf.DUMMYFUNCTION("IF(ISBLANK(D60),"""",IFERROR(XIRR({FILTER('Entradas y salidas'!J:J, 'Entradas y salidas'!D:D=D60, NOT(ISBLANK('Entradas y salidas'!J:J))); INDEX(FILTER('Cortes x inversión'!F:F, 'Cortes x inversión'!D:D=D60),1)}, {FILTER('Entradas y salidas'!F:F, 'Entrada"&"s y salidas'!D:D=D60, NOT(ISBLANK('Entradas y salidas'!J:J))); INDEX(FILTER('Cortes x inversión'!J:J, 'Cortes x inversión'!D:D=D60),1)}), """"))"),"") | K60: =IF(E60="USD", SUMIF('Entradas y salidas'!D:D, D60, 'Entradas y salidas'!I:I), ) | L60: =IFERROR(__xludf.DUMMYFUNCTION("IF(E60=""USD"", INDEX(FILTER('Cortes x inversión'!G:G, 'Cortes x inversión'!D:D=D60),1), )"),"") | M60: =IF(OR(K60="", L60=""),"", L60 - ABS(K60)) | N60: =IFERROR(__xludf.DUMMYFUNCTION("IF(ISBLANK(D60),"""",IFERROR(XIRR({FILTER('Entradas y salidas'!I:I, 'Entradas y salidas'!D:D=D60, NOT(ISBLANK('Entradas y salidas'!I:I))); INDEX(FILTER('Cortes x inversión'!G:G, 'Cortes x inversión'!D:D=D60),1)}, {FILTER('Entradas y salidas'!F:F, 'Entrada"&"s y salidas'!D:D=D60, NOT(ISBLANK('Entradas y salidas'!I:I))); INDEX(FILTER('Cortes x inversión'!J:J, 'Cortes x inversión'!D:D=D60),1)}), """"))"),"") | P60: =IFERROR(__xludf.DUMMYFUNCTION("IF(K60="""","""", GOOGLEFINANCE(""CURRENCY:USDCOP"")) "),"") | Q60: =IFERROR(__xludf.DUMMYFUNCTION("IF(L60="""","""", GOOGLEFINANCE(""CURRENCY:USDCOP"")) "),"") | R60: =IF(K60="","", L60*P60) | S60: =IF(OR(Q60="", R60=""),"", R60 - ABS(Q60)) | T60: =IFERROR(__xludf.DUMMYFUNCTION("IF(ISBLANK(D60),"""",IFERROR(XIRR({FILTER('Entradas y salidas'!K:K, 'Entradas y salidas'!D:D=D60, NOT(ISBLANK('Entradas y salidas'!K:K))); INDEX(FILTER('Cortes x inversión'!I:I, 'Cortes x inversión'!D:D=D60),1)}, {FILTER('Entradas y salidas'!F:F, 'Entrada"&"s y salidas'!D:D=D60, NOT(ISBLANK('Entradas y salidas'!K:K))); INDEX(FILTER('Cortes x inversión'!J:J, 'Cortes x inversión'!D:D=D60),1)}), """"))"),"")
F61: =IF(E61="COP", SUMIF('Entradas y salidas'!D:D, D61, 'Entradas y salidas'!J:J), ) | G61: =IFERROR(__xludf.DUMMYFUNCTION("IF(E61=""COP"", INDEX(FILTER('Cortes x inversión'!F:F, 'Cortes x inversión'!D:D=D61),1), )"),"") | H61: =IF(OR(F61="", G61=""),"", G61 - ABS(F61)) | I61: =IFERROR(__xludf.DUMMYFUNCTION("IF(ISBLANK(D61),"""",IFERROR(XIRR({FILTER('Entradas y salidas'!J:J, 'Entradas y salidas'!D:D=D61, NOT(ISBLANK('Entradas y salidas'!J:J))); INDEX(FILTER('Cortes x inversión'!F:F, 'Cortes x inversión'!D:D=D61),1)}, {FILTER('Entradas y salidas'!F:F, 'Entrada"&"s y salidas'!D:D=D61, NOT(ISBLANK('Entradas y salidas'!J:J))); INDEX(FILTER('Cortes x inversión'!J:J, 'Cortes x inversión'!D:D=D61),1)}), """"))"),"") | K61: =IF(E61="USD", SUMIF('Entradas y salidas'!D:D, D61, 'Entradas y salidas'!I:I), ) | L61: =IFERROR(__xludf.DUMMYFUNCTION("IF(E61=""USD"", INDEX(FILTER('Cortes x inversión'!G:G, 'Cortes x inversión'!D:D=D61),1), )"),"") | M61: =IF(OR(K61="", L61=""),"", L61 - ABS(K61)) | N61: =IFERROR(__xludf.DUMMYFUNCTION("IF(ISBLANK(D61),"""",IFERROR(XIRR({FILTER('Entradas y salidas'!I:I, 'Entradas y salidas'!D:D=D61, NOT(ISBLANK('Entradas y salidas'!I:I))); INDEX(FILTER('Cortes x inversión'!G:G, 'Cortes x inversión'!D:D=D61),1)}, {FILTER('Entradas y salidas'!F:F, 'Entrada"&"s y salidas'!D:D=D61, NOT(ISBLANK('Entradas y salidas'!I:I))); INDEX(FILTER('Cortes x inversión'!J:J, 'Cortes x inversión'!D:D=D61),1)}), """"))"),"") | P61: =IFERROR(__xludf.DUMMYFUNCTION("IF(K61="""","""", GOOGLEFINANCE(""CURRENCY:USDCOP"")) "),"") | Q61: =IFERROR(__xludf.DUMMYFUNCTION("IF(L61="""","""", GOOGLEFINANCE(""CURRENCY:USDCOP"")) "),"") | R61: =IF(K61="","", L61*P61) | S61: =IF(OR(Q61="", R61=""),"", R61 - ABS(Q61)) | T61: =IFERROR(__xludf.DUMMYFUNCTION("IF(ISBLANK(D61),"""",IFERROR(XIRR({FILTER('Entradas y salidas'!K:K, 'Entradas y salidas'!D:D=D61, NOT(ISBLANK('Entradas y salidas'!K:K))); INDEX(FILTER('Cortes x inversión'!I:I, 'Cortes x inversión'!D:D=D61),1)}, {FILTER('Entradas y salidas'!F:F, 'Entrada"&"s y salidas'!D:D=D61, NOT(ISBLANK('Entradas y salidas'!K:K))); INDEX(FILTER('Cortes x inversión'!J:J, 'Cortes x inversión'!D:D=D61),1)}), """"))"),"")
F62: =IF(E62="COP", SUMIF('Entradas y salidas'!D:D, D62, 'Entradas y salidas'!J:J), ) | G62: =IFERROR(__xludf.DUMMYFUNCTION("IF(E62=""COP"", INDEX(FILTER('Cortes x inversión'!F:F, 'Cortes x inversión'!D:D=D62),1), )"),"") | H62: =IF(OR(F62="", G62=""),"", G62 - ABS(F62)) | I62: =IFERROR(__xludf.DUMMYFUNCTION("IF(ISBLANK(D62),"""",IFERROR(XIRR({FILTER('Entradas y salidas'!J:J, 'Entradas y salidas'!D:D=D62, NOT(ISBLANK('Entradas y salidas'!J:J))); INDEX(FILTER('Cortes x inversión'!F:F, 'Cortes x inversión'!D:D=D62),1)}, {FILTER('Entradas y salidas'!F:F, 'Entrada"&"s y salidas'!D:D=D62, NOT(ISBLANK('Entradas y salidas'!J:J))); INDEX(FILTER('Cortes x inversión'!J:J, 'Cortes x inversión'!D:D=D62),1)}), """"))"),"") | K62: =IF(E62="USD", SUMIF('Entradas y salidas'!D:D, D62, 'Entradas y salidas'!I:I), ) | L62: =IFERROR(__xludf.DUMMYFUNCTION("IF(E62=""USD"", INDEX(FILTER('Cortes x inversión'!G:G, 'Cortes x inversión'!D:D=D62),1), )"),"") | M62: =IF(OR(K62="", L62=""),"", L62 - ABS(K62)) | N62: =IFERROR(__xludf.DUMMYFUNCTION("IF(ISBLANK(D62),"""",IFERROR(XIRR({FILTER('Entradas y salidas'!I:I, 'Entradas y salidas'!D:D=D62, NOT(ISBLANK('Entradas y salidas'!I:I))); INDEX(FILTER('Cortes x inversión'!G:G, 'Cortes x inversión'!D:D=D62),1)}, {FILTER('Entradas y salidas'!F:F, 'Entrada"&"s y salidas'!D:D=D62, NOT(ISBLANK('Entradas y salidas'!I:I))); INDEX(FILTER('Cortes x inversión'!J:J, 'Cortes x inversión'!D:D=D62),1)}), """"))"),"") | P62: =IFERROR(__xludf.DUMMYFUNCTION("IF(K62="""","""", GOOGLEFINANCE(""CURRENCY:USDCOP"")) "),"") | Q62: =IFERROR(__xludf.DUMMYFUNCTION("IF(L62="""","""", GOOGLEFINANCE(""CURRENCY:USDCOP"")) "),"") | R62: =IF(K62="","", L62*P62) | S62: =IF(OR(Q62="", R62=""),"", R62 - ABS(Q62)) | T62: =IFERROR(__xludf.DUMMYFUNCTION("IF(ISBLANK(D62),"""",IFERROR(XIRR({FILTER('Entradas y salidas'!K:K, 'Entradas y salidas'!D:D=D62, NOT(ISBLANK('Entradas y salidas'!K:K))); INDEX(FILTER('Cortes x inversión'!I:I, 'Cortes x inversión'!D:D=D62),1)}, {FILTER('Entradas y salidas'!F:F, 'Entrada"&"s y salidas'!D:D=D62, NOT(ISBLANK('Entradas y salidas'!K:K))); INDEX(FILTER('Cortes x inversión'!J:J, 'Cortes x inversión'!D:D=D62),1)}), """"))"),"")
F63: =IF(E63="COP", SUMIF('Entradas y salidas'!D:D, D63, 'Entradas y salidas'!J:J), ) | G63: =IFERROR(__xludf.DUMMYFUNCTION("IF(E63=""COP"", INDEX(FILTER('Cortes x inversión'!F:F, 'Cortes x inversión'!D:D=D63),1), )"),"") | H63: =IF(OR(F63="", G63=""),"", G63 - ABS(F63)) | I63: =IFERROR(__xludf.DUMMYFUNCTION("IF(ISBLANK(D63),"""",IFERROR(XIRR({FILTER('Entradas y salidas'!J:J, 'Entradas y salidas'!D:D=D63, NOT(ISBLANK('Entradas y salidas'!J:J))); INDEX(FILTER('Cortes x inversión'!F:F, 'Cortes x inversión'!D:D=D63),1)}, {FILTER('Entradas y salidas'!F:F, 'Entrada"&"s y salidas'!D:D=D63, NOT(ISBLANK('Entradas y salidas'!J:J))); INDEX(FILTER('Cortes x inversión'!J:J, 'Cortes x inversión'!D:D=D63),1)}), """"))"),"") | K63: =IF(E63="USD", SUMIF('Entradas y salidas'!D:D, D63, 'Entradas y salidas'!I:I), ) | L63: =IFERROR(__xludf.DUMMYFUNCTION("IF(E63=""USD"", INDEX(FILTER('Cortes x inversión'!G:G, 'Cortes x inversión'!D:D=D63),1), )"),"") | M63: =IF(OR(K63="", L63=""),"", L63 - ABS(K63)) | N63: =IFERROR(__xludf.DUMMYFUNCTION("IF(ISBLANK(D63),"""",IFERROR(XIRR({FILTER('Entradas y salidas'!I:I, 'Entradas y salidas'!D:D=D63, NOT(ISBLANK('Entradas y salidas'!I:I))); INDEX(FILTER('Cortes x inversión'!G:G, 'Cortes x inversión'!D:D=D63),1)}, {FILTER('Entradas y salidas'!F:F, 'Entrada"&"s y salidas'!D:D=D63, NOT(ISBLANK('Entradas y salidas'!I:I))); INDEX(FILTER('Cortes x inversión'!J:J, 'Cortes x inversión'!D:D=D63),1)}), """"))"),"") | P63: =IFERROR(__xludf.DUMMYFUNCTION("IF(K63="""","""", GOOGLEFINANCE(""CURRENCY:USDCOP"")) "),"") | Q63: =IFERROR(__xludf.DUMMYFUNCTION("IF(L63="""","""", GOOGLEFINANCE(""CURRENCY:USDCOP"")) "),"") | R63: =IF(K63="","", L63*P63) | S63: =IF(OR(Q63="", R63=""),"", R63 - ABS(Q63)) | T63: =IFERROR(__xludf.DUMMYFUNCTION("IF(ISBLANK(D63),"""",IFERROR(XIRR({FILTER('Entradas y salidas'!K:K, 'Entradas y salidas'!D:D=D63, NOT(ISBLANK('Entradas y salidas'!K:K))); INDEX(FILTER('Cortes x inversión'!I:I, 'Cortes x inversión'!D:D=D63),1)}, {FILTER('Entradas y salidas'!F:F, 'Entrada"&"s y salidas'!D:D=D63, NOT(ISBLANK('Entradas y salidas'!K:K))); INDEX(FILTER('Cortes x inversión'!J:J, 'Cortes x inversión'!D:D=D63),1)}), """"))"),"")
F64: =IF(E64="COP", SUMIF('Entradas y salidas'!D:D, D64, 'Entradas y salidas'!J:J), ) | G64: =IFERROR(__xludf.DUMMYFUNCTION("IF(E64=""COP"", INDEX(FILTER('Cortes x inversión'!F:F, 'Cortes x inversión'!D:D=D64),1), )"),"") | H64: =IF(OR(F64="", G64=""),"", G64 - ABS(F64)) | I64: =IFERROR(__xludf.DUMMYFUNCTION("IF(ISBLANK(D64),"""",IFERROR(XIRR({FILTER('Entradas y salidas'!J:J, 'Entradas y salidas'!D:D=D64, NOT(ISBLANK('Entradas y salidas'!J:J))); INDEX(FILTER('Cortes x inversión'!F:F, 'Cortes x inversión'!D:D=D64),1)}, {FILTER('Entradas y salidas'!F:F, 'Entrada"&"s y salidas'!D:D=D64, NOT(ISBLANK('Entradas y salidas'!J:J))); INDEX(FILTER('Cortes x inversión'!J:J, 'Cortes x inversión'!D:D=D64),1)}), """"))"),"") | K64: =IF(E64="USD", SUMIF('Entradas y salidas'!D:D, D64, 'Entradas y salidas'!I:I), ) | L64: =IFERROR(__xludf.DUMMYFUNCTION("IF(E64=""USD"", INDEX(FILTER('Cortes x inversión'!G:G, 'Cortes x inversión'!D:D=D64),1), )"),"") | M64: =IF(OR(K64="", L64=""),"", L64 - ABS(K64)) | N64: =IFERROR(__xludf.DUMMYFUNCTION("IF(ISBLANK(D64),"""",IFERROR(XIRR({FILTER('Entradas y salidas'!I:I, 'Entradas y salidas'!D:D=D64, NOT(ISBLANK('Entradas y salidas'!I:I))); INDEX(FILTER('Cortes x inversión'!G:G, 'Cortes x inversión'!D:D=D64),1)}, {FILTER('Entradas y salidas'!F:F, 'Entrada"&"s y salidas'!D:D=D64, NOT(ISBLANK('Entradas y salidas'!I:I))); INDEX(FILTER('Cortes x inversión'!J:J, 'Cortes x inversión'!D:D=D64),1)}), """"))"),"") | P64: =IFERROR(__xludf.DUMMYFUNCTION("IF(K64="""","""", GOOGLEFINANCE(""CURRENCY:USDCOP"")) "),"") | Q64: =IFERROR(__xludf.DUMMYFUNCTION("IF(L64="""","""", GOOGLEFINANCE(""CURRENCY:USDCOP"")) "),"") | R64: =IF(K64="","", L64*P64) | S64: =IF(OR(Q64="", R64=""),"", R64 - ABS(Q64)) | T64: =IFERROR(__xludf.DUMMYFUNCTION("IF(ISBLANK(D64),"""",IFERROR(XIRR({FILTER('Entradas y salidas'!K:K, 'Entradas y salidas'!D:D=D64, NOT(ISBLANK('Entradas y salidas'!K:K))); INDEX(FILTER('Cortes x inversión'!I:I, 'Cortes x inversión'!D:D=D64),1)}, {FILTER('Entradas y salidas'!F:F, 'Entrada"&"s y salidas'!D:D=D64, NOT(ISBLANK('Entradas y salidas'!K:K))); INDEX(FILTER('Cortes x inversión'!J:J, 'Cortes x inversión'!D:D=D64),1)}), """"))"),"")
F65: =IF(E65="COP", SUMIF('Entradas y salidas'!D:D, D65, 'Entradas y salidas'!J:J), ) | G65: =IFERROR(__xludf.DUMMYFUNCTION("IF(E65=""COP"", INDEX(FILTER('Cortes x inversión'!F:F, 'Cortes x inversión'!D:D=D65),1), )"),"") | H65: =IF(OR(F65="", G65=""),"", G65 - ABS(F65)) | I65: =IFERROR(__xludf.DUMMYFUNCTION("IF(ISBLANK(D65),"""",IFERROR(XIRR({FILTER('Entradas y salidas'!J:J, 'Entradas y salidas'!D:D=D65, NOT(ISBLANK('Entradas y salidas'!J:J))); INDEX(FILTER('Cortes x inversión'!F:F, 'Cortes x inversión'!D:D=D65),1)}, {FILTER('Entradas y salidas'!F:F, 'Entrada"&"s y salidas'!D:D=D65, NOT(ISBLANK('Entradas y salidas'!J:J))); INDEX(FILTER('Cortes x inversión'!J:J, 'Cortes x inversión'!D:D=D65),1)}), """"))"),"") | K65: =IF(E65="USD", SUMIF('Entradas y salidas'!D:D, D65, 'Entradas y salidas'!I:I), ) | L65: =IFERROR(__xludf.DUMMYFUNCTION("IF(E65=""USD"", INDEX(FILTER('Cortes x inversión'!G:G, 'Cortes x inversión'!D:D=D65),1), )"),"") | M65: =IF(OR(K65="", L65=""),"", L65 - ABS(K65)) | N65: =IFERROR(__xludf.DUMMYFUNCTION("IF(ISBLANK(D65),"""",IFERROR(XIRR({FILTER('Entradas y salidas'!I:I, 'Entradas y salidas'!D:D=D65, NOT(ISBLANK('Entradas y salidas'!I:I))); INDEX(FILTER('Cortes x inversión'!G:G, 'Cortes x inversión'!D:D=D65),1)}, {FILTER('Entradas y salidas'!F:F, 'Entrada"&"s y salidas'!D:D=D65, NOT(ISBLANK('Entradas y salidas'!I:I))); INDEX(FILTER('Cortes x inversión'!J:J, 'Cortes x inversión'!D:D=D65),1)}), """"))"),"") | P65: =IFERROR(__xludf.DUMMYFUNCTION("IF(K65="""","""", GOOGLEFINANCE(""CURRENCY:USDCOP"")) "),"") | Q65: =IFERROR(__xludf.DUMMYFUNCTION("IF(L65="""","""", GOOGLEFINANCE(""CURRENCY:USDCOP"")) "),"") | R65: =IF(K65="","", L65*P65) | S65: =IF(OR(Q65="", R65=""),"", R65 - ABS(Q65)) | T65: =IFERROR(__xludf.DUMMYFUNCTION("IF(ISBLANK(D65),"""",IFERROR(XIRR({FILTER('Entradas y salidas'!K:K, 'Entradas y salidas'!D:D=D65, NOT(ISBLANK('Entradas y salidas'!K:K))); INDEX(FILTER('Cortes x inversión'!I:I, 'Cortes x inversión'!D:D=D65),1)}, {FILTER('Entradas y salidas'!F:F, 'Entrada"&"s y salidas'!D:D=D65, NOT(ISBLANK('Entradas y salidas'!K:K))); INDEX(FILTER('Cortes x inversión'!J:J, 'Cortes x inversión'!D:D=D65),1)}), """"))"),"")
F66: =IF(E66="COP", SUMIF('Entradas y salidas'!D:D, D66, 'Entradas y salidas'!J:J), ) | G66: =IFERROR(__xludf.DUMMYFUNCTION("IF(E66=""COP"", INDEX(FILTER('Cortes x inversión'!F:F, 'Cortes x inversión'!D:D=D66),1), )"),"") | H66: =IF(OR(F66="", G66=""),"", G66 - ABS(F66)) | I66: =IFERROR(__xludf.DUMMYFUNCTION("IF(ISBLANK(D66),"""",IFERROR(XIRR({FILTER('Entradas y salidas'!J:J, 'Entradas y salidas'!D:D=D66, NOT(ISBLANK('Entradas y salidas'!J:J))); INDEX(FILTER('Cortes x inversión'!F:F, 'Cortes x inversión'!D:D=D66),1)}, {FILTER('Entradas y salidas'!F:F, 'Entrada"&"s y salidas'!D:D=D66, NOT(ISBLANK('Entradas y salidas'!J:J))); INDEX(FILTER('Cortes x inversión'!J:J, 'Cortes x inversión'!D:D=D66),1)}), """"))"),"") | K66: =IF(E66="USD", SUMIF('Entradas y salidas'!D:D, D66, 'Entradas y salidas'!I:I), ) | L66: =IFERROR(__xludf.DUMMYFUNCTION("IF(E66=""USD"", INDEX(FILTER('Cortes x inversión'!G:G, 'Cortes x inversión'!D:D=D66),1), )"),"") | M66: =IF(OR(K66="", L66=""),"", L66 - ABS(K66)) | N66: =IFERROR(__xludf.DUMMYFUNCTION("IF(ISBLANK(D66),"""",IFERROR(XIRR({FILTER('Entradas y salidas'!I:I, 'Entradas y salidas'!D:D=D66, NOT(ISBLANK('Entradas y salidas'!I:I))); INDEX(FILTER('Cortes x inversión'!G:G, 'Cortes x inversión'!D:D=D66),1)}, {FILTER('Entradas y salidas'!F:F, 'Entrada"&"s y salidas'!D:D=D66, NOT(ISBLANK('Entradas y salidas'!I:I))); INDEX(FILTER('Cortes x inversión'!J:J, 'Cortes x inversión'!D:D=D66),1)}), """"))"),"") | P66: =IFERROR(__xludf.DUMMYFUNCTION("IF(K66="""","""", GOOGLEFINANCE(""CURRENCY:USDCOP"")) "),"") | Q66: =IFERROR(__xludf.DUMMYFUNCTION("IF(L66="""","""", GOOGLEFINANCE(""CURRENCY:USDCOP"")) "),"") | R66: =IF(K66="","", L66*P66) | S66: =IF(OR(Q66="", R66=""),"", R66 - ABS(Q66)) | T66: =IFERROR(__xludf.DUMMYFUNCTION("IF(ISBLANK(D66),"""",IFERROR(XIRR({FILTER('Entradas y salidas'!K:K, 'Entradas y salidas'!D:D=D66, NOT(ISBLANK('Entradas y salidas'!K:K))); INDEX(FILTER('Cortes x inversión'!I:I, 'Cortes x inversión'!D:D=D66),1)}, {FILTER('Entradas y salidas'!F:F, 'Entrada"&"s y salidas'!D:D=D66, NOT(ISBLANK('Entradas y salidas'!K:K))); INDEX(FILTER('Cortes x inversión'!J:J, 'Cortes x inversión'!D:D=D66),1)}), """"))"),"")
F67: =IF(E67="COP", SUMIF('Entradas y salidas'!D:D, D67, 'Entradas y salidas'!J:J), ) | G67: =IFERROR(__xludf.DUMMYFUNCTION("IF(E67=""COP"", INDEX(FILTER('Cortes x inversión'!F:F, 'Cortes x inversión'!D:D=D67),1), )"),"") | H67: =IF(OR(F67="", G67=""),"", G67 - ABS(F67)) | I67: =IFERROR(__xludf.DUMMYFUNCTION("IF(ISBLANK(D67),"""",IFERROR(XIRR({FILTER('Entradas y salidas'!J:J, 'Entradas y salidas'!D:D=D67, NOT(ISBLANK('Entradas y salidas'!J:J))); INDEX(FILTER('Cortes x inversión'!F:F, 'Cortes x inversión'!D:D=D67),1)}, {FILTER('Entradas y salidas'!F:F, 'Entrada"&"s y salidas'!D:D=D67, NOT(ISBLANK('Entradas y salidas'!J:J))); INDEX(FILTER('Cortes x inversión'!J:J, 'Cortes x inversión'!D:D=D67),1)}), """"))"),"") | K67: =IF(E67="USD", SUMIF('Entradas y salidas'!D:D, D67, 'Entradas y salidas'!I:I), ) | L67: =IFERROR(__xludf.DUMMYFUNCTION("IF(E67=""USD"", INDEX(FILTER('Cortes x inversión'!G:G, 'Cortes x inversión'!D:D=D67),1), )"),"") | M67: =IF(OR(K67="", L67=""),"", L67 - ABS(K67)) | N67: =IFERROR(__xludf.DUMMYFUNCTION("IF(ISBLANK(D67),"""",IFERROR(XIRR({FILTER('Entradas y salidas'!I:I, 'Entradas y salidas'!D:D=D67, NOT(ISBLANK('Entradas y salidas'!I:I))); INDEX(FILTER('Cortes x inversión'!G:G, 'Cortes x inversión'!D:D=D67),1)}, {FILTER('Entradas y salidas'!F:F, 'Entrada"&"s y salidas'!D:D=D67, NOT(ISBLANK('Entradas y salidas'!I:I))); INDEX(FILTER('Cortes x inversión'!J:J, 'Cortes x inversión'!D:D=D67),1)}), """"))"),"") | P67: =IFERROR(__xludf.DUMMYFUNCTION("IF(K67="""","""", GOOGLEFINANCE(""CURRENCY:USDCOP"")) "),"") | Q67: =IFERROR(__xludf.DUMMYFUNCTION("IF(L67="""","""", GOOGLEFINANCE(""CURRENCY:USDCOP"")) "),"") | R67: =IF(K67="","", L67*P67) | S67: =IF(OR(Q67="", R67=""),"", R67 - ABS(Q67)) | T67: =IFERROR(__xludf.DUMMYFUNCTION("IF(ISBLANK(D67),"""",IFERROR(XIRR({FILTER('Entradas y salidas'!K:K, 'Entradas y salidas'!D:D=D67, NOT(ISBLANK('Entradas y salidas'!K:K))); INDEX(FILTER('Cortes x inversión'!I:I, 'Cortes x inversión'!D:D=D67),1)}, {FILTER('Entradas y salidas'!F:F, 'Entrada"&"s y salidas'!D:D=D67, NOT(ISBLANK('Entradas y salidas'!K:K))); INDEX(FILTER('Cortes x inversión'!J:J, 'Cortes x inversión'!D:D=D67),1)}), """"))"),"")
F68: =IF(E68="COP", SUMIF('Entradas y salidas'!D:D, D68, 'Entradas y salidas'!J:J), ) | G68: =IFERROR(__xludf.DUMMYFUNCTION("IF(E68=""COP"", INDEX(FILTER('Cortes x inversión'!F:F, 'Cortes x inversión'!D:D=D68),1), )"),"") | H68: =IF(OR(F68="", G68=""),"", G68 - ABS(F68)) | I68: =IFERROR(__xludf.DUMMYFUNCTION("IF(ISBLANK(D68),"""",IFERROR(XIRR({FILTER('Entradas y salidas'!J:J, 'Entradas y salidas'!D:D=D68, NOT(ISBLANK('Entradas y salidas'!J:J))); INDEX(FILTER('Cortes x inversión'!F:F, 'Cortes x inversión'!D:D=D68),1)}, {FILTER('Entradas y salidas'!F:F, 'Entrada"&"s y salidas'!D:D=D68, NOT(ISBLANK('Entradas y salidas'!J:J))); INDEX(FILTER('Cortes x inversión'!J:J, 'Cortes x inversión'!D:D=D68),1)}), """"))"),"") | K68: =IF(E68="USD", SUMIF('Entradas y salidas'!D:D, D68, 'Entradas y salidas'!I:I), ) | L68: =IFERROR(__xludf.DUMMYFUNCTION("IF(E68=""USD"", INDEX(FILTER('Cortes x inversión'!G:G, 'Cortes x inversión'!D:D=D68),1), )"),"") | M68: =IF(OR(K68="", L68=""),"", L68 - ABS(K68)) | N68: =IFERROR(__xludf.DUMMYFUNCTION("IF(ISBLANK(D68),"""",IFERROR(XIRR({FILTER('Entradas y salidas'!I:I, 'Entradas y salidas'!D:D=D68, NOT(ISBLANK('Entradas y salidas'!I:I))); INDEX(FILTER('Cortes x inversión'!G:G, 'Cortes x inversión'!D:D=D68),1)}, {FILTER('Entradas y salidas'!F:F, 'Entrada"&"s y salidas'!D:D=D68, NOT(ISBLANK('Entradas y salidas'!I:I))); INDEX(FILTER('Cortes x inversión'!J:J, 'Cortes x inversión'!D:D=D68),1)}), """"))"),"") | P68: =IFERROR(__xludf.DUMMYFUNCTION("IF(K68="""","""", GOOGLEFINANCE(""CURRENCY:USDCOP"")) "),"") | Q68: =IFERROR(__xludf.DUMMYFUNCTION("IF(L68="""","""", GOOGLEFINANCE(""CURRENCY:USDCOP"")) "),"") | R68: =IF(K68="","", L68*P68) | S68: =IF(OR(Q68="", R68=""),"", R68 - ABS(Q68)) | T68: =IFERROR(__xludf.DUMMYFUNCTION("IF(ISBLANK(D68),"""",IFERROR(XIRR({FILTER('Entradas y salidas'!K:K, 'Entradas y salidas'!D:D=D68, NOT(ISBLANK('Entradas y salidas'!K:K))); INDEX(FILTER('Cortes x inversión'!I:I, 'Cortes x inversión'!D:D=D68),1)}, {FILTER('Entradas y salidas'!F:F, 'Entrada"&"s y salidas'!D:D=D68, NOT(ISBLANK('Entradas y salidas'!K:K))); INDEX(FILTER('Cortes x inversión'!J:J, 'Cortes x inversión'!D:D=D68),1)}), """"))"),"")
F69: =IF(E69="COP", SUMIF('Entradas y salidas'!D:D, D69, 'Entradas y salidas'!J:J), ) | G69: =IFERROR(__xludf.DUMMYFUNCTION("IF(E69=""COP"", INDEX(FILTER('Cortes x inversión'!F:F, 'Cortes x inversión'!D:D=D69),1), )"),"") | H69: =IF(OR(F69="", G69=""),"", G69 - ABS(F69)) | I69: =IFERROR(__xludf.DUMMYFUNCTION("IF(ISBLANK(D69),"""",IFERROR(XIRR({FILTER('Entradas y salidas'!J:J, 'Entradas y salidas'!D:D=D69, NOT(ISBLANK('Entradas y salidas'!J:J))); INDEX(FILTER('Cortes x inversión'!F:F, 'Cortes x inversión'!D:D=D69),1)}, {FILTER('Entradas y salidas'!F:F, 'Entrada"&"s y salidas'!D:D=D69, NOT(ISBLANK('Entradas y salidas'!J:J))); INDEX(FILTER('Cortes x inversión'!J:J, 'Cortes x inversión'!D:D=D69),1)}), """"))"),"") | K69: =IF(E69="USD", SUMIF('Entradas y salidas'!D:D, D69, 'Entradas y salidas'!I:I), ) | L69: =IFERROR(__xludf.DUMMYFUNCTION("IF(E69=""USD"", INDEX(FILTER('Cortes x inversión'!G:G, 'Cortes x inversión'!D:D=D69),1), )"),"") | M69: =IF(OR(K69="", L69=""),"", L69 - ABS(K69)) | N69: =IFERROR(__xludf.DUMMYFUNCTION("IF(ISBLANK(D69),"""",IFERROR(XIRR({FILTER('Entradas y salidas'!I:I, 'Entradas y salidas'!D:D=D69, NOT(ISBLANK('Entradas y salidas'!I:I))); INDEX(FILTER('Cortes x inversión'!G:G, 'Cortes x inversión'!D:D=D69),1)}, {FILTER('Entradas y salidas'!F:F, 'Entrada"&"s y salidas'!D:D=D69, NOT(ISBLANK('Entradas y salidas'!I:I))); INDEX(FILTER('Cortes x inversión'!J:J, 'Cortes x inversión'!D:D=D69),1)}), """"))"),"") | P69: =IFERROR(__xludf.DUMMYFUNCTION("IF(K69="""","""", GOOGLEFINANCE(""CURRENCY:USDCOP"")) "),"") | Q69: =IFERROR(__xludf.DUMMYFUNCTION("IF(L69="""","""", GOOGLEFINANCE(""CURRENCY:USDCOP"")) "),"") | R69: =IF(K69="","", L69*P69) | S69: =IF(OR(Q69="", R69=""),"", R69 - ABS(Q69)) | T69: =IFERROR(__xludf.DUMMYFUNCTION("IF(ISBLANK(D69),"""",IFERROR(XIRR({FILTER('Entradas y salidas'!K:K, 'Entradas y salidas'!D:D=D69, NOT(ISBLANK('Entradas y salidas'!K:K))); INDEX(FILTER('Cortes x inversión'!I:I, 'Cortes x inversión'!D:D=D69),1)}, {FILTER('Entradas y salidas'!F:F, 'Entrada"&"s y salidas'!D:D=D69, NOT(ISBLANK('Entradas y salidas'!K:K))); INDEX(FILTER('Cortes x inversión'!J:J, 'Cortes x inversión'!D:D=D69),1)}), """"))"),"")
F70: =IF(E70="COP", SUMIF('Entradas y salidas'!D:D, D70, 'Entradas y salidas'!J:J), ) | G70: =IFERROR(__xludf.DUMMYFUNCTION("IF(E70=""COP"", INDEX(FILTER('Cortes x inversión'!F:F, 'Cortes x inversión'!D:D=D70),1), )"),"") | H70: =IF(OR(F70="", G70=""),"", G70 - ABS(F70)) | I70: =IFERROR(__xludf.DUMMYFUNCTION("IF(ISBLANK(D70),"""",IFERROR(XIRR({FILTER('Entradas y salidas'!J:J, 'Entradas y salidas'!D:D=D70, NOT(ISBLANK('Entradas y salidas'!J:J))); INDEX(FILTER('Cortes x inversión'!F:F, 'Cortes x inversión'!D:D=D70),1)}, {FILTER('Entradas y salidas'!F:F, 'Entrada"&"s y salidas'!D:D=D70, NOT(ISBLANK('Entradas y salidas'!J:J))); INDEX(FILTER('Cortes x inversión'!J:J, 'Cortes x inversión'!D:D=D70),1)}), """"))"),"") | K70: =IF(E70="USD", SUMIF('Entradas y salidas'!D:D, D70, 'Entradas y salidas'!I:I), ) | L70: =IFERROR(__xludf.DUMMYFUNCTION("IF(E70=""USD"", INDEX(FILTER('Cortes x inversión'!G:G, 'Cortes x inversión'!D:D=D70),1), )"),"") | M70: =IF(OR(K70="", L70=""),"", L70 - ABS(K70)) | N70: =IFERROR(__xludf.DUMMYFUNCTION("IF(ISBLANK(D70),"""",IFERROR(XIRR({FILTER('Entradas y salidas'!I:I, 'Entradas y salidas'!D:D=D70, NOT(ISBLANK('Entradas y salidas'!I:I))); INDEX(FILTER('Cortes x inversión'!G:G, 'Cortes x inversión'!D:D=D70),1)}, {FILTER('Entradas y salidas'!F:F, 'Entrada"&"s y salidas'!D:D=D70, NOT(ISBLANK('Entradas y salidas'!I:I))); INDEX(FILTER('Cortes x inversión'!J:J, 'Cortes x inversión'!D:D=D70),1)}), """"))"),"") | P70: =IFERROR(__xludf.DUMMYFUNCTION("IF(K70="""","""", GOOGLEFINANCE(""CURRENCY:USDCOP"")) "),"") | Q70: =IFERROR(__xludf.DUMMYFUNCTION("IF(L70="""","""", GOOGLEFINANCE(""CURRENCY:USDCOP"")) "),"") | R70: =IF(K70="","", L70*P70) | S70: =IF(OR(Q70="", R70=""),"", R70 - ABS(Q70)) | T70: =IFERROR(__xludf.DUMMYFUNCTION("IF(ISBLANK(D70),"""",IFERROR(XIRR({FILTER('Entradas y salidas'!K:K, 'Entradas y salidas'!D:D=D70, NOT(ISBLANK('Entradas y salidas'!K:K))); INDEX(FILTER('Cortes x inversión'!I:I, 'Cortes x inversión'!D:D=D70),1)}, {FILTER('Entradas y salidas'!F:F, 'Entrada"&"s y salidas'!D:D=D70, NOT(ISBLANK('Entradas y salidas'!K:K))); INDEX(FILTER('Cortes x inversión'!J:J, 'Cortes x inversión'!D:D=D70),1)}), """"))"),"")
F71: =IF(E71="COP", SUMIF('Entradas y salidas'!D:D, D71, 'Entradas y salidas'!J:J), ) | G71: =IFERROR(__xludf.DUMMYFUNCTION("IF(E71=""COP"", INDEX(FILTER('Cortes x inversión'!F:F, 'Cortes x inversión'!D:D=D71),1), )"),"") | H71: =IF(OR(F71="", G71=""),"", G71 - ABS(F71)) | I71: =IFERROR(__xludf.DUMMYFUNCTION("IF(ISBLANK(D71),"""",IFERROR(XIRR({FILTER('Entradas y salidas'!J:J, 'Entradas y salidas'!D:D=D71, NOT(ISBLANK('Entradas y salidas'!J:J))); INDEX(FILTER('Cortes x inversión'!F:F, 'Cortes x inversión'!D:D=D71),1)}, {FILTER('Entradas y salidas'!F:F, 'Entrada"&"s y salidas'!D:D=D71, NOT(ISBLANK('Entradas y salidas'!J:J))); INDEX(FILTER('Cortes x inversión'!J:J, 'Cortes x inversión'!D:D=D71),1)}), """"))"),"") | K71: =IF(E71="USD", SUMIF('Entradas y salidas'!D:D, D71, 'Entradas y salidas'!I:I), ) | L71: =IFERROR(__xludf.DUMMYFUNCTION("IF(E71=""USD"", INDEX(FILTER('Cortes x inversión'!G:G, 'Cortes x inversión'!D:D=D71),1), )"),"") | M71: =IF(OR(K71="", L71=""),"", L71 - ABS(K71)) | N71: =IFERROR(__xludf.DUMMYFUNCTION("IF(ISBLANK(D71),"""",IFERROR(XIRR({FILTER('Entradas y salidas'!I:I, 'Entradas y salidas'!D:D=D71, NOT(ISBLANK('Entradas y salidas'!I:I))); INDEX(FILTER('Cortes x inversión'!G:G, 'Cortes x inversión'!D:D=D71),1)}, {FILTER('Entradas y salidas'!F:F, 'Entrada"&"s y salidas'!D:D=D71, NOT(ISBLANK('Entradas y salidas'!I:I))); INDEX(FILTER('Cortes x inversión'!J:J, 'Cortes x inversión'!D:D=D71),1)}), """"))"),"") | P71: =IFERROR(__xludf.DUMMYFUNCTION("IF(K71="""","""", GOOGLEFINANCE(""CURRENCY:USDCOP"")) "),"") | Q71: =IFERROR(__xludf.DUMMYFUNCTION("IF(L71="""","""", GOOGLEFINANCE(""CURRENCY:USDCOP"")) "),"") | R71: =IF(K71="","", L71*P71) | S71: =IF(OR(Q71="", R71=""),"", R71 - ABS(Q71)) | T71: =IFERROR(__xludf.DUMMYFUNCTION("IF(ISBLANK(D71),"""",IFERROR(XIRR({FILTER('Entradas y salidas'!K:K, 'Entradas y salidas'!D:D=D71, NOT(ISBLANK('Entradas y salidas'!K:K))); INDEX(FILTER('Cortes x inversión'!I:I, 'Cortes x inversión'!D:D=D71),1)}, {FILTER('Entradas y salidas'!F:F, 'Entrada"&"s y salidas'!D:D=D71, NOT(ISBLANK('Entradas y salidas'!K:K))); INDEX(FILTER('Cortes x inversión'!J:J, 'Cortes x inversión'!D:D=D71),1)}), """"))"),"")
F72: =IF(E72="COP", SUMIF('Entradas y salidas'!D:D, D72, 'Entradas y salidas'!J:J), ) | G72: =IFERROR(__xludf.DUMMYFUNCTION("IF(E72=""COP"", INDEX(FILTER('Cortes x inversión'!F:F, 'Cortes x inversión'!D:D=D72),1), )"),"") | H72: =IF(OR(F72="", G72=""),"", G72 - ABS(F72)) | I72: =IFERROR(__xludf.DUMMYFUNCTION("IF(ISBLANK(D72),"""",IFERROR(XIRR({FILTER('Entradas y salidas'!J:J, 'Entradas y salidas'!D:D=D72, NOT(ISBLANK('Entradas y salidas'!J:J))); INDEX(FILTER('Cortes x inversión'!F:F, 'Cortes x inversión'!D:D=D72),1)}, {FILTER('Entradas y salidas'!F:F, 'Entrada"&"s y salidas'!D:D=D72, NOT(ISBLANK('Entradas y salidas'!J:J))); INDEX(FILTER('Cortes x inversión'!J:J, 'Cortes x inversión'!D:D=D72),1)}), """"))"),"") | K72: =IF(E72="USD", SUMIF('Entradas y salidas'!D:D, D72, 'Entradas y salidas'!I:I), ) | L72: =IFERROR(__xludf.DUMMYFUNCTION("IF(E72=""USD"", INDEX(FILTER('Cortes x inversión'!G:G, 'Cortes x inversión'!D:D=D72),1), )"),"") | M72: =IF(OR(K72="", L72=""),"", L72 - ABS(K72)) | N72: =IFERROR(__xludf.DUMMYFUNCTION("IF(ISBLANK(D72),"""",IFERROR(XIRR({FILTER('Entradas y salidas'!I:I, 'Entradas y salidas'!D:D=D72, NOT(ISBLANK('Entradas y salidas'!I:I))); INDEX(FILTER('Cortes x inversión'!G:G, 'Cortes x inversión'!D:D=D72),1)}, {FILTER('Entradas y salidas'!F:F, 'Entrada"&"s y salidas'!D:D=D72, NOT(ISBLANK('Entradas y salidas'!I:I))); INDEX(FILTER('Cortes x inversión'!J:J, 'Cortes x inversión'!D:D=D72),1)}), """"))"),"") | P72: =IFERROR(__xludf.DUMMYFUNCTION("IF(K72="""","""", GOOGLEFINANCE(""CURRENCY:USDCOP"")) "),"") | Q72: =IFERROR(__xludf.DUMMYFUNCTION("IF(L72="""","""", GOOGLEFINANCE(""CURRENCY:USDCOP"")) "),"") | R72: =IF(K72="","", L72*P72) | S72: =IF(OR(Q72="", R72=""),"", R72 - ABS(Q72)) | T72: =IFERROR(__xludf.DUMMYFUNCTION("IF(ISBLANK(D72),"""",IFERROR(XIRR({FILTER('Entradas y salidas'!K:K, 'Entradas y salidas'!D:D=D72, NOT(ISBLANK('Entradas y salidas'!K:K))); INDEX(FILTER('Cortes x inversión'!I:I, 'Cortes x inversión'!D:D=D72),1)}, {FILTER('Entradas y salidas'!F:F, 'Entrada"&"s y salidas'!D:D=D72, NOT(ISBLANK('Entradas y salidas'!K:K))); INDEX(FILTER('Cortes x inversión'!J:J, 'Cortes x inversión'!D:D=D72),1)}), """"))"),"")
F73: =IF(E73="COP", SUMIF('Entradas y salidas'!D:D, D73, 'Entradas y salidas'!J:J), ) | G73: =IFERROR(__xludf.DUMMYFUNCTION("IF(E73=""COP"", INDEX(FILTER('Cortes x inversión'!F:F, 'Cortes x inversión'!D:D=D73),1), )"),"") | H73: =IF(OR(F73="", G73=""),"", G73 - ABS(F73)) | I73: =IFERROR(__xludf.DUMMYFUNCTION("IF(ISBLANK(D73),"""",IFERROR(XIRR({FILTER('Entradas y salidas'!J:J, 'Entradas y salidas'!D:D=D73, NOT(ISBLANK('Entradas y salidas'!J:J))); INDEX(FILTER('Cortes x inversión'!F:F, 'Cortes x inversión'!D:D=D73),1)}, {FILTER('Entradas y salidas'!F:F, 'Entrada"&"s y salidas'!D:D=D73, NOT(ISBLANK('Entradas y salidas'!J:J))); INDEX(FILTER('Cortes x inversión'!J:J, 'Cortes x inversión'!D:D=D73),1)}), """"))"),"") | K73: =IF(E73="USD", SUMIF('Entradas y salidas'!D:D, D73, 'Entradas y salidas'!I:I), ) | L73: =IFERROR(__xludf.DUMMYFUNCTION("IF(E73=""USD"", INDEX(FILTER('Cortes x inversión'!G:G, 'Cortes x inversión'!D:D=D73),1), )"),"") | M73: =IF(OR(K73="", L73=""),"", L73 - ABS(K73)) | N73: =IFERROR(__xludf.DUMMYFUNCTION("IF(ISBLANK(D73),"""",IFERROR(XIRR({FILTER('Entradas y salidas'!I:I, 'Entradas y salidas'!D:D=D73, NOT(ISBLANK('Entradas y salidas'!I:I))); INDEX(FILTER('Cortes x inversión'!G:G, 'Cortes x inversión'!D:D=D73),1)}, {FILTER('Entradas y salidas'!F:F, 'Entrada"&"s y salidas'!D:D=D73, NOT(ISBLANK('Entradas y salidas'!I:I))); INDEX(FILTER('Cortes x inversión'!J:J, 'Cortes x inversión'!D:D=D73),1)}), """"))"),"") | P73: =IFERROR(__xludf.DUMMYFUNCTION("IF(K73="""","""", GOOGLEFINANCE(""CURRENCY:USDCOP"")) "),"") | Q73: =IFERROR(__xludf.DUMMYFUNCTION("IF(L73="""","""", GOOGLEFINANCE(""CURRENCY:USDCOP"")) "),"") | R73: =IF(K73="","", L73*P73) | S73: =IF(OR(Q73="", R73=""),"", R73 - ABS(Q73)) | T73: =IFERROR(__xludf.DUMMYFUNCTION("IF(ISBLANK(D73),"""",IFERROR(XIRR({FILTER('Entradas y salidas'!K:K, 'Entradas y salidas'!D:D=D73, NOT(ISBLANK('Entradas y salidas'!K:K))); INDEX(FILTER('Cortes x inversión'!I:I, 'Cortes x inversión'!D:D=D73),1)}, {FILTER('Entradas y salidas'!F:F, 'Entrada"&"s y salidas'!D:D=D73, NOT(ISBLANK('Entradas y salidas'!K:K))); INDEX(FILTER('Cortes x inversión'!J:J, 'Cortes x inversión'!D:D=D73),1)}), """"))"),"")
F74: =IF(E74="COP", SUMIF('Entradas y salidas'!D:D, D74, 'Entradas y salidas'!J:J), ) | G74: =IFERROR(__xludf.DUMMYFUNCTION("IF(E74=""COP"", INDEX(FILTER('Cortes x inversión'!F:F, 'Cortes x inversión'!D:D=D74),1), )"),"") | H74: =IF(OR(F74="", G74=""),"", G74 - ABS(F74)) | I74: =IFERROR(__xludf.DUMMYFUNCTION("IF(ISBLANK(D74),"""",IFERROR(XIRR({FILTER('Entradas y salidas'!J:J, 'Entradas y salidas'!D:D=D74, NOT(ISBLANK('Entradas y salidas'!J:J))); INDEX(FILTER('Cortes x inversión'!F:F, 'Cortes x inversión'!D:D=D74),1)}, {FILTER('Entradas y salidas'!F:F, 'Entrada"&"s y salidas'!D:D=D74, NOT(ISBLANK('Entradas y salidas'!J:J))); INDEX(FILTER('Cortes x inversión'!J:J, 'Cortes x inversión'!D:D=D74),1)}), """"))"),"") | K74: =IF(E74="USD", SUMIF('Entradas y salidas'!D:D, D74, 'Entradas y salidas'!I:I), ) | L74: =IFERROR(__xludf.DUMMYFUNCTION("IF(E74=""USD"", INDEX(FILTER('Cortes x inversión'!G:G, 'Cortes x inversión'!D:D=D74),1), )"),"") | M74: =IF(OR(K74="", L74=""),"", L74 - ABS(K74)) | N74: =IFERROR(__xludf.DUMMYFUNCTION("IF(ISBLANK(D74),"""",IFERROR(XIRR({FILTER('Entradas y salidas'!I:I, 'Entradas y salidas'!D:D=D74, NOT(ISBLANK('Entradas y salidas'!I:I))); INDEX(FILTER('Cortes x inversión'!G:G, 'Cortes x inversión'!D:D=D74),1)}, {FILTER('Entradas y salidas'!F:F, 'Entrada"&"s y salidas'!D:D=D74, NOT(ISBLANK('Entradas y salidas'!I:I))); INDEX(FILTER('Cortes x inversión'!J:J, 'Cortes x inversión'!D:D=D74),1)}), """"))"),"") | P74: =IFERROR(__xludf.DUMMYFUNCTION("IF(K74="""","""", GOOGLEFINANCE(""CURRENCY:USDCOP"")) "),"") | Q74: =IFERROR(__xludf.DUMMYFUNCTION("IF(L74="""","""", GOOGLEFINANCE(""CURRENCY:USDCOP"")) "),"") | R74: =IF(K74="","", L74*P74) | S74: =IF(OR(Q74="", R74=""),"", R74 - ABS(Q74)) | T74: =IFERROR(__xludf.DUMMYFUNCTION("IF(ISBLANK(D74),"""",IFERROR(XIRR({FILTER('Entradas y salidas'!K:K, 'Entradas y salidas'!D:D=D74, NOT(ISBLANK('Entradas y salidas'!K:K))); INDEX(FILTER('Cortes x inversión'!I:I, 'Cortes x inversión'!D:D=D74),1)}, {FILTER('Entradas y salidas'!F:F, 'Entrada"&"s y salidas'!D:D=D74, NOT(ISBLANK('Entradas y salidas'!K:K))); INDEX(FILTER('Cortes x inversión'!J:J, 'Cortes x inversión'!D:D=D74),1)}), """"))"),"")
F75: =IF(E75="COP", SUMIF('Entradas y salidas'!D:D, D75, 'Entradas y salidas'!J:J), ) | G75: =IFERROR(__xludf.DUMMYFUNCTION("IF(E75=""COP"", INDEX(FILTER('Cortes x inversión'!F:F, 'Cortes x inversión'!D:D=D75),1), )"),"") | H75: =IF(OR(F75="", G75=""),"", G75 - ABS(F75)) | I75: =IFERROR(__xludf.DUMMYFUNCTION("IF(ISBLANK(D75),"""",IFERROR(XIRR({FILTER('Entradas y salidas'!J:J, 'Entradas y salidas'!D:D=D75, NOT(ISBLANK('Entradas y salidas'!J:J))); INDEX(FILTER('Cortes x inversión'!F:F, 'Cortes x inversión'!D:D=D75),1)}, {FILTER('Entradas y salidas'!F:F, 'Entrada"&"s y salidas'!D:D=D75, NOT(ISBLANK('Entradas y salidas'!J:J))); INDEX(FILTER('Cortes x inversión'!J:J, 'Cortes x inversión'!D:D=D75),1)}), """"))"),"") | K75: =IF(E75="USD", SUMIF('Entradas y salidas'!D:D, D75, 'Entradas y salidas'!I:I), ) | L75: =IFERROR(__xludf.DUMMYFUNCTION("IF(E75=""USD"", INDEX(FILTER('Cortes x inversión'!G:G, 'Cortes x inversión'!D:D=D75),1), )"),"") | M75: =IF(OR(K75="", L75=""),"", L75 - ABS(K75)) | N75: =IFERROR(__xludf.DUMMYFUNCTION("IF(ISBLANK(D75),"""",IFERROR(XIRR({FILTER('Entradas y salidas'!I:I, 'Entradas y salidas'!D:D=D75, NOT(ISBLANK('Entradas y salidas'!I:I))); INDEX(FILTER('Cortes x inversión'!G:G, 'Cortes x inversión'!D:D=D75),1)}, {FILTER('Entradas y salidas'!F:F, 'Entrada"&"s y salidas'!D:D=D75, NOT(ISBLANK('Entradas y salidas'!I:I))); INDEX(FILTER('Cortes x inversión'!J:J, 'Cortes x inversión'!D:D=D75),1)}), """"))"),"") | P75: =IFERROR(__xludf.DUMMYFUNCTION("IF(K75="""","""", GOOGLEFINANCE(""CURRENCY:USDCOP"")) "),"") | Q75: =IFERROR(__xludf.DUMMYFUNCTION("IF(L75="""","""", GOOGLEFINANCE(""CURRENCY:USDCOP"")) "),"") | R75: =IF(K75="","", L75*P75) | S75: =IF(OR(Q75="", R75=""),"", R75 - ABS(Q75)) | T75: =IFERROR(__xludf.DUMMYFUNCTION("IF(ISBLANK(D75),"""",IFERROR(XIRR({FILTER('Entradas y salidas'!K:K, 'Entradas y salidas'!D:D=D75, NOT(ISBLANK('Entradas y salidas'!K:K))); INDEX(FILTER('Cortes x inversión'!I:I, 'Cortes x inversión'!D:D=D75),1)}, {FILTER('Entradas y salidas'!F:F, 'Entrada"&"s y salidas'!D:D=D75, NOT(ISBLANK('Entradas y salidas'!K:K))); INDEX(FILTER('Cortes x inversión'!J:J, 'Cortes x inversión'!D:D=D75),1)}), """"))"),"")
F76: =IF(E76="COP", SUMIF('Entradas y salidas'!D:D, D76, 'Entradas y salidas'!J:J), ) | G76: =IFERROR(__xludf.DUMMYFUNCTION("IF(E76=""COP"", INDEX(FILTER('Cortes x inversión'!F:F, 'Cortes x inversión'!D:D=D76),1), )"),"") | H76: =IF(OR(F76="", G76=""),"", G76 - ABS(F76)) | I76: =IFERROR(__xludf.DUMMYFUNCTION("IF(ISBLANK(D76),"""",IFERROR(XIRR({FILTER('Entradas y salidas'!J:J, 'Entradas y salidas'!D:D=D76, NOT(ISBLANK('Entradas y salidas'!J:J))); INDEX(FILTER('Cortes x inversión'!F:F, 'Cortes x inversión'!D:D=D76),1)}, {FILTER('Entradas y salidas'!F:F, 'Entrada"&"s y salidas'!D:D=D76, NOT(ISBLANK('Entradas y salidas'!J:J))); INDEX(FILTER('Cortes x inversión'!J:J, 'Cortes x inversión'!D:D=D76),1)}), """"))"),"") | K76: =IF(E76="USD", SUMIF('Entradas y salidas'!D:D, D76, 'Entradas y salidas'!I:I), ) | L76: =IFERROR(__xludf.DUMMYFUNCTION("IF(E76=""USD"", INDEX(FILTER('Cortes x inversión'!G:G, 'Cortes x inversión'!D:D=D76),1), )"),"") | M76: =IF(OR(K76="", L76=""),"", L76 - ABS(K76)) | N76: =IFERROR(__xludf.DUMMYFUNCTION("IF(ISBLANK(D76),"""",IFERROR(XIRR({FILTER('Entradas y salidas'!I:I, 'Entradas y salidas'!D:D=D76, NOT(ISBLANK('Entradas y salidas'!I:I))); INDEX(FILTER('Cortes x inversión'!G:G, 'Cortes x inversión'!D:D=D76),1)}, {FILTER('Entradas y salidas'!F:F, 'Entrada"&"s y salidas'!D:D=D76, NOT(ISBLANK('Entradas y salidas'!I:I))); INDEX(FILTER('Cortes x inversión'!J:J, 'Cortes x inversión'!D:D=D76),1)}), """"))"),"") | P76: =IFERROR(__xludf.DUMMYFUNCTION("IF(K76="""","""", GOOGLEFINANCE(""CURRENCY:USDCOP"")) "),"") | Q76: =IFERROR(__xludf.DUMMYFUNCTION("IF(L76="""","""", GOOGLEFINANCE(""CURRENCY:USDCOP"")) "),"") | R76: =IF(K76="","", L76*P76) | S76: =IF(OR(Q76="", R76=""),"", R76 - ABS(Q76)) | T76: =IFERROR(__xludf.DUMMYFUNCTION("IF(ISBLANK(D76),"""",IFERROR(XIRR({FILTER('Entradas y salidas'!K:K, 'Entradas y salidas'!D:D=D76, NOT(ISBLANK('Entradas y salidas'!K:K))); INDEX(FILTER('Cortes x inversión'!I:I, 'Cortes x inversión'!D:D=D76),1)}, {FILTER('Entradas y salidas'!F:F, 'Entrada"&"s y salidas'!D:D=D76, NOT(ISBLANK('Entradas y salidas'!K:K))); INDEX(FILTER('Cortes x inversión'!J:J, 'Cortes x inversión'!D:D=D76),1)}), """"))"),"")
F77: =IF(E77="COP", SUMIF('Entradas y salidas'!D:D, D77, 'Entradas y salidas'!J:J), ) | G77: =IFERROR(__xludf.DUMMYFUNCTION("IF(E77=""COP"", INDEX(FILTER('Cortes x inversión'!F:F, 'Cortes x inversión'!D:D=D77),1), )"),"") | H77: =IF(OR(F77="", G77=""),"", G77 - ABS(F77)) | I77: =IFERROR(__xludf.DUMMYFUNCTION("IF(ISBLANK(D77),"""",IFERROR(XIRR({FILTER('Entradas y salidas'!J:J, 'Entradas y salidas'!D:D=D77, NOT(ISBLANK('Entradas y salidas'!J:J))); INDEX(FILTER('Cortes x inversión'!F:F, 'Cortes x inversión'!D:D=D77),1)}, {FILTER('Entradas y salidas'!F:F, 'Entrada"&"s y salidas'!D:D=D77, NOT(ISBLANK('Entradas y salidas'!J:J))); INDEX(FILTER('Cortes x inversión'!J:J, 'Cortes x inversión'!D:D=D77),1)}), """"))"),"") | K77: =IF(E77="USD", SUMIF('Entradas y salidas'!D:D, D77, 'Entradas y salidas'!I:I), ) | L77: =IFERROR(__xludf.DUMMYFUNCTION("IF(E77=""USD"", INDEX(FILTER('Cortes x inversión'!G:G, 'Cortes x inversión'!D:D=D77),1), )"),"") | M77: =IF(OR(K77="", L77=""),"", L77 - ABS(K77)) | N77: =IFERROR(__xludf.DUMMYFUNCTION("IF(ISBLANK(D77),"""",IFERROR(XIRR({FILTER('Entradas y salidas'!I:I, 'Entradas y salidas'!D:D=D77, NOT(ISBLANK('Entradas y salidas'!I:I))); INDEX(FILTER('Cortes x inversión'!G:G, 'Cortes x inversión'!D:D=D77),1)}, {FILTER('Entradas y salidas'!F:F, 'Entrada"&"s y salidas'!D:D=D77, NOT(ISBLANK('Entradas y salidas'!I:I))); INDEX(FILTER('Cortes x inversión'!J:J, 'Cortes x inversión'!D:D=D77),1)}), """"))"),"") | P77: =IFERROR(__xludf.DUMMYFUNCTION("IF(K77="""","""", GOOGLEFINANCE(""CURRENCY:USDCOP"")) "),"") | Q77: =IFERROR(__xludf.DUMMYFUNCTION("IF(L77="""","""", GOOGLEFINANCE(""CURRENCY:USDCOP"")) "),"") | R77: =IF(K77="","", L77*P77) | S77: =IF(OR(Q77="", R77=""),"", R77 - ABS(Q77)) | T77: =IFERROR(__xludf.DUMMYFUNCTION("IF(ISBLANK(D77),"""",IFERROR(XIRR({FILTER('Entradas y salidas'!K:K, 'Entradas y salidas'!D:D=D77, NOT(ISBLANK('Entradas y salidas'!K:K))); INDEX(FILTER('Cortes x inversión'!I:I, 'Cortes x inversión'!D:D=D77),1)}, {FILTER('Entradas y salidas'!F:F, 'Entrada"&"s y salidas'!D:D=D77, NOT(ISBLANK('Entradas y salidas'!K:K))); INDEX(FILTER('Cortes x inversión'!J:J, 'Cortes x inversión'!D:D=D77),1)}), """"))"),"")
F78: =IF(E78="COP", SUMIF('Entradas y salidas'!D:D, D78, 'Entradas y salidas'!J:J), ) | G78: =IFERROR(__xludf.DUMMYFUNCTION("IF(E78=""COP"", INDEX(FILTER('Cortes x inversión'!F:F, 'Cortes x inversión'!D:D=D78),1), )"),"") | H78: =IF(OR(F78="", G78=""),"", G78 - ABS(F78)) | I78: =IFERROR(__xludf.DUMMYFUNCTION("IF(ISBLANK(D78),"""",IFERROR(XIRR({FILTER('Entradas y salidas'!J:J, 'Entradas y salidas'!D:D=D78, NOT(ISBLANK('Entradas y salidas'!J:J))); INDEX(FILTER('Cortes x inversión'!F:F, 'Cortes x inversión'!D:D=D78),1)}, {FILTER('Entradas y salidas'!F:F, 'Entrada"&"s y salidas'!D:D=D78, NOT(ISBLANK('Entradas y salidas'!J:J))); INDEX(FILTER('Cortes x inversión'!J:J, 'Cortes x inversión'!D:D=D78),1)}), """"))"),"") | K78: =IF(E78="USD", SUMIF('Entradas y salidas'!D:D, D78, 'Entradas y salidas'!I:I), ) | L78: =IFERROR(__xludf.DUMMYFUNCTION("IF(E78=""USD"", INDEX(FILTER('Cortes x inversión'!G:G, 'Cortes x inversión'!D:D=D78),1), )"),"") | M78: =IF(OR(K78="", L78=""),"", L78 - ABS(K78)) | N78: =IFERROR(__xludf.DUMMYFUNCTION("IF(ISBLANK(D78),"""",IFERROR(XIRR({FILTER('Entradas y salidas'!I:I, 'Entradas y salidas'!D:D=D78, NOT(ISBLANK('Entradas y salidas'!I:I))); INDEX(FILTER('Cortes x inversión'!G:G, 'Cortes x inversión'!D:D=D78),1)}, {FILTER('Entradas y salidas'!F:F, 'Entrada"&"s y salidas'!D:D=D78, NOT(ISBLANK('Entradas y salidas'!I:I))); INDEX(FILTER('Cortes x inversión'!J:J, 'Cortes x inversión'!D:D=D78),1)}), """"))"),"") | P78: =IFERROR(__xludf.DUMMYFUNCTION("IF(K78="""","""", GOOGLEFINANCE(""CURRENCY:USDCOP"")) "),"") | Q78: =IFERROR(__xludf.DUMMYFUNCTION("IF(L78="""","""", GOOGLEFINANCE(""CURRENCY:USDCOP"")) "),"") | R78: =IF(K78="","", L78*P78) | S78: =IF(OR(Q78="", R78=""),"", R78 - ABS(Q78)) | T78: =IFERROR(__xludf.DUMMYFUNCTION("IF(ISBLANK(D78),"""",IFERROR(XIRR({FILTER('Entradas y salidas'!K:K, 'Entradas y salidas'!D:D=D78, NOT(ISBLANK('Entradas y salidas'!K:K))); INDEX(FILTER('Cortes x inversión'!I:I, 'Cortes x inversión'!D:D=D78),1)}, {FILTER('Entradas y salidas'!F:F, 'Entrada"&"s y salidas'!D:D=D78, NOT(ISBLANK('Entradas y salidas'!K:K))); INDEX(FILTER('Cortes x inversión'!J:J, 'Cortes x inversión'!D:D=D78),1)}), """"))"),"")
F79: =IF(E79="COP", SUMIF('Entradas y salidas'!D:D, D79, 'Entradas y salidas'!J:J), ) | G79: =IFERROR(__xludf.DUMMYFUNCTION("IF(E79=""COP"", INDEX(FILTER('Cortes x inversión'!F:F, 'Cortes x inversión'!D:D=D79),1), )"),"") | H79: =IF(OR(F79="", G79=""),"", G79 - ABS(F79)) | I79: =IFERROR(__xludf.DUMMYFUNCTION("IF(ISBLANK(D79),"""",IFERROR(XIRR({FILTER('Entradas y salidas'!J:J, 'Entradas y salidas'!D:D=D79, NOT(ISBLANK('Entradas y salidas'!J:J))); INDEX(FILTER('Cortes x inversión'!F:F, 'Cortes x inversión'!D:D=D79),1)}, {FILTER('Entradas y salidas'!F:F, 'Entrada"&"s y salidas'!D:D=D79, NOT(ISBLANK('Entradas y salidas'!J:J))); INDEX(FILTER('Cortes x inversión'!J:J, 'Cortes x inversión'!D:D=D79),1)}), """"))"),"") | K79: =IF(E79="USD", SUMIF('Entradas y salidas'!D:D, D79, 'Entradas y salidas'!I:I), ) | L79: =IFERROR(__xludf.DUMMYFUNCTION("IF(E79=""USD"", INDEX(FILTER('Cortes x inversión'!G:G, 'Cortes x inversión'!D:D=D79),1), )"),"") | M79: =IF(OR(K79="", L79=""),"", L79 - ABS(K79)) | N79: =IFERROR(__xludf.DUMMYFUNCTION("IF(ISBLANK(D79),"""",IFERROR(XIRR({FILTER('Entradas y salidas'!I:I, 'Entradas y salidas'!D:D=D79, NOT(ISBLANK('Entradas y salidas'!I:I))); INDEX(FILTER('Cortes x inversión'!G:G, 'Cortes x inversión'!D:D=D79),1)}, {FILTER('Entradas y salidas'!F:F, 'Entrada"&"s y salidas'!D:D=D79, NOT(ISBLANK('Entradas y salidas'!I:I))); INDEX(FILTER('Cortes x inversión'!J:J, 'Cortes x inversión'!D:D=D79),1)}), """"))"),"") | P79: =IFERROR(__xludf.DUMMYFUNCTION("IF(K79="""","""", GOOGLEFINANCE(""CURRENCY:USDCOP"")) "),"") | Q79: =IFERROR(__xludf.DUMMYFUNCTION("IF(L79="""","""", GOOGLEFINANCE(""CURRENCY:USDCOP"")) "),"") | R79: =IF(K79="","", L79*P79) | S79: =IF(OR(Q79="", R79=""),"", R79 - ABS(Q79)) | T79: =IFERROR(__xludf.DUMMYFUNCTION("IF(ISBLANK(D79),"""",IFERROR(XIRR({FILTER('Entradas y salidas'!K:K, 'Entradas y salidas'!D:D=D79, NOT(ISBLANK('Entradas y salidas'!K:K))); INDEX(FILTER('Cortes x inversión'!I:I, 'Cortes x inversión'!D:D=D79),1)}, {FILTER('Entradas y salidas'!F:F, 'Entrada"&"s y salidas'!D:D=D79, NOT(ISBLANK('Entradas y salidas'!K:K))); INDEX(FILTER('Cortes x inversión'!J:J, 'Cortes x inversión'!D:D=D79),1)}), """"))"),"")
F80: =IF(E80="COP", SUMIF('Entradas y salidas'!D:D, D80, 'Entradas y salidas'!J:J), ) | G80: =IFERROR(__xludf.DUMMYFUNCTION("IF(E80=""COP"", INDEX(FILTER('Cortes x inversión'!F:F, 'Cortes x inversión'!D:D=D80),1), )"),"") | H80: =IF(OR(F80="", G80=""),"", G80 - ABS(F80)) | I80: =IFERROR(__xludf.DUMMYFUNCTION("IF(ISBLANK(D80),"""",IFERROR(XIRR({FILTER('Entradas y salidas'!J:J, 'Entradas y salidas'!D:D=D80, NOT(ISBLANK('Entradas y salidas'!J:J))); INDEX(FILTER('Cortes x inversión'!F:F, 'Cortes x inversión'!D:D=D80),1)}, {FILTER('Entradas y salidas'!F:F, 'Entrada"&"s y salidas'!D:D=D80, NOT(ISBLANK('Entradas y salidas'!J:J))); INDEX(FILTER('Cortes x inversión'!J:J, 'Cortes x inversión'!D:D=D80),1)}), """"))"),"") | K80: =IF(E80="USD", SUMIF('Entradas y salidas'!D:D, D80, 'Entradas y salidas'!I:I), ) | L80: =IFERROR(__xludf.DUMMYFUNCTION("IF(E80=""USD"", INDEX(FILTER('Cortes x inversión'!G:G, 'Cortes x inversión'!D:D=D80),1), )"),"") | M80: =IF(OR(K80="", L80=""),"", L80 - ABS(K80)) | N80: =IFERROR(__xludf.DUMMYFUNCTION("IF(ISBLANK(D80),"""",IFERROR(XIRR({FILTER('Entradas y salidas'!I:I, 'Entradas y salidas'!D:D=D80, NOT(ISBLANK('Entradas y salidas'!I:I))); INDEX(FILTER('Cortes x inversión'!G:G, 'Cortes x inversión'!D:D=D80),1)}, {FILTER('Entradas y salidas'!F:F, 'Entrada"&"s y salidas'!D:D=D80, NOT(ISBLANK('Entradas y salidas'!I:I))); INDEX(FILTER('Cortes x inversión'!J:J, 'Cortes x inversión'!D:D=D80),1)}), """"))"),"") | P80: =IFERROR(__xludf.DUMMYFUNCTION("IF(K80="""","""", GOOGLEFINANCE(""CURRENCY:USDCOP"")) "),"") | Q80: =IFERROR(__xludf.DUMMYFUNCTION("IF(L80="""","""", GOOGLEFINANCE(""CURRENCY:USDCOP"")) "),"") | R80: =IF(K80="","", L80*P80) | S80: =IF(OR(Q80="", R80=""),"", R80 - ABS(Q80)) | T80: =IFERROR(__xludf.DUMMYFUNCTION("IF(ISBLANK(D80),"""",IFERROR(XIRR({FILTER('Entradas y salidas'!K:K, 'Entradas y salidas'!D:D=D80, NOT(ISBLANK('Entradas y salidas'!K:K))); INDEX(FILTER('Cortes x inversión'!I:I, 'Cortes x inversión'!D:D=D80),1)}, {FILTER('Entradas y salidas'!F:F, 'Entrada"&"s y salidas'!D:D=D80, NOT(ISBLANK('Entradas y salidas'!K:K))); INDEX(FILTER('Cortes x inversión'!J:J, 'Cortes x inversión'!D:D=D80),1)}), """"))"),"")
F81: =IF(E81="COP", SUMIF('Entradas y salidas'!D:D, D81, 'Entradas y salidas'!J:J), ) | G81: =IFERROR(__xludf.DUMMYFUNCTION("IF(E81=""COP"", INDEX(FILTER('Cortes x inversión'!F:F, 'Cortes x inversión'!D:D=D81),1), )"),"") | H81: =IF(OR(F81="", G81=""),"", G81 - ABS(F81)) | I81: =IFERROR(__xludf.DUMMYFUNCTION("IF(ISBLANK(D81),"""",IFERROR(XIRR({FILTER('Entradas y salidas'!J:J, 'Entradas y salidas'!D:D=D81, NOT(ISBLANK('Entradas y salidas'!J:J))); INDEX(FILTER('Cortes x inversión'!F:F, 'Cortes x inversión'!D:D=D81),1)}, {FILTER('Entradas y salidas'!F:F, 'Entrada"&"s y salidas'!D:D=D81, NOT(ISBLANK('Entradas y salidas'!J:J))); INDEX(FILTER('Cortes x inversión'!J:J, 'Cortes x inversión'!D:D=D81),1)}), """"))"),"") | K81: =IF(E81="USD", SUMIF('Entradas y salidas'!D:D, D81, 'Entradas y salidas'!I:I), ) | L81: =IFERROR(__xludf.DUMMYFUNCTION("IF(E81=""USD"", INDEX(FILTER('Cortes x inversión'!G:G, 'Cortes x inversión'!D:D=D81),1), )"),"") | M81: =IF(OR(K81="", L81=""),"", L81 - ABS(K81)) | N81: =IFERROR(__xludf.DUMMYFUNCTION("IF(ISBLANK(D81),"""",IFERROR(XIRR({FILTER('Entradas y salidas'!I:I, 'Entradas y salidas'!D:D=D81, NOT(ISBLANK('Entradas y salidas'!I:I))); INDEX(FILTER('Cortes x inversión'!G:G, 'Cortes x inversión'!D:D=D81),1)}, {FILTER('Entradas y salidas'!F:F, 'Entrada"&"s y salidas'!D:D=D81, NOT(ISBLANK('Entradas y salidas'!I:I))); INDEX(FILTER('Cortes x inversión'!J:J, 'Cortes x inversión'!D:D=D81),1)}), """"))"),"") | P81: =IFERROR(__xludf.DUMMYFUNCTION("IF(K81="""","""", GOOGLEFINANCE(""CURRENCY:USDCOP"")) "),"") | Q81: =IFERROR(__xludf.DUMMYFUNCTION("IF(L81="""","""", GOOGLEFINANCE(""CURRENCY:USDCOP"")) "),"") | R81: =IF(K81="","", L81*P81) | S81: =IF(OR(Q81="", R81=""),"", R81 - ABS(Q81)) | T81: =IFERROR(__xludf.DUMMYFUNCTION("IF(ISBLANK(D81),"""",IFERROR(XIRR({FILTER('Entradas y salidas'!K:K, 'Entradas y salidas'!D:D=D81, NOT(ISBLANK('Entradas y salidas'!K:K))); INDEX(FILTER('Cortes x inversión'!I:I, 'Cortes x inversión'!D:D=D81),1)}, {FILTER('Entradas y salidas'!F:F, 'Entrada"&"s y salidas'!D:D=D81, NOT(ISBLANK('Entradas y salidas'!K:K))); INDEX(FILTER('Cortes x inversión'!J:J, 'Cortes x inversión'!D:D=D81),1)}), """"))"),"")
F82: =IF(E82="COP", SUMIF('Entradas y salidas'!D:D, D82, 'Entradas y salidas'!J:J), ) | G82: =IFERROR(__xludf.DUMMYFUNCTION("IF(E82=""COP"", INDEX(FILTER('Cortes x inversión'!F:F, 'Cortes x inversión'!D:D=D82),1), )"),"") | H82: =IF(OR(F82="", G82=""),"", G82 - ABS(F82)) | I82: =IFERROR(__xludf.DUMMYFUNCTION("IF(ISBLANK(D82),"""",IFERROR(XIRR({FILTER('Entradas y salidas'!J:J, 'Entradas y salidas'!D:D=D82, NOT(ISBLANK('Entradas y salidas'!J:J))); INDEX(FILTER('Cortes x inversión'!F:F, 'Cortes x inversión'!D:D=D82),1)}, {FILTER('Entradas y salidas'!F:F, 'Entrada"&"s y salidas'!D:D=D82, NOT(ISBLANK('Entradas y salidas'!J:J))); INDEX(FILTER('Cortes x inversión'!J:J, 'Cortes x inversión'!D:D=D82),1)}), """"))"),"") | K82: =IF(E82="USD", SUMIF('Entradas y salidas'!D:D, D82, 'Entradas y salidas'!I:I), ) | L82: =IFERROR(__xludf.DUMMYFUNCTION("IF(E82=""USD"", INDEX(FILTER('Cortes x inversión'!G:G, 'Cortes x inversión'!D:D=D82),1), )"),"") | M82: =IF(OR(K82="", L82=""),"", L82 - ABS(K82)) | N82: =IFERROR(__xludf.DUMMYFUNCTION("IF(ISBLANK(D82),"""",IFERROR(XIRR({FILTER('Entradas y salidas'!I:I, 'Entradas y salidas'!D:D=D82, NOT(ISBLANK('Entradas y salidas'!I:I))); INDEX(FILTER('Cortes x inversión'!G:G, 'Cortes x inversión'!D:D=D82),1)}, {FILTER('Entradas y salidas'!F:F, 'Entrada"&"s y salidas'!D:D=D82, NOT(ISBLANK('Entradas y salidas'!I:I))); INDEX(FILTER('Cortes x inversión'!J:J, 'Cortes x inversión'!D:D=D82),1)}), """"))"),"") | P82: =IFERROR(__xludf.DUMMYFUNCTION("IF(K82="""","""", GOOGLEFINANCE(""CURRENCY:USDCOP"")) "),"") | Q82: =IFERROR(__xludf.DUMMYFUNCTION("IF(L82="""","""", GOOGLEFINANCE(""CURRENCY:USDCOP"")) "),"") | R82: =IF(K82="","", L82*P82) | S82: =IF(OR(Q82="", R82=""),"", R82 - ABS(Q82)) | T82: =IFERROR(__xludf.DUMMYFUNCTION("IF(ISBLANK(D82),"""",IFERROR(XIRR({FILTER('Entradas y salidas'!K:K, 'Entradas y salidas'!D:D=D82, NOT(ISBLANK('Entradas y salidas'!K:K))); INDEX(FILTER('Cortes x inversión'!I:I, 'Cortes x inversión'!D:D=D82),1)}, {FILTER('Entradas y salidas'!F:F, 'Entrada"&"s y salidas'!D:D=D82, NOT(ISBLANK('Entradas y salidas'!K:K))); INDEX(FILTER('Cortes x inversión'!J:J, 'Cortes x inversión'!D:D=D82),1)}), """"))"),"")
F83: =IF(E83="COP", SUMIF('Entradas y salidas'!D:D, D83, 'Entradas y salidas'!J:J), ) | G83: =IFERROR(__xludf.DUMMYFUNCTION("IF(E83=""COP"", INDEX(FILTER('Cortes x inversión'!F:F, 'Cortes x inversión'!D:D=D83),1), )"),"") | H83: =IF(OR(F83="", G83=""),"", G83 - ABS(F83)) | I83: =IFERROR(__xludf.DUMMYFUNCTION("IF(ISBLANK(D83),"""",IFERROR(XIRR({FILTER('Entradas y salidas'!J:J, 'Entradas y salidas'!D:D=D83, NOT(ISBLANK('Entradas y salidas'!J:J))); INDEX(FILTER('Cortes x inversión'!F:F, 'Cortes x inversión'!D:D=D83),1)}, {FILTER('Entradas y salidas'!F:F, 'Entrada"&"s y salidas'!D:D=D83, NOT(ISBLANK('Entradas y salidas'!J:J))); INDEX(FILTER('Cortes x inversión'!J:J, 'Cortes x inversión'!D:D=D83),1)}), """"))"),"") | K83: =IF(E83="USD", SUMIF('Entradas y salidas'!D:D, D83, 'Entradas y salidas'!I:I), ) | L83: =IFERROR(__xludf.DUMMYFUNCTION("IF(E83=""USD"", INDEX(FILTER('Cortes x inversión'!G:G, 'Cortes x inversión'!D:D=D83),1), )"),"") | M83: =IF(OR(K83="", L83=""),"", L83 - ABS(K83)) | N83: =IFERROR(__xludf.DUMMYFUNCTION("IF(ISBLANK(D83),"""",IFERROR(XIRR({FILTER('Entradas y salidas'!I:I, 'Entradas y salidas'!D:D=D83, NOT(ISBLANK('Entradas y salidas'!I:I))); INDEX(FILTER('Cortes x inversión'!G:G, 'Cortes x inversión'!D:D=D83),1)}, {FILTER('Entradas y salidas'!F:F, 'Entrada"&"s y salidas'!D:D=D83, NOT(ISBLANK('Entradas y salidas'!I:I))); INDEX(FILTER('Cortes x inversión'!J:J, 'Cortes x inversión'!D:D=D83),1)}), """"))"),"") | P83: =IFERROR(__xludf.DUMMYFUNCTION("IF(K83="""","""", GOOGLEFINANCE(""CURRENCY:USDCOP"")) "),"") | Q83: =IFERROR(__xludf.DUMMYFUNCTION("IF(L83="""","""", GOOGLEFINANCE(""CURRENCY:USDCOP"")) "),"") | R83: =IF(K83="","", L83*P83) | S83: =IF(OR(Q83="", R83=""),"", R83 - ABS(Q83)) | T83: =IFERROR(__xludf.DUMMYFUNCTION("IF(ISBLANK(D83),"""",IFERROR(XIRR({FILTER('Entradas y salidas'!K:K, 'Entradas y salidas'!D:D=D83, NOT(ISBLANK('Entradas y salidas'!K:K))); INDEX(FILTER('Cortes x inversión'!I:I, 'Cortes x inversión'!D:D=D83),1)}, {FILTER('Entradas y salidas'!F:F, 'Entrada"&"s y salidas'!D:D=D83, NOT(ISBLANK('Entradas y salidas'!K:K))); INDEX(FILTER('Cortes x inversión'!J:J, 'Cortes x inversión'!D:D=D83),1)}), """"))"),"")
F84: =IF(E84="COP", SUMIF('Entradas y salidas'!D:D, D84, 'Entradas y salidas'!J:J), ) | G84: =IFERROR(__xludf.DUMMYFUNCTION("IF(E84=""COP"", INDEX(FILTER('Cortes x inversión'!F:F, 'Cortes x inversión'!D:D=D84),1), )"),"") | H84: =IF(OR(F84="", G84=""),"", G84 - ABS(F84)) | I84: =IFERROR(__xludf.DUMMYFUNCTION("IF(ISBLANK(D84),"""",IFERROR(XIRR({FILTER('Entradas y salidas'!J:J, 'Entradas y salidas'!D:D=D84, NOT(ISBLANK('Entradas y salidas'!J:J))); INDEX(FILTER('Cortes x inversión'!F:F, 'Cortes x inversión'!D:D=D84),1)}, {FILTER('Entradas y salidas'!F:F, 'Entrada"&"s y salidas'!D:D=D84, NOT(ISBLANK('Entradas y salidas'!J:J))); INDEX(FILTER('Cortes x inversión'!J:J, 'Cortes x inversión'!D:D=D84),1)}), """"))"),"") | K84: =IF(E84="USD", SUMIF('Entradas y salidas'!D:D, D84, 'Entradas y salidas'!I:I), ) | L84: =IFERROR(__xludf.DUMMYFUNCTION("IF(E84=""USD"", INDEX(FILTER('Cortes x inversión'!G:G, 'Cortes x inversión'!D:D=D84),1), )"),"") | M84: =IF(OR(K84="", L84=""),"", L84 - ABS(K84)) | N84: =IFERROR(__xludf.DUMMYFUNCTION("IF(ISBLANK(D84),"""",IFERROR(XIRR({FILTER('Entradas y salidas'!I:I, 'Entradas y salidas'!D:D=D84, NOT(ISBLANK('Entradas y salidas'!I:I))); INDEX(FILTER('Cortes x inversión'!G:G, 'Cortes x inversión'!D:D=D84),1)}, {FILTER('Entradas y salidas'!F:F, 'Entrada"&"s y salidas'!D:D=D84, NOT(ISBLANK('Entradas y salidas'!I:I))); INDEX(FILTER('Cortes x inversión'!J:J, 'Cortes x inversión'!D:D=D84),1)}), """"))"),"") | P84: =IFERROR(__xludf.DUMMYFUNCTION("IF(K84="""","""", GOOGLEFINANCE(""CURRENCY:USDCOP"")) "),"") | Q84: =IFERROR(__xludf.DUMMYFUNCTION("IF(L84="""","""", GOOGLEFINANCE(""CURRENCY:USDCOP"")) "),"") | R84: =IF(K84="","", L84*P84) | S84: =IF(OR(Q84="", R84=""),"", R84 - ABS(Q84)) | T84: =IFERROR(__xludf.DUMMYFUNCTION("IF(ISBLANK(D84),"""",IFERROR(XIRR({FILTER('Entradas y salidas'!K:K, 'Entradas y salidas'!D:D=D84, NOT(ISBLANK('Entradas y salidas'!K:K))); INDEX(FILTER('Cortes x inversión'!I:I, 'Cortes x inversión'!D:D=D84),1)}, {FILTER('Entradas y salidas'!F:F, 'Entrada"&"s y salidas'!D:D=D84, NOT(ISBLANK('Entradas y salidas'!K:K))); INDEX(FILTER('Cortes x inversión'!J:J, 'Cortes x inversión'!D:D=D84),1)}), """"))"),"")
F85: =IF(E85="COP", SUMIF('Entradas y salidas'!D:D, D85, 'Entradas y salidas'!J:J), ) | G85: =IFERROR(__xludf.DUMMYFUNCTION("IF(E85=""COP"", INDEX(FILTER('Cortes x inversión'!F:F, 'Cortes x inversión'!D:D=D85),1), )"),"") | H85: =IF(OR(F85="", G85=""),"", G85 - ABS(F85)) | I85: =IFERROR(__xludf.DUMMYFUNCTION("IF(ISBLANK(D85),"""",IFERROR(XIRR({FILTER('Entradas y salidas'!J:J, 'Entradas y salidas'!D:D=D85, NOT(ISBLANK('Entradas y salidas'!J:J))); INDEX(FILTER('Cortes x inversión'!F:F, 'Cortes x inversión'!D:D=D85),1)}, {FILTER('Entradas y salidas'!F:F, 'Entrada"&"s y salidas'!D:D=D85, NOT(ISBLANK('Entradas y salidas'!J:J))); INDEX(FILTER('Cortes x inversión'!J:J, 'Cortes x inversión'!D:D=D85),1)}), """"))"),"") | K85: =IF(E85="USD", SUMIF('Entradas y salidas'!D:D, D85, 'Entradas y salidas'!I:I), ) | L85: =IFERROR(__xludf.DUMMYFUNCTION("IF(E85=""USD"", INDEX(FILTER('Cortes x inversión'!G:G, 'Cortes x inversión'!D:D=D85),1), )"),"") | M85: =IF(OR(K85="", L85=""),"", L85 - ABS(K85)) | N85: =IFERROR(__xludf.DUMMYFUNCTION("IF(ISBLANK(D85),"""",IFERROR(XIRR({FILTER('Entradas y salidas'!I:I, 'Entradas y salidas'!D:D=D85, NOT(ISBLANK('Entradas y salidas'!I:I))); INDEX(FILTER('Cortes x inversión'!G:G, 'Cortes x inversión'!D:D=D85),1)}, {FILTER('Entradas y salidas'!F:F, 'Entrada"&"s y salidas'!D:D=D85, NOT(ISBLANK('Entradas y salidas'!I:I))); INDEX(FILTER('Cortes x inversión'!J:J, 'Cortes x inversión'!D:D=D85),1)}), """"))"),"") | P85: =IFERROR(__xludf.DUMMYFUNCTION("IF(K85="""","""", GOOGLEFINANCE(""CURRENCY:USDCOP"")) "),"") | Q85: =IFERROR(__xludf.DUMMYFUNCTION("IF(L85="""","""", GOOGLEFINANCE(""CURRENCY:USDCOP"")) "),"") | R85: =IF(K85="","", L85*P85) | S85: =IF(OR(Q85="", R85=""),"", R85 - ABS(Q85)) | T85: =IFERROR(__xludf.DUMMYFUNCTION("IF(ISBLANK(D85),"""",IFERROR(XIRR({FILTER('Entradas y salidas'!K:K, 'Entradas y salidas'!D:D=D85, NOT(ISBLANK('Entradas y salidas'!K:K))); INDEX(FILTER('Cortes x inversión'!I:I, 'Cortes x inversión'!D:D=D85),1)}, {FILTER('Entradas y salidas'!F:F, 'Entrada"&"s y salidas'!D:D=D85, NOT(ISBLANK('Entradas y salidas'!K:K))); INDEX(FILTER('Cortes x inversión'!J:J, 'Cortes x inversión'!D:D=D85),1)}), """"))"),"")
F86: =IF(E86="COP", SUMIF('Entradas y salidas'!D:D, D86, 'Entradas y salidas'!J:J), ) | G86: =IFERROR(__xludf.DUMMYFUNCTION("IF(E86=""COP"", INDEX(FILTER('Cortes x inversión'!F:F, 'Cortes x inversión'!D:D=D86),1), )"),"") | H86: =IF(OR(F86="", G86=""),"", G86 - ABS(F86)) | I86: =IFERROR(__xludf.DUMMYFUNCTION("IF(ISBLANK(D86),"""",IFERROR(XIRR({FILTER('Entradas y salidas'!J:J, 'Entradas y salidas'!D:D=D86, NOT(ISBLANK('Entradas y salidas'!J:J))); INDEX(FILTER('Cortes x inversión'!F:F, 'Cortes x inversión'!D:D=D86),1)}, {FILTER('Entradas y salidas'!F:F, 'Entrada"&"s y salidas'!D:D=D86, NOT(ISBLANK('Entradas y salidas'!J:J))); INDEX(FILTER('Cortes x inversión'!J:J, 'Cortes x inversión'!D:D=D86),1)}), """"))"),"") | K86: =IF(E86="USD", SUMIF('Entradas y salidas'!D:D, D86, 'Entradas y salidas'!I:I), ) | L86: =IFERROR(__xludf.DUMMYFUNCTION("IF(E86=""USD"", INDEX(FILTER('Cortes x inversión'!G:G, 'Cortes x inversión'!D:D=D86),1), )"),"") | M86: =IF(OR(K86="", L86=""),"", L86 - ABS(K86)) | N86: =IFERROR(__xludf.DUMMYFUNCTION("IF(ISBLANK(D86),"""",IFERROR(XIRR({FILTER('Entradas y salidas'!I:I, 'Entradas y salidas'!D:D=D86, NOT(ISBLANK('Entradas y salidas'!I:I))); INDEX(FILTER('Cortes x inversión'!G:G, 'Cortes x inversión'!D:D=D86),1)}, {FILTER('Entradas y salidas'!F:F, 'Entrada"&"s y salidas'!D:D=D86, NOT(ISBLANK('Entradas y salidas'!I:I))); INDEX(FILTER('Cortes x inversión'!J:J, 'Cortes x inversión'!D:D=D86),1)}), """"))"),"") | P86: =IFERROR(__xludf.DUMMYFUNCTION("IF(K86="""","""", GOOGLEFINANCE(""CURRENCY:USDCOP"")) "),"") | Q86: =IFERROR(__xludf.DUMMYFUNCTION("IF(L86="""","""", GOOGLEFINANCE(""CURRENCY:USDCOP"")) "),"") | R86: =IF(K86="","", L86*P86) | S86: =IF(OR(Q86="", R86=""),"", R86 - ABS(Q86)) | T86: =IFERROR(__xludf.DUMMYFUNCTION("IF(ISBLANK(D86),"""",IFERROR(XIRR({FILTER('Entradas y salidas'!K:K, 'Entradas y salidas'!D:D=D86, NOT(ISBLANK('Entradas y salidas'!K:K))); INDEX(FILTER('Cortes x inversión'!I:I, 'Cortes x inversión'!D:D=D86),1)}, {FILTER('Entradas y salidas'!F:F, 'Entrada"&"s y salidas'!D:D=D86, NOT(ISBLANK('Entradas y salidas'!K:K))); INDEX(FILTER('Cortes x inversión'!J:J, 'Cortes x inversión'!D:D=D86),1)}), """"))"),"")
F87: =IF(E87="COP", SUMIF('Entradas y salidas'!D:D, D87, 'Entradas y salidas'!J:J), ) | G87: =IFERROR(__xludf.DUMMYFUNCTION("IF(E87=""COP"", INDEX(FILTER('Cortes x inversión'!F:F, 'Cortes x inversión'!D:D=D87),1), )"),"") | H87: =IF(OR(F87="", G87=""),"", G87 - ABS(F87)) | I87: =IFERROR(__xludf.DUMMYFUNCTION("IF(ISBLANK(D87),"""",IFERROR(XIRR({FILTER('Entradas y salidas'!J:J, 'Entradas y salidas'!D:D=D87, NOT(ISBLANK('Entradas y salidas'!J:J))); INDEX(FILTER('Cortes x inversión'!F:F, 'Cortes x inversión'!D:D=D87),1)}, {FILTER('Entradas y salidas'!F:F, 'Entrada"&"s y salidas'!D:D=D87, NOT(ISBLANK('Entradas y salidas'!J:J))); INDEX(FILTER('Cortes x inversión'!J:J, 'Cortes x inversión'!D:D=D87),1)}), """"))"),"") | K87: =IF(E87="USD", SUMIF('Entradas y salidas'!D:D, D87, 'Entradas y salidas'!I:I), ) | L87: =IFERROR(__xludf.DUMMYFUNCTION("IF(E87=""USD"", INDEX(FILTER('Cortes x inversión'!G:G, 'Cortes x inversión'!D:D=D87),1), )"),"") | M87: =IF(OR(K87="", L87=""),"", L87 - ABS(K87)) | N87: =IFERROR(__xludf.DUMMYFUNCTION("IF(ISBLANK(D87),"""",IFERROR(XIRR({FILTER('Entradas y salidas'!I:I, 'Entradas y salidas'!D:D=D87, NOT(ISBLANK('Entradas y salidas'!I:I))); INDEX(FILTER('Cortes x inversión'!G:G, 'Cortes x inversión'!D:D=D87),1)}, {FILTER('Entradas y salidas'!F:F, 'Entrada"&"s y salidas'!D:D=D87, NOT(ISBLANK('Entradas y salidas'!I:I))); INDEX(FILTER('Cortes x inversión'!J:J, 'Cortes x inversión'!D:D=D87),1)}), """"))"),"") | P87: =IFERROR(__xludf.DUMMYFUNCTION("IF(K87="""","""", GOOGLEFINANCE(""CURRENCY:USDCOP"")) "),"") | Q87: =IFERROR(__xludf.DUMMYFUNCTION("IF(L87="""","""", GOOGLEFINANCE(""CURRENCY:USDCOP"")) "),"") | R87: =IF(K87="","", L87*P87) | S87: =IF(OR(Q87="", R87=""),"", R87 - ABS(Q87)) | T87: =IFERROR(__xludf.DUMMYFUNCTION("IF(ISBLANK(D87),"""",IFERROR(XIRR({FILTER('Entradas y salidas'!K:K, 'Entradas y salidas'!D:D=D87, NOT(ISBLANK('Entradas y salidas'!K:K))); INDEX(FILTER('Cortes x inversión'!I:I, 'Cortes x inversión'!D:D=D87),1)}, {FILTER('Entradas y salidas'!F:F, 'Entrada"&"s y salidas'!D:D=D87, NOT(ISBLANK('Entradas y salidas'!K:K))); INDEX(FILTER('Cortes x inversión'!J:J, 'Cortes x inversión'!D:D=D87),1)}), """"))"),"")
F88: =IF(E88="COP", SUMIF('Entradas y salidas'!D:D, D88, 'Entradas y salidas'!J:J), ) | G88: =IFERROR(__xludf.DUMMYFUNCTION("IF(E88=""COP"", INDEX(FILTER('Cortes x inversión'!F:F, 'Cortes x inversión'!D:D=D88),1), )"),"") | H88: =IF(OR(F88="", G88=""),"", G88 - ABS(F88)) | I88: =IFERROR(__xludf.DUMMYFUNCTION("IF(ISBLANK(D88),"""",IFERROR(XIRR({FILTER('Entradas y salidas'!J:J, 'Entradas y salidas'!D:D=D88, NOT(ISBLANK('Entradas y salidas'!J:J))); INDEX(FILTER('Cortes x inversión'!F:F, 'Cortes x inversión'!D:D=D88),1)}, {FILTER('Entradas y salidas'!F:F, 'Entrada"&"s y salidas'!D:D=D88, NOT(ISBLANK('Entradas y salidas'!J:J))); INDEX(FILTER('Cortes x inversión'!J:J, 'Cortes x inversión'!D:D=D88),1)}), """"))"),"") | K88: =IF(E88="USD", SUMIF('Entradas y salidas'!D:D, D88, 'Entradas y salidas'!I:I), ) | L88: =IFERROR(__xludf.DUMMYFUNCTION("IF(E88=""USD"", INDEX(FILTER('Cortes x inversión'!G:G, 'Cortes x inversión'!D:D=D88),1), )"),"") | M88: =IF(OR(K88="", L88=""),"", L88 - ABS(K88)) | N88: =IFERROR(__xludf.DUMMYFUNCTION("IF(ISBLANK(D88),"""",IFERROR(XIRR({FILTER('Entradas y salidas'!I:I, 'Entradas y salidas'!D:D=D88, NOT(ISBLANK('Entradas y salidas'!I:I))); INDEX(FILTER('Cortes x inversión'!G:G, 'Cortes x inversión'!D:D=D88),1)}, {FILTER('Entradas y salidas'!F:F, 'Entrada"&"s y salidas'!D:D=D88, NOT(ISBLANK('Entradas y salidas'!I:I))); INDEX(FILTER('Cortes x inversión'!J:J, 'Cortes x inversión'!D:D=D88),1)}), """"))"),"") | P88: =IFERROR(__xludf.DUMMYFUNCTION("IF(K88="""","""", GOOGLEFINANCE(""CURRENCY:USDCOP"")) "),"") | Q88: =IFERROR(__xludf.DUMMYFUNCTION("IF(L88="""","""", GOOGLEFINANCE(""CURRENCY:USDCOP"")) "),"") | R88: =IF(K88="","", L88*P88) | S88: =IF(OR(Q88="", R88=""),"", R88 - ABS(Q88)) | T88: =IFERROR(__xludf.DUMMYFUNCTION("IF(ISBLANK(D88),"""",IFERROR(XIRR({FILTER('Entradas y salidas'!K:K, 'Entradas y salidas'!D:D=D88, NOT(ISBLANK('Entradas y salidas'!K:K))); INDEX(FILTER('Cortes x inversión'!I:I, 'Cortes x inversión'!D:D=D88),1)}, {FILTER('Entradas y salidas'!F:F, 'Entrada"&"s y salidas'!D:D=D88, NOT(ISBLANK('Entradas y salidas'!K:K))); INDEX(FILTER('Cortes x inversión'!J:J, 'Cortes x inversión'!D:D=D88),1)}), """"))"),"")
F89: =IF(E89="COP", SUMIF('Entradas y salidas'!D:D, D89, 'Entradas y salidas'!J:J), ) | G89: =IFERROR(__xludf.DUMMYFUNCTION("IF(E89=""COP"", INDEX(FILTER('Cortes x inversión'!F:F, 'Cortes x inversión'!D:D=D89),1), )"),"") | H89: =IF(OR(F89="", G89=""),"", G89 - ABS(F89)) | I89: =IFERROR(__xludf.DUMMYFUNCTION("IF(ISBLANK(D89),"""",IFERROR(XIRR({FILTER('Entradas y salidas'!J:J, 'Entradas y salidas'!D:D=D89, NOT(ISBLANK('Entradas y salidas'!J:J))); INDEX(FILTER('Cortes x inversión'!F:F, 'Cortes x inversión'!D:D=D89),1)}, {FILTER('Entradas y salidas'!F:F, 'Entrada"&"s y salidas'!D:D=D89, NOT(ISBLANK('Entradas y salidas'!J:J))); INDEX(FILTER('Cortes x inversión'!J:J, 'Cortes x inversión'!D:D=D89),1)}), """"))"),"") | K89: =IF(E89="USD", SUMIF('Entradas y salidas'!D:D, D89, 'Entradas y salidas'!I:I), ) | L89: =IFERROR(__xludf.DUMMYFUNCTION("IF(E89=""USD"", INDEX(FILTER('Cortes x inversión'!G:G, 'Cortes x inversión'!D:D=D89),1), )"),"") | M89: =IF(OR(K89="", L89=""),"", L89 - ABS(K89)) | N89: =IFERROR(__xludf.DUMMYFUNCTION("IF(ISBLANK(D89),"""",IFERROR(XIRR({FILTER('Entradas y salidas'!I:I, 'Entradas y salidas'!D:D=D89, NOT(ISBLANK('Entradas y salidas'!I:I))); INDEX(FILTER('Cortes x inversión'!G:G, 'Cortes x inversión'!D:D=D89),1)}, {FILTER('Entradas y salidas'!F:F, 'Entrada"&"s y salidas'!D:D=D89, NOT(ISBLANK('Entradas y salidas'!I:I))); INDEX(FILTER('Cortes x inversión'!J:J, 'Cortes x inversión'!D:D=D89),1)}), """"))"),"") | P89: =IFERROR(__xludf.DUMMYFUNCTION("IF(K89="""","""", GOOGLEFINANCE(""CURRENCY:USDCOP"")) "),"") | Q89: =IFERROR(__xludf.DUMMYFUNCTION("IF(L89="""","""", GOOGLEFINANCE(""CURRENCY:USDCOP"")) "),"") | R89: =IF(K89="","", L89*P89) | S89: =IF(OR(Q89="", R89=""),"", R89 - ABS(Q89)) | T89: =IFERROR(__xludf.DUMMYFUNCTION("IF(ISBLANK(D89),"""",IFERROR(XIRR({FILTER('Entradas y salidas'!K:K, 'Entradas y salidas'!D:D=D89, NOT(ISBLANK('Entradas y salidas'!K:K))); INDEX(FILTER('Cortes x inversión'!I:I, 'Cortes x inversión'!D:D=D89),1)}, {FILTER('Entradas y salidas'!F:F, 'Entrada"&"s y salidas'!D:D=D89, NOT(ISBLANK('Entradas y salidas'!K:K))); INDEX(FILTER('Cortes x inversión'!J:J, 'Cortes x inversión'!D:D=D89),1)}), """"))"),"")
F90: =IF(E90="COP", SUMIF('Entradas y salidas'!D:D, D90, 'Entradas y salidas'!J:J), ) | G90: =IFERROR(__xludf.DUMMYFUNCTION("IF(E90=""COP"", INDEX(FILTER('Cortes x inversión'!F:F, 'Cortes x inversión'!D:D=D90),1), )"),"") | H90: =IF(OR(F90="", G90=""),"", G90 - ABS(F90)) | I90: =IFERROR(__xludf.DUMMYFUNCTION("IF(ISBLANK(D90),"""",IFERROR(XIRR({FILTER('Entradas y salidas'!J:J, 'Entradas y salidas'!D:D=D90, NOT(ISBLANK('Entradas y salidas'!J:J))); INDEX(FILTER('Cortes x inversión'!F:F, 'Cortes x inversión'!D:D=D90),1)}, {FILTER('Entradas y salidas'!F:F, 'Entrada"&"s y salidas'!D:D=D90, NOT(ISBLANK('Entradas y salidas'!J:J))); INDEX(FILTER('Cortes x inversión'!J:J, 'Cortes x inversión'!D:D=D90),1)}), """"))"),"") | K90: =IF(E90="USD", SUMIF('Entradas y salidas'!D:D, D90, 'Entradas y salidas'!I:I), ) | L90: =IFERROR(__xludf.DUMMYFUNCTION("IF(E90=""USD"", INDEX(FILTER('Cortes x inversión'!G:G, 'Cortes x inversión'!D:D=D90),1), )"),"") | M90: =IF(OR(K90="", L90=""),"", L90 - ABS(K90)) | N90: =IFERROR(__xludf.DUMMYFUNCTION("IF(ISBLANK(D90),"""",IFERROR(XIRR({FILTER('Entradas y salidas'!I:I, 'Entradas y salidas'!D:D=D90, NOT(ISBLANK('Entradas y salidas'!I:I))); INDEX(FILTER('Cortes x inversión'!G:G, 'Cortes x inversión'!D:D=D90),1)}, {FILTER('Entradas y salidas'!F:F, 'Entrada"&"s y salidas'!D:D=D90, NOT(ISBLANK('Entradas y salidas'!I:I))); INDEX(FILTER('Cortes x inversión'!J:J, 'Cortes x inversión'!D:D=D90),1)}), """"))"),"") | P90: =IFERROR(__xludf.DUMMYFUNCTION("IF(K90="""","""", GOOGLEFINANCE(""CURRENCY:USDCOP"")) "),"") | Q90: =IFERROR(__xludf.DUMMYFUNCTION("IF(L90="""","""", GOOGLEFINANCE(""CURRENCY:USDCOP"")) "),"") | R90: =IF(K90="","", L90*P90) | S90: =IF(OR(Q90="", R90=""),"", R90 - ABS(Q90)) | T90: =IFERROR(__xludf.DUMMYFUNCTION("IF(ISBLANK(D90),"""",IFERROR(XIRR({FILTER('Entradas y salidas'!K:K, 'Entradas y salidas'!D:D=D90, NOT(ISBLANK('Entradas y salidas'!K:K))); INDEX(FILTER('Cortes x inversión'!I:I, 'Cortes x inversión'!D:D=D90),1)}, {FILTER('Entradas y salidas'!F:F, 'Entrada"&"s y salidas'!D:D=D90, NOT(ISBLANK('Entradas y salidas'!K:K))); INDEX(FILTER('Cortes x inversión'!J:J, 'Cortes x inversión'!D:D=D90),1)}), """"))"),"")
F91: =IF(E91="COP", SUMIF('Entradas y salidas'!D:D, D91, 'Entradas y salidas'!J:J), ) | G91: =IFERROR(__xludf.DUMMYFUNCTION("IF(E91=""COP"", INDEX(FILTER('Cortes x inversión'!F:F, 'Cortes x inversión'!D:D=D91),1), )"),"") | H91: =IF(OR(F91="", G91=""),"", G91 - ABS(F91)) | I91: =IFERROR(__xludf.DUMMYFUNCTION("IF(ISBLANK(D91),"""",IFERROR(XIRR({FILTER('Entradas y salidas'!J:J, 'Entradas y salidas'!D:D=D91, NOT(ISBLANK('Entradas y salidas'!J:J))); INDEX(FILTER('Cortes x inversión'!F:F, 'Cortes x inversión'!D:D=D91),1)}, {FILTER('Entradas y salidas'!F:F, 'Entrada"&"s y salidas'!D:D=D91, NOT(ISBLANK('Entradas y salidas'!J:J))); INDEX(FILTER('Cortes x inversión'!J:J, 'Cortes x inversión'!D:D=D91),1)}), """"))"),"") | K91: =IF(E91="USD", SUMIF('Entradas y salidas'!D:D, D91, 'Entradas y salidas'!I:I), ) | L91: =IFERROR(__xludf.DUMMYFUNCTION("IF(E91=""USD"", INDEX(FILTER('Cortes x inversión'!G:G, 'Cortes x inversión'!D:D=D91),1), )"),"") | M91: =IF(OR(K91="", L91=""),"", L91 - ABS(K91)) | N91: =IFERROR(__xludf.DUMMYFUNCTION("IF(ISBLANK(D91),"""",IFERROR(XIRR({FILTER('Entradas y salidas'!I:I, 'Entradas y salidas'!D:D=D91, NOT(ISBLANK('Entradas y salidas'!I:I))); INDEX(FILTER('Cortes x inversión'!G:G, 'Cortes x inversión'!D:D=D91),1)}, {FILTER('Entradas y salidas'!F:F, 'Entrada"&"s y salidas'!D:D=D91, NOT(ISBLANK('Entradas y salidas'!I:I))); INDEX(FILTER('Cortes x inversión'!J:J, 'Cortes x inversión'!D:D=D91),1)}), """"))"),"") | P91: =IFERROR(__xludf.DUMMYFUNCTION("IF(K91="""","""", GOOGLEFINANCE(""CURRENCY:USDCOP"")) "),"") | Q91: =IFERROR(__xludf.DUMMYFUNCTION("IF(L91="""","""", GOOGLEFINANCE(""CURRENCY:USDCOP"")) "),"") | R91: =IF(K91="","", L91*P91) | S91: =IF(OR(Q91="", R91=""),"", R91 - ABS(Q91)) | T91: =IFERROR(__xludf.DUMMYFUNCTION("IF(ISBLANK(D91),"""",IFERROR(XIRR({FILTER('Entradas y salidas'!K:K, 'Entradas y salidas'!D:D=D91, NOT(ISBLANK('Entradas y salidas'!K:K))); INDEX(FILTER('Cortes x inversión'!I:I, 'Cortes x inversión'!D:D=D91),1)}, {FILTER('Entradas y salidas'!F:F, 'Entrada"&"s y salidas'!D:D=D91, NOT(ISBLANK('Entradas y salidas'!K:K))); INDEX(FILTER('Cortes x inversión'!J:J, 'Cortes x inversión'!D:D=D91),1)}), """"))"),"")
F92: =IF(E92="COP", SUMIF('Entradas y salidas'!D:D, D92, 'Entradas y salidas'!J:J), ) | G92: =IFERROR(__xludf.DUMMYFUNCTION("IF(E92=""COP"", INDEX(FILTER('Cortes x inversión'!F:F, 'Cortes x inversión'!D:D=D92),1), )"),"") | H92: =IF(OR(F92="", G92=""),"", G92 - ABS(F92)) | I92: =IFERROR(__xludf.DUMMYFUNCTION("IF(ISBLANK(D92),"""",IFERROR(XIRR({FILTER('Entradas y salidas'!J:J, 'Entradas y salidas'!D:D=D92, NOT(ISBLANK('Entradas y salidas'!J:J))); INDEX(FILTER('Cortes x inversión'!F:F, 'Cortes x inversión'!D:D=D92),1)}, {FILTER('Entradas y salidas'!F:F, 'Entrada"&"s y salidas'!D:D=D92, NOT(ISBLANK('Entradas y salidas'!J:J))); INDEX(FILTER('Cortes x inversión'!J:J, 'Cortes x inversión'!D:D=D92),1)}), """"))"),"") | K92: =IF(E92="USD", SUMIF('Entradas y salidas'!D:D, D92, 'Entradas y salidas'!I:I), ) | L92: =IFERROR(__xludf.DUMMYFUNCTION("IF(E92=""USD"", INDEX(FILTER('Cortes x inversión'!G:G, 'Cortes x inversión'!D:D=D92),1), )"),"") | M92: =IF(OR(K92="", L92=""),"", L92 - ABS(K92)) | N92: =IFERROR(__xludf.DUMMYFUNCTION("IF(ISBLANK(D92),"""",IFERROR(XIRR({FILTER('Entradas y salidas'!I:I, 'Entradas y salidas'!D:D=D92, NOT(ISBLANK('Entradas y salidas'!I:I))); INDEX(FILTER('Cortes x inversión'!G:G, 'Cortes x inversión'!D:D=D92),1)}, {FILTER('Entradas y salidas'!F:F, 'Entrada"&"s y salidas'!D:D=D92, NOT(ISBLANK('Entradas y salidas'!I:I))); INDEX(FILTER('Cortes x inversión'!J:J, 'Cortes x inversión'!D:D=D92),1)}), """"))"),"") | P92: =IFERROR(__xludf.DUMMYFUNCTION("IF(K92="""","""", GOOGLEFINANCE(""CURRENCY:USDCOP"")) "),"") | Q92: =IFERROR(__xludf.DUMMYFUNCTION("IF(L92="""","""", GOOGLEFINANCE(""CURRENCY:USDCOP"")) "),"") | R92: =IF(K92="","", L92*P92) | S92: =IF(OR(Q92="", R92=""),"", R92 - ABS(Q92)) | T92: =IFERROR(__xludf.DUMMYFUNCTION("IF(ISBLANK(D92),"""",IFERROR(XIRR({FILTER('Entradas y salidas'!K:K, 'Entradas y salidas'!D:D=D92, NOT(ISBLANK('Entradas y salidas'!K:K))); INDEX(FILTER('Cortes x inversión'!I:I, 'Cortes x inversión'!D:D=D92),1)}, {FILTER('Entradas y salidas'!F:F, 'Entrada"&"s y salidas'!D:D=D92, NOT(ISBLANK('Entradas y salidas'!K:K))); INDEX(FILTER('Cortes x inversión'!J:J, 'Cortes x inversión'!D:D=D92),1)}), """"))"),"")
F93: =IF(E93="COP", SUMIF('Entradas y salidas'!D:D, D93, 'Entradas y salidas'!J:J), ) | G93: =IFERROR(__xludf.DUMMYFUNCTION("IF(E93=""COP"", INDEX(FILTER('Cortes x inversión'!F:F, 'Cortes x inversión'!D:D=D93),1), )"),"") | H93: =IF(OR(F93="", G93=""),"", G93 - ABS(F93)) | I93: =IFERROR(__xludf.DUMMYFUNCTION("IF(ISBLANK(D93),"""",IFERROR(XIRR({FILTER('Entradas y salidas'!J:J, 'Entradas y salidas'!D:D=D93, NOT(ISBLANK('Entradas y salidas'!J:J))); INDEX(FILTER('Cortes x inversión'!F:F, 'Cortes x inversión'!D:D=D93),1)}, {FILTER('Entradas y salidas'!F:F, 'Entrada"&"s y salidas'!D:D=D93, NOT(ISBLANK('Entradas y salidas'!J:J))); INDEX(FILTER('Cortes x inversión'!J:J, 'Cortes x inversión'!D:D=D93),1)}), """"))"),"") | K93: =IF(E93="USD", SUMIF('Entradas y salidas'!D:D, D93, 'Entradas y salidas'!I:I), ) | L93: =IFERROR(__xludf.DUMMYFUNCTION("IF(E93=""USD"", INDEX(FILTER('Cortes x inversión'!G:G, 'Cortes x inversión'!D:D=D93),1), )"),"") | M93: =IF(OR(K93="", L93=""),"", L93 - ABS(K93)) | N93: =IFERROR(__xludf.DUMMYFUNCTION("IF(ISBLANK(D93),"""",IFERROR(XIRR({FILTER('Entradas y salidas'!I:I, 'Entradas y salidas'!D:D=D93, NOT(ISBLANK('Entradas y salidas'!I:I))); INDEX(FILTER('Cortes x inversión'!G:G, 'Cortes x inversión'!D:D=D93),1)}, {FILTER('Entradas y salidas'!F:F, 'Entrada"&"s y salidas'!D:D=D93, NOT(ISBLANK('Entradas y salidas'!I:I))); INDEX(FILTER('Cortes x inversión'!J:J, 'Cortes x inversión'!D:D=D93),1)}), """"))"),"") | P93: =IFERROR(__xludf.DUMMYFUNCTION("IF(K93="""","""", GOOGLEFINANCE(""CURRENCY:USDCOP"")) "),"") | Q93: =IFERROR(__xludf.DUMMYFUNCTION("IF(L93="""","""", GOOGLEFINANCE(""CURRENCY:USDCOP"")) "),"") | R93: =IF(K93="","", L93*P93) | S93: =IF(OR(Q93="", R93=""),"", R93 - ABS(Q93)) | T93: =IFERROR(__xludf.DUMMYFUNCTION("IF(ISBLANK(D93),"""",IFERROR(XIRR({FILTER('Entradas y salidas'!K:K, 'Entradas y salidas'!D:D=D93, NOT(ISBLANK('Entradas y salidas'!K:K))); INDEX(FILTER('Cortes x inversión'!I:I, 'Cortes x inversión'!D:D=D93),1)}, {FILTER('Entradas y salidas'!F:F, 'Entrada"&"s y salidas'!D:D=D93, NOT(ISBLANK('Entradas y salidas'!K:K))); INDEX(FILTER('Cortes x inversión'!J:J, 'Cortes x inversión'!D:D=D93),1)}), """"))"),"")
